Workbook

Sheet Read me
A1: CDS-IGRL | Investment model | B1: Basis / limitations
A2: Units | B2: NGN billions unless stated. Nominal; no automatic inflation, debt, refinancing or terminal proceeds.
A3: Status | B3: ILLUSTRATIVE, NOT INVESTMENT VALIDATION. No executed guarantee, concession or tariff evidence verified.
A4: Source | B4: Investors Pitch Deck.docx, dated 15 October 2026; references below use its numbered sections.
A5: How to edit | B5: Blue font = editable input; black = formula; green = cross-sheet formula. Inputs, Streams and Funding are input tabs.
A6: Cases | B6: Headline: 35B each month; Ramp: M1–5 zero, M6–8 15B, M9–11 25B, M12 onward 35B. Downside: 60% realization and 3-month delay, both illustrative.
A7: Boundary convention | B7: Source M6–9/M9–12/M12–18 bands overlap. Non-overlapping M6–8/M9–11/M12+ adopted, not independently sourced.
A8: Funding conflict | B8: Source says first 5B and second 5B (§4); second 25B (§8); first25B+second25B (§10). Adopt illustrative 25B M0 +25B M9, not a resolved contractual schedule.
A9: Headline comparison | B9: Headline alone adopts full 50B funding M0 for like-for-like audit of source 420B proceeds. Ramp and Downside use staged funding.
A10: Revenue allocation | B10: Original seven bucket targets retained. Thirteen mutually exclusive substream allocations are illustrative, not evidence supporting 35B/month.
A11: Bottom-up | B11: Quantity × fee × events/year /1e9. Missing frequencies assumed annual and flagged. Unpriced streams =0, not invented revenue. Combined licensing/pattern quantity assigned to licensing only to avoid double count.
A12: VAT / WHT | B12: Default target revenue is VAT-exclusive; editable VAT-inclusive switch and rate. VAT is not revenue. WHT is not modeled as an expense: creditability, timing and treatment require tax advice.
... A25: Source claims | B25: 840% is gross proceeds/capital, not net ROI (740% at headline). Source ~68% IRR is not reproduced; 8.4x is MOIC, not DSCR.

Sheet Inputs
A1: Driver | B1: Value | C1: Units / source / assumption
A2: Months per year | B2: 12 | C2: Calendar convention
A3: Model months | B3: 120 | C3: Source §3: ten years
A4: Government share | B4: 0.4 | C4: Source §4/6
A5: Investor share | B5: 0.1 | C5: Source §4/6
A6: CDS legal share | B6: 0.5 | C6: Source §4/6; includes reserve and distribution
A7: OPEX reserve share | B7: 0.2 | C7: Source §4; reserve only, not actual cost
A8: CDS sweep share | B8: 0.3 | C8: Source §4; illustrative actual distribution policy
A9: VAT-inclusive target switch | B9: 0 | C9: ASSUMPTION: 0 excludes VAT from target, 1 divides target by 1+VAT rate
A10: VAT rate assumption | B10: 0.075 | C10: ILLUSTRATIVE tax parameter, not legal opinion
A11: Cash income tax rate | B11: 0.3 | C11: ILLUSTRATIVE positive monthly EBIT tax; no loss relief
A12: Staff count | B12: 800 | C12: Source §5 recruitment target; assumed fully staffed from M1
A13: Monthly cost per employee NGN | B13: 500000 | C13: UNPROVIDED assumption, fully loaded
... A35: One | B35: 1 | C35: Formula constant

Sheet Funding
A1: Use of funds | B1: B NGN | C1: Capitalized flag | D1: Source / modeling treatment
A2: Equipment | B2: 25 | C2: 1 | D2: Source §5 amount; accounting treatment illustrative
A3: Infrastructure | B3: 10 | C3: 1 | D3: Source §5 amount; accounting treatment illustrative
A4: Technology | B4: 8 | C4: 1 | D4: Source §5 amount; accounting treatment illustrative
A5: Human capital | B5: 4 | C5: 0 | D5: Source §5 amount; accounting treatment illustrative
A6: Compliance | B6: 3 | C6: 0 | D6: Source §5 amount; accounting treatment illustrative
A7: Total | B7: =SUM(B2:B6) -> 50 | C7: =SUMPRODUCT(B2:B6,C2:C6) -> 43 | D7: Capitalized total in C7
A8: Launch expense | B8: =B7-C7 -> 7

Sheet Streams
A1: Non-overlapping stream | B1: Original source bucket | C1: Bucket monthly B | D1: Illustrative allocation % | E1: Target B/month | F1: Quantity | G1: Fee NGN | H1: Events/year | I1: Bottom-up annual B | J1: Bottom-up monthly B | K1: Basis / missing evidence
A2: Pumps | B2: Oil & gas | C2: 12 | D2: 0.66666667 | E2: =C2*D2 -> 8 | F2: 20000 | G2: 100000 | H2: 4 | I2: =F2*G2*H2/Inputs!$B$32 -> 8 | J2: =I2/Inputs!$B$2 -> 0.66666667 | K2: §2: quarterly frequency explicit; allocation splits illustrative
A3: Tankers | B3: Oil & gas | C3: 12 | D3: 0.25 | E3: =C3*D3 -> 3 | F3: 10000 | G3: 200000 | H3: 1 | I3: =F3*G3*H3/Inputs!$B$32 -> 2 | J3: =I3/Inputs!$B$2 -> 0.16666667 | K3: §2: frequency UNKNOWN; annual assumed; allocation splits illustrative
A4: Depots | B4: Oil & gas | C4: 12 | D4: 0.083333333 | E4: =C4*D4 -> 1 | F4: 200 | G4: 5000000 | H4: 1 | I4: =F4*G4*H4/Inputs!$B$32 -> 1 | J4: =I4/Inputs!$B$2 -> 0.083333333 | K4: §2: frequency UNKNOWN; annual assumed; allocation splits illustrative
A5: Retail scales | B5: Retail/FMCG | C5: 6 | D5: 0.75 | E5: =C5*D5 -> 4.5 | F5: 150000 | G5: 40000 | H5: 1 | I5: =F5*G5*H5/Inputs!$B$32 -> 6 | J5: =I5/Inputs!$B$2 -> 0.5 | K5: §2: annual explicit; allocation splits illustrative
A6: Scanners | B6: Retail/FMCG | C6: 6 | D6: 0.25 | E6: =C6*D6 -> 1.5 | F6: 20000 | G6: 100000 | H6: 1 | I6: =F6*G6*H6/Inputs!$B$32 -> 2 | J6: =I6/Inputs!$B$2 -> 0.16666667 | K6: §2: frequency UNKNOWN; annual assumed; allocation splits illustrative
A7: Electricity meters | B7: Power/utilities | C7: 5 | D7: 1 | E7: =C7*D7 -> 5 | F7: 500000 | G7: 10000 | H7: 1 | I7: =F7*G7*H7/Inputs!$B$32 -> 5 | J7: =I7/Inputs!$B$2 -> 0.41666667 | K7: §2: annual explicit; allocation splits illustrative
A8: Telecom billing | B8: Telecom/banking/ICT | C8: 4 | D8: 0.625 | E8: =C8*D8 -> 2.5 | F8: 0 | G8: 0 | H8: 1 | I8: =F8*G8*H8/Inputs!$B$32 -> 0 | J8: =I8/Inputs!$B$2 -> 0 | K8: §2: no volume/fee; zero bottom-up; allocation splits illustrative
A9: Banking ICT | B9: Telecom/banking/ICT | C9: 4 | D9: 0.375 | E9: =C9*D9 -> 1.5 | F9: 0 | G9: 0 | H9: 1 | I9: =F9*G9*H9/Inputs!$B$32 -> 0 | J9: =I9/Inputs!$B$2 -> 0 | K9: §2: no volume/fee; zero bottom-up; allocation splits illustrative
A10: Manufacturing weighbridges | B10: Manufacturing | C10: 3 | D10: 1 | E10: =C10*D10 -> 3 | F10: 2000 | G10: 1500000 | H10: 1 | I10: =F10*G10*H10/Inputs!$B$32 -> 3 | J10: =I10/Inputs!$B$2 -> 0.25 | K10: §2: annual explicit; allocation splits illustrative
A11: Aviation | B11: Aviation/marine/bulk | C11: 2 | D11: 0.5 | E11: =C11*D11 -> 1 | F11: 0 | G11: 0 | H11: 1 | I11: =F11*G11*H11/Inputs!$B$32 -> 0 | J11: =I11/Inputs!$B$2 -> 0 | K11: §2: no volume/fee; zero bottom-up; airport bowsers only, excludes road tankers; allocation splits illustrative
A12: Marine | B12: Aviation/marine/bulk | C12: 2 | D12: 0.5 | E12: =C12*D12 -> 1 | F12: 0 | G12: 0 | H12: 1 | I12: =F12*G12*H12/Inputs!$B$32 -> 0 | J12: =I12/Inputs!$B$2 -> 0 | K12: §2: no volume/fee; zero bottom-up; ships/bulk marine only; allocation splits illustrative
A13: Licensing | B13: Licensing/pattern | C13: 3 | D13: 0.66666667 | E13: =C13*D13 -> 2 | F13: 5000 | G13: 600000 | H13: 1 | I13: =F13*G13*H13/Inputs!$B$32 -> 3 | J13: =I13/Inputs!$B$2 -> 0.25 | K13: §2 combined5000 assigned here only; frequency UNKNOWN annual assumed; allocation splits illustrative
A14: Pattern approval | B14: Licensing/pattern | C14: 3 | D14: 0.33333333 | E14: =C14*D14 -> 1 | F14: 0 | G14: 0 | H14: 1 | I14: =F14*G14*H14/Inputs!$B$32 -> 0 | J14: =I14/Inputs!$B$2 -> 0 | K14: §2 combined bucket; no separate priced volume; zero avoids double count; allocation splits illustrative
A15: TOTAL | E15: =SUM(E2:E14) -> 35 | I15: =SUM(I2:I14) -> 30 | J15: =SUM(J2:J14) -> 2.5
A17: Bottom-up / target | E17: =J15/E15 -> 0.071428571
A18: Unbridged target B/month | E18: =E15-J15 -> 32.5
A21: Oil & gas | B21: Allocation check =0 | E21: =SUMIF(B2:B14,A21,D2:D14)-Inputs!$B$35 -> 0
A22: Retail/FMCG | B22: Allocation check =0 | E22: =SUMIF(B2:B14,A22,D2:D14)-Inputs!$B$35 -> 0
A23: Power/utilities | B23: Allocation check =0 | E23: =SUMIF(B2:B14,A23,D2:D14)-Inputs!$B$35 -> 0
A24: Telecom/banking/ICT | B24: Allocation check =0 | E24: =SUMIF(B2:B14,A24,D2:D14)-Inputs!$B$35 -> 0
A25: Manufacturing | B25: Allocation check =0 | E25: =SUMIF(B2:B14,A25,D2:D14)-Inputs!$B$35 -> 0
A26: Aviation/marine/bulk | B26: Allocation check =0 | E26: =SUMIF(B2:B14,A26,D2:D14)-Inputs!$B$35 -> 0
A27: Licensing/pattern | B27: Allocation check =0 | E27: =SUMIF(B2:B14,A27,D2:D14)-Inputs!$B$35 -> 0

Sheet Headline
A1: Month index | B1: =Inputs!$B$34 -> 0 | C1: =B1+Inputs!$B$35 -> 1 | D1: =C1+Inputs!$B$35 -> 2 | E1: =D1+Inputs!$B$35 -> 3 | F1: =E1+Inputs!$B$35 -> 4 | G1: =F1+Inputs!$B$35 -> 5 | H1: =G1+Inputs!$B$35 -> 6 | I1: =H1+Inputs!$B$35 -> 7 | J1: =I1+Inputs!$B$35 -> 8 | ... DR1: =DQ1+Inputs!$B$35 -> 120
A2: Model year | B2: =ROUNDUP(B$1/Inputs!$B$2,Inputs!$B$34) -> 0 | C2: =ROUNDUP(C$1/Inputs!$B$2,Inputs!$B$34) -> 1 | D2: =ROUNDUP(D$1/Inputs!$B$2,Inputs!$B$34) -> 1 | E2: =ROUNDUP(E$1/Inputs!$B$2,Inputs!$B$34) -> 1 | F2: =ROUNDUP(F$1/Inputs!$B$2,Inputs!$B$34) -> 1 | G2: =ROUNDUP(G$1/Inputs!$B$2,Inputs!$B$34) -> 1 | H2: =ROUNDUP(H$1/Inputs!$B$2,Inputs!$B$34) -> 1 | I2: =ROUNDUP(I$1/Inputs!$B$2,Inputs!$B$34) -> 1 | ... DR2: =ROUNDUP(DR$1/Inputs!$B$2,Inputs!$B$34) -> 10
A3: Case target before VAT B | B3: =IF(B$1=Inputs!$B$34,Inputs!$B$34,Streams!$E$15) -> 0 | C3: =IF(C$1=Inputs!$B$34,Inputs!$B$34,Streams!$E$15) -> 35 | D3: =IF(D$1=Inputs!$B$34,Inputs!$B$34,Streams!$E$15) -> 35 | E3: =IF(E$1=Inputs!$B$34,Inputs!$B$34,Streams!$E$15) -> 35 | F3: =IF(F$1=Inputs!$B$34,Inputs!$B$34,Streams!$E$15) -> 35 | G3: =IF(G$1=Inputs!$B$34,Inputs!$B$34,Streams!$E$15) -> 35 | H3: =IF(H$1=Inputs!$B$34,Inputs!$B$34,Streams!$E$15) -> 35 | I3: =IF(I$1=Inputs!$B$34,Inputs!$B$34,Streams!$E$15) -> 35 | ... DR3: =IF(DR$1=Inputs!$B$34,Inputs!$B$34,Streams!$E$15) -> 35
A4: Revenue base excluding VAT | B4: =B3/(Inputs!$B$35+Inputs!$B$9*Inputs!$B$10) -> 0 | C4: =C3/(Inputs!$B$35+Inputs!$B$9*Inputs!$B$10) -> 35 | D4: =D3/(Inputs!$B$35+Inputs!$B$9*Inputs!$B$10) -> 35 | E4: =E3/(Inputs!$B$35+Inputs!$B$9*Inputs!$B$10) -> 35 | F4: =F3/(Inputs!$B$35+Inputs!$B$9*Inputs!$B$10) -> 35 | G4: =G3/(Inputs!$B$35+Inputs!$B$9*Inputs!$B$10) -> 35 | H4: =H3/(Inputs!$B$35+Inputs!$B$9*Inputs!$B$10) -> 35 | I4: =I3/(Inputs!$B$35+Inputs!$B$9*Inputs!$B$10) -> 35 | ... DR4: =DR3/(Inputs!$B$35+Inputs!$B$9*Inputs!$B$10) -> 35
A5: VAT excluded from base (informational) | B5: =B3-B4 -> 0 | C5: =C3-C4 -> 0 | D5: =D3-D4 -> 0 | E5: =E3-E4 -> 0 | F5: =F3-F4 -> 0 | G5: =G3-G4 -> 0 | H5: =H3-H4 -> 0 | I5: =I3-I4 -> 0 | ... DR5: =DR3-DR4 -> 0
A6: Pumps revenue | B6: =B4*Streams!$E$2/Streams!$E$15 -> 0 | C6: =C4*Streams!$E$2/Streams!$E$15 -> 8 | D6: =D4*Streams!$E$2/Streams!$E$15 -> 8 | E6: =E4*Streams!$E$2/Streams!$E$15 -> 8 | F6: =F4*Streams!$E$2/Streams!$E$15 -> 8 | G6: =G4*Streams!$E$2/Streams!$E$15 -> 8 | H6: =H4*Streams!$E$2/Streams!$E$15 -> 8 | I6: =I4*Streams!$E$2/Streams!$E$15 -> 8 | ... DR6: =DR4*Streams!$E$2/Streams!$E$15 -> 8
A7: Tankers revenue | B7: =B4*Streams!$E$3/Streams!$E$15 -> 0 | C7: =C4*Streams!$E$3/Streams!$E$15 -> 3 | D7: =D4*Streams!$E$3/Streams!$E$15 -> 3 | E7: =E4*Streams!$E$3/Streams!$E$15 -> 3 | F7: =F4*Streams!$E$3/Streams!$E$15 -> 3 | G7: =G4*Streams!$E$3/Streams!$E$15 -> 3 | H7: =H4*Streams!$E$3/Streams!$E$15 -> 3 | I7: =I4*Streams!$E$3/Streams!$E$15 -> 3 | ... DR7: =DR4*Streams!$E$3/Streams!$E$15 -> 3
A8: Depots revenue | B8: =B4*Streams!$E$4/Streams!$E$15 -> 0 | C8: =C4*Streams!$E$4/Streams!$E$15 -> 1 | D8: =D4*Streams!$E$4/Streams!$E$15 -> 1 | E8: =E4*Streams!$E$4/Streams!$E$15 -> 1 | F8: =F4*Streams!$E$4/Streams!$E$15 -> 1 | G8: =G4*Streams!$E$4/Streams!$E$15 -> 1 | H8: =H4*Streams!$E$4/Streams!$E$15 -> 1 | I8: =I4*Streams!$E$4/Streams!$E$15 -> 1 | ... DR8: =DR4*Streams!$E$4/Streams!$E$15 -> 1
A9: Retail scales revenue | B9: =B4*Streams!$E$5/Streams!$E$15 -> 0 | C9: =C4*Streams!$E$5/Streams!$E$15 -> 4.5 | D9: =D4*Streams!$E$5/Streams!$E$15 -> 4.5 | E9: =E4*Streams!$E$5/Streams!$E$15 -> 4.5 | F9: =F4*Streams!$E$5/Streams!$E$15 -> 4.5 | G9: =G4*Streams!$E$5/Streams!$E$15 -> 4.5 | H9: =H4*Streams!$E$5/Streams!$E$15 -> 4.5 | I9: =I4*Streams!$E$5/Streams!$E$15 -> 4.5 | ... DR9: =DR4*Streams!$E$5/Streams!$E$15 -> 4.5
A10: Scanners revenue | B10: =B4*Streams!$E$6/Streams!$E$15 -> 0 | C10: =C4*Streams!$E$6/Streams!$E$15 -> 1.5 | D10: =D4*Streams!$E$6/Streams!$E$15 -> 1.5 | E10: =E4*Streams!$E$6/Streams!$E$15 -> 1.5 | F10: =F4*Streams!$E$6/Streams!$E$15 -> 1.5 | G10: =G4*Streams!$E$6/Streams!$E$15 -> 1.5 | H10: =H4*Streams!$E$6/Streams!$E$15 -> 1.5 | I10: =I4*Streams!$E$6/Streams!$E$15 -> 1.5 | ... DR10: =DR4*Streams!$E$6/Streams!$E$15 -> 1.5
A11: Electricity meters revenue | B11: =B4*Streams!$E$7/Streams!$E$15 -> 0 | C11: =C4*Streams!$E$7/Streams!$E$15 -> 5 | D11: =D4*Streams!$E$7/Streams!$E$15 -> 5 | E11: =E4*Streams!$E$7/Streams!$E$15 -> 5 | F11: =F4*Streams!$E$7/Streams!$E$15 -> 5 | G11: =G4*Streams!$E$7/Streams!$E$15 -> 5 | H11: =H4*Streams!$E$7/Streams!$E$15 -> 5 | I11: =I4*Streams!$E$7/Streams!$E$15 -> 5 | ... DR11: =DR4*Streams!$E$7/Streams!$E$15 -> 5
A12: Telecom billing revenue | B12: =B4*Streams!$E$8/Streams!$E$15 -> 0 | C12: =C4*Streams!$E$8/Streams!$E$15 -> 2.5 | D12: =D4*Streams!$E$8/Streams!$E$15 -> 2.5 | E12: =E4*Streams!$E$8/Streams!$E$15 -> 2.5 | F12: =F4*Streams!$E$8/Streams!$E$15 -> 2.5 | G12: =G4*Streams!$E$8/Streams!$E$15 -> 2.5 | H12: =H4*Streams!$E$8/Streams!$E$15 -> 2.5 | I12: =I4*Streams!$E$8/Streams!$E$15 -> 2.5 | ... DR12: =DR4*Streams!$E$8/Streams!$E$15 -> 2.5
A13: Banking ICT revenue | B13: =B4*Streams!$E$9/Streams!$E$15 -> 0 | C13: =C4*Streams!$E$9/Streams!$E$15 -> 1.5 | D13: =D4*Streams!$E$9/Streams!$E$15 -> 1.5 | E13: =E4*Streams!$E$9/Streams!$E$15 -> 1.5 | F13: =F4*Streams!$E$9/Streams!$E$15 -> 1.5 | G13: =G4*Streams!$E$9/Streams!$E$15 -> 1.5 | H13: =H4*Streams!$E$9/Streams!$E$15 -> 1.5 | I13: =I4*Streams!$E$9/Streams!$E$15 -> 1.5 | ... DR13: =DR4*Streams!$E$9/Streams!$E$15 -> 1.5
A14: Manufacturing weighbridges revenue | B14: =B4*Streams!$E$10/Streams!$E$15 -> 0 | C14: =C4*Streams!$E$10/Streams!$E$15 -> 3 | D14: =D4*Streams!$E$10/Streams!$E$15 -> 3 | E14: =E4*Streams!$E$10/Streams!$E$15 -> 3 | F14: =F4*Streams!$E$10/Streams!$E$15 -> 3 | G14: =G4*Streams!$E$10/Streams!$E$15 -> 3 | H14: =H4*Streams!$E$10/Streams!$E$15 -> 3 | I14: =I4*Streams!$E$10/Streams!$E$15 -> 3 | ... DR14: =DR4*Streams!$E$10/Streams!$E$15 -> 3
A15: Aviation revenue | B15: =B4*Streams!$E$11/Streams!$E$15 -> 0 | C15: =C4*Streams!$E$11/Streams!$E$15 -> 1 | D15: =D4*Streams!$E$11/Streams!$E$15 -> 1 | E15: =E4*Streams!$E$11/Streams!$E$15 -> 1 | F15: =F4*Streams!$E$11/Streams!$E$15 -> 1 | G15: =G4*Streams!$E$11/Streams!$E$15 -> 1 | H15: =H4*Streams!$E$11/Streams!$E$15 -> 1 | I15: =I4*Streams!$E$11/Streams!$E$15 -> 1 | ... DR15: =DR4*Streams!$E$11/Streams!$E$15 -> 1
A16: Marine revenue | B16: =B4*Streams!$E$12/Streams!$E$15 -> 0 | C16: =C4*Streams!$E$12/Streams!$E$15 -> 1 | D16: =D4*Streams!$E$12/Streams!$E$15 -> 1 | E16: =E4*Streams!$E$12/Streams!$E$15 -> 1 | F16: =F4*Streams!$E$12/Streams!$E$15 -> 1 | G16: =G4*Streams!$E$12/Streams!$E$15 -> 1 | H16: =H4*Streams!$E$12/Streams!$E$15 -> 1 | I16: =I4*Streams!$E$12/Streams!$E$15 -> 1 | ... DR16: =DR4*Streams!$E$12/Streams!$E$15 -> 1
A17: Licensing revenue | B17: =B4*Streams!$E$13/Streams!$E$15 -> 0 | C17: =C4*Streams!$E$13/Streams!$E$15 -> 2 | D17: =D4*Streams!$E$13/Streams!$E$15 -> 2 | E17: =E4*Streams!$E$13/Streams!$E$15 -> 2 | F17: =F4*Streams!$E$13/Streams!$E$15 -> 2 | G17: =G4*Streams!$E$13/Streams!$E$15 -> 2 | H17: =H4*Streams!$E$13/Streams!$E$15 -> 2 | I17: =I4*Streams!$E$13/Streams!$E$15 -> 2 | ... DR17: =DR4*Streams!$E$13/Streams!$E$15 -> 2
A18: Pattern approval revenue | B18: =B4*Streams!$E$14/Streams!$E$15 -> 0 | C18: =C4*Streams!$E$14/Streams!$E$15 -> 1 | D18: =D4*Streams!$E$14/Streams!$E$15 -> 1 | E18: =E4*Streams!$E$14/Streams!$E$15 -> 1 | F18: =F4*Streams!$E$14/Streams!$E$15 -> 1 | G18: =G4*Streams!$E$14/Streams!$E$15 -> 1 | H18: =H4*Streams!$E$14/Streams!$E$15 -> 1 | I18: =I4*Streams!$E$14/Streams!$E$15 -> 1 | ... DR18: =DR4*Streams!$E$14/Streams!$E$15 -> 1
A19: Total stream revenue | B19: =SUM(B6:B18) -> 0 | C19: =SUM(C6:C18) -> 35 | D19: =SUM(D6:D18) -> 35 | E19: =SUM(E6:E18) -> 35 | F19: =SUM(F6:F18) -> 35 | G19: =SUM(G6:G18) -> 35 | H19: =SUM(H6:H18) -> 35 | I19: =SUM(I6:I18) -> 35 | ... DR19: =SUM(DR6:DR18) -> 35
A20: AR closing | B20: =B19*Inputs!$B$16/Inputs!$B$18 -> 0 | C20: =C19*Inputs!$B$16/Inputs!$B$18 -> 0 | D20: =D19*Inputs!$B$16/Inputs!$B$18 -> 0 | E20: =E19*Inputs!$B$16/Inputs!$B$18 -> 0 | F20: =F19*Inputs!$B$16/Inputs!$B$18 -> 0 | G20: =G19*Inputs!$B$16/Inputs!$B$18 -> 0 | H20: =H19*Inputs!$B$16/Inputs!$B$18 -> 0 | I20: =I19*Inputs!$B$16/Inputs!$B$18 -> 0 | ... DR20: =DR19*Inputs!$B$16/Inputs!$B$18 -> 0
A21: Change in AR | B21: =B20-Inputs!$B$34 -> 0 | C21: =C20-B20 -> 0 | D21: =D20-C20 -> 0 | E21: =E20-D20 -> 0 | F21: =F20-E20 -> 0 | G21: =G20-F20 -> 0 | H21: =H20-G20 -> 0 | I21: =I20-H20 -> 0 | J21: =J20-I20 -> 0 | ... DR21: =DR20-DQ20 -> 0
A22: Cash receipts | B22: =B19-B21 -> 0 | C22: =C19-C21 -> 35 | D22: =D19-D21 -> 35 | E22: =E19-E21 -> 35 | F22: =F19-F21 -> 35 | G22: =G19-G21 -> 35 | H22: =H19-H21 -> 35 | I22: =I19-I21 -> 35 | ... DR22: =DR19-DR21 -> 35
A23: Government allocation expense / cash paid | B23: =B19*Inputs!$B$4 -> 0 | C23: =C19*Inputs!$B$4 -> 14 | D23: =D19*Inputs!$B$4 -> 14 | E23: =E19*Inputs!$B$4 -> 14 | F23: =F19*Inputs!$B$4 -> 14 | G23: =G19*Inputs!$B$4 -> 14 | H23: =H19*Inputs!$B$4 -> 14 | I23: =I19*Inputs!$B$4 -> 14 | ... DR23: =DR19*Inputs!$B$4 -> 14
A24: Investor distribution entitlement | B24: =B22*Inputs!$B$5 -> 0 | C24: =C22*Inputs!$B$5 -> 3.5 | D24: =D22*Inputs!$B$5 -> 3.5 | E24: =E22*Inputs!$B$5 -> 3.5 | F24: =F22*Inputs!$B$5 -> 3.5 | G24: =G22*Inputs!$B$5 -> 3.5 | H24: =H22*Inputs!$B$5 -> 3.5 | I24: =I22*Inputs!$B$5 -> 3.5 | ... DR24: =DR22*Inputs!$B$5 -> 3.5
A25: CDS legal 50% of receipts (memo) | B25: =B22*Inputs!$B$6 -> 0 | C25: =C22*Inputs!$B$6 -> 17.5 | D25: =D22*Inputs!$B$6 -> 17.5 | E25: =E22*Inputs!$B$6 -> 17.5 | F25: =F22*Inputs!$B$6 -> 17.5 | G25: =G22*Inputs!$B$6 -> 17.5 | H25: =H22*Inputs!$B$6 -> 17.5 | I25: =I22*Inputs!$B$6 -> 17.5 | ... DR25: =DR22*Inputs!$B$6 -> 17.5
A26: OPEX reserve 20% receipts (memo) | B26: =B22*Inputs!$B$7 -> 0 | C26: =C22*Inputs!$B$7 -> 7 | D26: =D22*Inputs!$B$7 -> 7 | E26: =E22*Inputs!$B$7 -> 7 | F26: =F22*Inputs!$B$7 -> 7 | G26: =G22*Inputs!$B$7 -> 7 | H26: =H22*Inputs!$B$7 -> 7 | I26: =I22*Inputs!$B$7 -> 7 | ... DR26: =DR22*Inputs!$B$7 -> 7
A27: CDS distribution 30% receipts | B27: =B22*Inputs!$B$8 -> 0 | C27: =C22*Inputs!$B$8 -> 10.5 | D27: =D22*Inputs!$B$8 -> 10.5 | E27: =E22*Inputs!$B$8 -> 10.5 | F27: =F22*Inputs!$B$8 -> 10.5 | G27: =G22*Inputs!$B$8 -> 10.5 | H27: =H22*Inputs!$B$8 -> 10.5 | I27: =I22*Inputs!$B$8 -> 10.5 | ... DR27: =DR22*Inputs!$B$8 -> 10.5
A28: Personnel recurring OPEX | B28: =IF(B$1=Inputs!$B$34,Inputs!$B$34,Inputs!$B$12*Inputs!$B$13/Inputs!$B$32) -> 0 | C28: =IF(C$1=Inputs!$B$34,Inputs!$B$34,Inputs!$B$12*Inputs!$B$13/Inputs!$B$32) -> 0.4 | D28: =IF(D$1=Inputs!$B$34,Inputs!$B$34,Inputs!$B$12*Inputs!$B$13/Inputs!$B$32) -> 0.4 | E28: =IF(E$1=Inputs!$B$34,Inputs!$B$34,Inputs!$B$12*Inputs!$B$13/Inputs!$B$32) -> 0.4 | F28: =IF(F$1=Inputs!$B$34,Inputs!$B$34,Inputs!$B$12*Inputs!$B$13/Inputs!$B$32) -> 0.4 | G28: =IF(G$1=Inputs!$B$34,Inputs!$B$34,Inputs!$B$12*Inputs!$B$13/Inputs!$B$32) -> 0.4 | H28: =IF(H$1=Inputs!$B$34,Inputs!$B$34,Inputs!$B$12*Inputs!$B$13/Inputs!$B$32) -> 0.4 | I28: =IF(I$1=Inputs!$B$34,Inputs!$B$34,Inputs!$B$12*Inputs!$B$13/Inputs!$B$32) -> 0.4 | ... DR28: =IF(DR$1=Inputs!$B$34,Inputs!$B$34,Inputs!$B$12*Inputs!$B$13/Inputs!$B$32) -> 0.4
A29: Other fixed recurring OPEX | B29: =IF(B$1=Inputs!$B$34,Inputs!$B$34,Inputs!$B$14) -> 0 | C29: =IF(C$1=Inputs!$B$34,Inputs!$B$34,Inputs!$B$14) -> 0.15 | D29: =IF(D$1=Inputs!$B$34,Inputs!$B$34,Inputs!$B$14) -> 0.15 | E29: =IF(E$1=Inputs!$B$34,Inputs!$B$34,Inputs!$B$14) -> 0.15 | F29: =IF(F$1=Inputs!$B$34,Inputs!$B$34,Inputs!$B$14) -> 0.15 | G29: =IF(G$1=Inputs!$B$34,Inputs!$B$34,Inputs!$B$14) -> 0.15 | H29: =IF(H$1=Inputs!$B$34,Inputs!$B$34,Inputs!$B$14) -> 0.15 | I29: =IF(I$1=Inputs!$B$34,Inputs!$B$34,Inputs!$B$14) -> 0.15 | ... DR29: =IF(DR$1=Inputs!$B$34,Inputs!$B$34,Inputs!$B$14) -> 0.15
A30: Variable recurring OPEX | B30: =B19*Inputs!$B$15 -> 0 | C30: =C19*Inputs!$B$15 -> 2.8 | D30: =D19*Inputs!$B$15 -> 2.8 | E30: =E19*Inputs!$B$15 -> 2.8 | F30: =F19*Inputs!$B$15 -> 2.8 | G30: =G19*Inputs!$B$15 -> 2.8 | H30: =H19*Inputs!$B$15 -> 2.8 | I30: =I19*Inputs!$B$15 -> 2.8 | ... DR30: =DR19*Inputs!$B$15 -> 2.8
A31: Recurring OPEX total | B31: =SUM(B28:B30) -> 0 | C31: =SUM(C28:C30) -> 3.35 | D31: =SUM(D28:D30) -> 3.35 | E31: =SUM(E28:E30) -> 3.35 | F31: =SUM(F28:F30) -> 3.35 | G31: =SUM(G28:G30) -> 3.35 | H31: =SUM(H28:H30) -> 3.35 | I31: =SUM(I28:I30) -> 3.35 | ... DR31: =SUM(DR28:DR30) -> 3.35
A32: Launch expenses | B32: =IF(AND(B$1>Inputs!$B$34,B$1<=Inputs!$B$19),Funding!$B$8/Inputs!$B$19,Inputs!$B$34) -> 0 | C32: =IF(AND(C$1>Inputs!$B$34,C$1<=Inputs!$B$19),Funding!$B$8/Inputs!$B$19,Inputs!$B$34) -> 0.58333333 | D32: =IF(AND(D$1>Inputs!$B$34,D$1<=Inputs!$B$19),Funding!$B$8/Inputs!$B$19,Inputs!$B$34) -> 0.58333333 | E32: =IF(AND(E$1>Inputs!$B$34,E$1<=Inputs!$B$19),Funding!$B$8/Inputs!$B$19,Inputs!$B$34) -> 0.58333333 | F32: =IF(AND(F$1>Inputs!$B$34,F$1<=Inputs!$B$19),Funding!$B$8/Inputs!$B$19,Inputs!$B$34) -> 0.58333333 | G32: =IF(AND(G$1>Inputs!$B$34,G$1<=Inputs!$B$19),Funding!$B$8/Inputs!$B$19,Inputs!$B$34) -> 0.58333333 | H32: =IF(AND(H$1>Inputs!$B$34,H$1<=Inputs!$B$19),Funding!$B$8/Inputs!$B$19,Inputs!$B$34) -> 0.58333333 | I32: =IF(AND(I$1>Inputs!$B$34,I$1<=Inputs!$B$19),Funding!$B$8/Inputs!$B$19,Inputs!$B$34) -> 0.58333333 | ... DR32: =IF(AND(DR$1>Inputs!$B$34,DR$1<=Inputs!$B$19),Funding!$B$8/Inputs!$B$19,Inputs!$B$34) -> 0
A33: Total actual modeled OPEX | B33: =B31+B32 -> 0 | C33: =C31+C32 -> 3.9333333 | D33: =D31+D32 -> 3.9333333 | E33: =E31+E32 -> 3.9333333 | F33: =F31+F32 -> 3.9333333 | G33: =G31+G32 -> 3.9333333 | H33: =H31+H32 -> 3.9333333 | I33: =I31+I32 -> 3.9333333 | ... DR33: =DR31+DR32 -> 3.35
A34: Reserve less actual OPEX (memo) | B34: =B26-B33 -> 0 | C34: =C26-C33 -> 3.0666667 | D34: =D26-D33 -> 3.0666667 | E34: =E26-E33 -> 3.0666667 | F34: =F26-F33 -> 3.0666667 | G34: =G26-G33 -> 3.0666667 | H34: =H26-H33 -> 3.0666667 | I34: =I26-I33 -> 3.0666667 | ... DR34: =DR26-DR33 -> 3.65
A35: EBITDA after government allocation | B35: =B19-B23-B33 -> 0 | C35: =C19-C23-C33 -> 17.066667 | D35: =D19-D23-D33 -> 17.066667 | E35: =E19-E23-E33 -> 17.066667 | F35: =F19-F23-F33 -> 17.066667 | G35: =G19-G23-G33 -> 17.066667 | H35: =H19-H23-H33 -> 17.066667 | I35: =I19-I23-I33 -> 17.066667 | ... DR35: =DR19-DR23-DR33 -> 17.65
A36: Initial capex | B36: =IF(AND(B$1>Inputs!$B$34,B$1<=Inputs!$B$19),Funding!$C$7/Inputs!$B$19,Inputs!$B$34) -> 0 | C36: =IF(AND(C$1>Inputs!$B$34,C$1<=Inputs!$B$19),Funding!$C$7/Inputs!$B$19,Inputs!$B$34) -> 3.5833333 | D36: =IF(AND(D$1>Inputs!$B$34,D$1<=Inputs!$B$19),Funding!$C$7/Inputs!$B$19,Inputs!$B$34) -> 3.5833333 | E36: =IF(AND(E$1>Inputs!$B$34,E$1<=Inputs!$B$19),Funding!$C$7/Inputs!$B$19,Inputs!$B$34) -> 3.5833333 | F36: =IF(AND(F$1>Inputs!$B$34,F$1<=Inputs!$B$19),Funding!$C$7/Inputs!$B$19,Inputs!$B$34) -> 3.5833333 | G36: =IF(AND(G$1>Inputs!$B$34,G$1<=Inputs!$B$19),Funding!$C$7/Inputs!$B$19,Inputs!$B$34) -> 3.5833333 | H36: =IF(AND(H$1>Inputs!$B$34,H$1<=Inputs!$B$19),Funding!$C$7/Inputs!$B$19,Inputs!$B$34) -> 3.5833333 | I36: =IF(AND(I$1>Inputs!$B$34,I$1<=Inputs!$B$19),Funding!$C$7/Inputs!$B$19,Inputs!$B$34) -> 3.5833333 | ... DR36: =IF(AND(DR$1>Inputs!$B$34,DR$1<=Inputs!$B$19),Funding!$C$7/Inputs!$B$19,Inputs!$B$34) -> 0
A37: Maintenance capex | B37: =IF(B$1>Inputs!$B$19,B19*Inputs!$B$21,Inputs!$B$34) -> 0 | C37: =IF(C$1>Inputs!$B$19,C19*Inputs!$B$21,Inputs!$B$34) -> 0 | D37: =IF(D$1>Inputs!$B$19,D19*Inputs!$B$21,Inputs!$B$34) -> 0 | E37: =IF(E$1>Inputs!$B$19,E19*Inputs!$B$21,Inputs!$B$34) -> 0 | F37: =IF(F$1>Inputs!$B$19,F19*Inputs!$B$21,Inputs!$B$34) -> 0 | G37: =IF(G$1>Inputs!$B$19,G19*Inputs!$B$21,Inputs!$B$34) -> 0 | H37: =IF(H$1>Inputs!$B$19,H19*Inputs!$B$21,Inputs!$B$34) -> 0 | I37: =IF(I$1>Inputs!$B$19,I19*Inputs!$B$21,Inputs!$B$34) -> 0 | ... DR37: =IF(DR$1>Inputs!$B$19,DR19*Inputs!$B$21,Inputs!$B$34) -> 0.35
A38: Total capex | B38: =B36+B37 -> 0 | C38: =C36+C37 -> 3.5833333 | D38: =D36+D37 -> 3.5833333 | E38: =E36+E37 -> 3.5833333 | F38: =F36+F37 -> 3.5833333 | G38: =G36+G37 -> 3.5833333 | H38: =H36+H37 -> 3.5833333 | I38: =I36+I37 -> 3.5833333 | ... DR38: =DR36+DR37 -> 0.35
A39: Depreciation | B39: =SUM(INDEX($B$38:B38,Inputs!$B$35,MAX(Inputs!$B$35,COLUMN()-Inputs!$B$20)): B38)/Inputs!$B$20 -> 0 | C39: =SUM(INDEX($B$38:C38,Inputs!$B$35,MAX(Inputs!$B$35,COLUMN()-Inputs!$B$20)): C38)/Inputs!$B$20 -> 0.059722222 | D39: =SUM(INDEX($B$38:D38,Inputs!$B$35,MAX(Inputs!$B$35,COLUMN()-Inputs!$B$20)): D38)/Inputs!$B$20 -> 0.11944444 | E39: =SUM(INDEX($B$38:E38,Inputs!$B$35,MAX(Inputs!$B$35,COLUMN()-Inputs!$B$20)): E38)/Inputs!$B$20 -> 0.17916667 | F39: =SUM(INDEX($B$38:F38,Inputs!$B$35,MAX(Inputs!$B$35,COLUMN()-Inputs!$B$20)): F38)/Inputs!$B$20 -> 0.23888889 | G39: =SUM(INDEX($B$38:G38,Inputs!$B$35,MAX(Inputs!$B$35,COLUMN()-Inputs!$B$20)): G38)/Inputs!$B$20 -> 0.29861111 | H39: =SUM(INDEX($B$38:H38,Inputs!$B$35,MAX(Inputs!$B$35,COLUMN()-Inputs!$B$20)): H38)/Inputs!$B$20 -> 0.35833333 | I39: =SUM(INDEX($B$38:I38,Inputs!$B$35,MAX(Inputs!$B$35,COLUMN()-Inputs!$B$20)): I38)/Inputs!$B$20 -> 0.41805556 | ... DR39: =SUM(INDEX($B$38:DR38,Inputs!$B$35,MAX(Inputs!$B$35,COLUMN()-Inputs!$B$20)): DR38)/Inputs!$B$20 -> 0.35
A40: EBIT | B40: =B35-B39 -> 0 | C40: =C35-C39 -> 17.006944 | D40: =D35-D39 -> 16.947222 | E40: =E35-E39 -> 16.8875 | F40: =F35-F39 -> 16.827778 | G40: =G35-G39 -> 16.768056 | H40: =H35-H39 -> 16.708333 | I40: =I35-I39 -> 16.648611 | ... DR40: =DR35-DR39 -> 17.3
A41: Cash tax / tax expense | B41: =MAX(Inputs!$B$34,B40)*Inputs!$B$11 -> 0 | C41: =MAX(Inputs!$B$34,C40)*Inputs!$B$11 -> 5.1020833 | D41: =MAX(Inputs!$B$34,D40)*Inputs!$B$11 -> 5.0841667 | E41: =MAX(Inputs!$B$34,E40)*Inputs!$B$11 -> 5.06625 | F41: =MAX(Inputs!$B$34,F40)*Inputs!$B$11 -> 5.0483333 | G41: =MAX(Inputs!$B$34,G40)*Inputs!$B$11 -> 5.0304167 | H41: =MAX(Inputs!$B$34,H40)*Inputs!$B$11 -> 5.0125 | I41: =MAX(Inputs!$B$34,I40)*Inputs!$B$11 -> 4.9945833 | ... DR41: =MAX(Inputs!$B$34,DR40)*Inputs!$B$11 -> 5.19
A42: Net income before owner distributions | B42: =B40-B41 -> 0 | C42: =C40-C41 -> 11.904861 | D42: =D40-D41 -> 11.863056 | E42: =E40-E41 -> 11.82125 | F42: =F40-F41 -> 11.779444 | G42: =G40-G41 -> 11.737639 | H42: =H40-H41 -> 11.695833 | I42: =I40-I41 -> 11.654028 | ... DR42: =DR40-DR41 -> 12.11
A43: AP closing | B43: =B31*Inputs!$B$17/Inputs!$B$18 -> 0 | C43: =C31*Inputs!$B$17/Inputs!$B$18 -> 0 | D43: =D31*Inputs!$B$17/Inputs!$B$18 -> 0 | E43: =E31*Inputs!$B$17/Inputs!$B$18 -> 0 | F43: =F31*Inputs!$B$17/Inputs!$B$18 -> 0 | G43: =G31*Inputs!$B$17/Inputs!$B$18 -> 0 | H43: =H31*Inputs!$B$17/Inputs!$B$18 -> 0 | I43: =I31*Inputs!$B$17/Inputs!$B$18 -> 0 | ... DR43: =DR31*Inputs!$B$17/Inputs!$B$18 -> 0
A44: Change in AP | B44: =B43-Inputs!$B$34 -> 0 | C44: =C43-B43 -> 0 | D44: =D43-C43 -> 0 | E44: =E43-D43 -> 0 | F44: =F43-E43 -> 0 | G44: =G43-F43 -> 0 | H44: =H43-G43 -> 0 | I44: =I43-H43 -> 0 | J44: =J43-I43 -> 0 | ... DR44: =DR43-DQ43 -> 0
A45: CFO = NI + DA - change AR + change AP | B45: =B42+B39-B21+B44 -> 0 | C45: =C42+C39-C21+C44 -> 11.964583 | D45: =D42+D39-D21+D44 -> 11.9825 | E45: =E42+E39-E21+E44 -> 12.000417 | F45: =F42+F39-F21+F44 -> 12.018333 | G45: =G42+G39-G21+G44 -> 12.03625 | H45: =H42+H39-H21+H44 -> 12.054167 | I45: =I42+I39-I21+I44 -> 12.072083 | ... DR45: =DR42+DR39-DR21+DR44 -> 12.46
A46: CFI = capex outflow | B46: =-B38 -> 0 | C46: =-C38 -> -3.5833333 | D46: =-D38 -> -3.5833333 | E46: =-E38 -> -3.5833333 | F46: =-F38 -> -3.5833333 | G46: =-G38 -> -3.5833333 | H46: =-H38 -> -3.5833333 | I46: =-I38 -> -3.5833333 | ... DR46: =-DR38 -> -0.35
A47: Investor capital contributed | B47: =IF(B$1=Inputs!$B$34,Inputs!$B$22+Inputs!$B$23,Inputs!$B$34) -> 50 | C47: =IF(C$1=Inputs!$B$34,Inputs!$B$22+Inputs!$B$23,Inputs!$B$34) -> 0 | D47: =IF(D$1=Inputs!$B$34,Inputs!$B$22+Inputs!$B$23,Inputs!$B$34) -> 0 | E47: =IF(E$1=Inputs!$B$34,Inputs!$B$22+Inputs!$B$23,Inputs!$B$34) -> 0 | F47: =IF(F$1=Inputs!$B$34,Inputs!$B$22+Inputs!$B$23,Inputs!$B$34) -> 0 | G47: =IF(G$1=Inputs!$B$34,Inputs!$B$22+Inputs!$B$23,Inputs!$B$34) -> 0 | H47: =IF(H$1=Inputs!$B$34,Inputs!$B$22+Inputs!$B$23,Inputs!$B$34) -> 0 | I47: =IF(I$1=Inputs!$B$34,Inputs!$B$22+Inputs!$B$23,Inputs!$B$34) -> 0 | ... DR47: =IF(DR$1=Inputs!$B$34,Inputs!$B$22+Inputs!$B$23,Inputs!$B$34) -> 0
A48: Owner distributions (investor + CDS) | B48: =B24+B27 -> 0 | C48: =C24+C27 -> 14 | D48: =D24+D27 -> 14 | E48: =E24+E27 -> 14 | F48: =F24+F27 -> 14 | G48: =G24+G27 -> 14 | H48: =H24+H27 -> 14 | I48: =I24+I27 -> 14 | ... DR48: =DR24+DR27 -> 14
A49: CFF = contributions - owner distributions | B49: =B47-B48 -> 50 | C49: =C47-C48 -> -14 | D49: =D47-D48 -> -14 | E49: =E47-E48 -> -14 | F49: =F47-F48 -> -14 | G49: =G47-G48 -> -14 | H49: =H47-H48 -> -14 | I49: =I47-I48 -> -14 | ... DR49: =DR47-DR48 -> -14
A50: Net cash flow | B50: =SUM(B45:B46)+B49 -> 50 | C50: =SUM(C45:C46)+C49 -> -5.61875 | D50: =SUM(D45:D46)+D49 -> -5.6008333 | E50: =SUM(E45:E46)+E49 -> -5.5829167 | F50: =SUM(F45:F46)+F49 -> -5.565 | G50: =SUM(G45:G46)+G49 -> -5.5470833 | H50: =SUM(H45:H46)+H49 -> -5.5291667 | I50: =SUM(I45:I46)+I49 -> -5.51125 | ... DR50: =SUM(DR45:DR46)+DR49 -> -1.89
A51: Opening unfinanced cash | B51: =Inputs!$B$34 -> 0 | C51: =B52 -> 50 | D51: =C52 -> 44.38125 | E51: =D52 -> 38.780417 | F51: =E52 -> 33.1975 | G51: =F52 -> 27.6325 | H51: =G52 -> 22.085417 | I51: =H52 -> 16.55625 | J51: =I52 -> 11.045 | ... DR51: =DQ52 -> -210.0675
A52: Closing unfinanced cash | B52: =B51+B50 -> 50 | C52: =C51+C50 -> 44.38125 | D52: =D51+D50 -> 38.780417 | E52: =E51+E50 -> 33.1975 | F52: =F51+F50 -> 27.6325 | G52: =G51+G50 -> 22.085417 | H52: =H51+H50 -> 16.55625 | I52: =I51+I50 -> 11.045 | ... DR52: =DR51+DR50 -> -211.9575
A53: Funding gap at period end | B53: =MAX(Inputs!$B$34,-B52) -> 0 | C53: =MAX(Inputs!$B$34,-C52) -> 0 | D53: =MAX(Inputs!$B$34,-D52) -> 0 | E53: =MAX(Inputs!$B$34,-E52) -> 0 | F53: =MAX(Inputs!$B$34,-F52) -> 0 | G53: =MAX(Inputs!$B$34,-G52) -> 0 | H53: =MAX(Inputs!$B$34,-H52) -> 0 | I53: =MAX(Inputs!$B$34,-I52) -> 0 | ... DR53: =MAX(Inputs!$B$34,-DR52) -> 211.9575
A54: PP&E closing net | B54: =B38-B39 -> 0 | C54: =B54+C38-C39 -> 3.5236111 | D54: =C54+D38-D39 -> 6.9875 | E54: =D54+E38-E39 -> 10.391667 | F54: =E54+F38-F39 -> 13.736111 | G54: =F54+G38-G39 -> 17.020833 | H54: =G54+H38-H39 -> 20.245833 | I54: =H54+I38-I39 -> 23.411111 | J54: =I54+J38-J39 -> 26.516667 | ... DR54: =DQ54+DR38-DR39 -> 10.325
A55: Cumulative contributed capital | B55: =SUM($B47:B47) -> 50 | C55: =SUM($B47:C47) -> 50 | D55: =SUM($B47:D47) -> 50 | E55: =SUM($B47:E47) -> 50 | F55: =SUM($B47:F47) -> 50 | G55: =SUM($B47:G47) -> 50 | H55: =SUM($B47:H47) -> 50 | I55: =SUM($B47:I47) -> 50 | ... DR55: =SUM($B47:DR47) -> 50
A56: Retained earnings after distributions | B56: =B42-B48 -> 0 | C56: =B56+C42-C48 -> -2.0951389 | D56: =C56+D42-D48 -> -4.2320833 | E56: =D56+E42-E48 -> -6.4108333 | F56: =E56+F42-F48 -> -8.6313889 | G56: =F56+G42-G48 -> -10.89375 | H56: =G56+H42-H48 -> -13.197917 | I56: =H56+I42-I48 -> -15.543889 | J56: =I56+J42-J48 -> -17.931667 | ... DR56: =DQ56+DR42-DR48 -> -251.6325
A57: Total assets (cash may be unfunded) | B57: =B52+B20+B54 -> 50 | C57: =C52+C20+C54 -> 47.904861 | D57: =D52+D20+D54 -> 45.767917 | E57: =E52+E20+E54 -> 43.589167 | F57: =F52+F20+F54 -> 41.368611 | G57: =G52+G20+G54 -> 39.10625 | H57: =H52+H20+H54 -> 36.802083 | I57: =I52+I20+I54 -> 34.456111 | ... DR57: =DR52+DR20+DR54 -> -201.6325
A58: Total liabilities + equity | B58: =B43+B55+B56 -> 50 | C58: =C43+C55+C56 -> 47.904861 | D58: =D43+D55+D56 -> 45.767917 | E58: =E43+E55+E56 -> 43.589167 | F58: =F43+F55+F56 -> 41.368611 | G58: =G43+G55+G56 -> 39.10625 | H58: =H43+H55+H56 -> 36.802083 | I58: =I43+I55+I56 -> 34.456111 | ... DR58: =DR43+DR55+DR56 -> -201.6325
A59: Balance sheet check | B59: =B57-B58 -> 0 | C59: =C57-C58 -> 0 | D59: =D57-D58 -> 0 | E59: =E57-E58 -> 0 | F59: =F57-F58 -> 0 | G59: =G57-G58 -> 0 | H59: =H57-H58 -> 0 | I59: =I57-I58 -> 0 | ... DR59: =DR57-DR58 -> 0
A60: Cash roll-forward check | B60: =B52-B51-B50 -> 0 | C60: =C52-C51-C50 -> 0 | D60: =D52-D51-D50 -> 0 | E60: =E52-E51-E50 -> 0 | F60: =F52-F51-F50 -> 0 | G60: =G52-G51-G50 -> 0 | H60: =H52-H51-H50 -> 0 | I60: =I52-I51-I50 -> 0 | ... DR60: =DR52-DR51-DR50 -> 1.4210855e-14
A61: Allocation split check | B61: =B25-B26-B27 -> 0 | C61: =C25-C26-C27 -> 0 | D61: =D25-D26-D27 -> 0 | E61: =E25-E26-E27 -> 0 | F61: =F25-F26-F27 -> 0 | G61: =G25-G26-G27 -> 0 | H61: =H25-H26-H27 -> 0 | I61: =I25-I26-I27 -> 0 | ... DR61: =DR25-DR26-DR27 -> 0
A62: Investor net cash flow | B62: =B24-B47 -> -50 | C62: =C24-C47 -> 3.5 | D62: =D24-D47 -> 3.5 | E62: =E24-E47 -> 3.5 | F62: =F24-F47 -> 3.5 | G62: =G24-G47 -> 3.5 | H62: =H24-H47 -> 3.5 | I62: =I24-I47 -> 3.5 | ... DR62: =DR24-DR47 -> 3.5
A63: Investor cumulative net cash flow | B63: =SUM($B62:B62) -> -50 | C63: =SUM($B62:C62) -> -46.5 | D63: =SUM($B62:D62) -> -43 | E63: =SUM($B62:E62) -> -39.5 | F63: =SUM($B62:F62) -> -36 | G63: =SUM($B62:G62) -> -32.5 | H63: =SUM($B62:H62) -> -29 | I63: =SUM($B62:I62) -> -25.5 | ... DR63: =SUM($B62:DR62) -> 370
A64: Investor cumulative distributions | B64: =SUM($B24:B24) -> 0 | C64: =SUM($B24:C24) -> 3.5 | D64: =SUM($B24:D24) -> 7 | E64: =SUM($B24:E24) -> 10.5 | F64: =SUM($B24:F24) -> 14 | G64: =SUM($B24:G24) -> 17.5 | H64: =SUM($B24:H24) -> 21 | I64: =SUM($B24:I24) -> 24.5 | ... DR64: =SUM($B24:DR24) -> 420
A65: Gross share source entitlement | B65: =B19*Inputs!$B$5 -> 0 | C65: =C19*Inputs!$B$5 -> 3.5 | D65: =D19*Inputs!$B$5 -> 3.5 | E65: =E19*Inputs!$B$5 -> 3.5 | F65: =F19*Inputs!$B$5 -> 3.5 | G65: =G19*Inputs!$B$5 -> 3.5 | H65: =H19*Inputs!$B$5 -> 3.5 | I65: =I19*Inputs!$B$5 -> 3.5 | ... DR65: =DR19*Inputs!$B$5 -> 3.5
A66: Revenue stream tie check | B66: =B19-B4 -> 0 | C66: =C19-C4 -> 0 | D66: =D19-D4 -> 0 | E66: =E19-E4 -> 0 | F66: =F19-F4 -> 0 | G66: =G19-G4 -> 0 | H66: =H19-H4 -> 0 | I66: =I19-I4 -> 0 | ... DR66: =DR19-DR4 -> 0
A67: Investor CF after all committed funding reserved | B67: =B64-SUM($B$47:$DR$47) -> -50 | C67: =C64-SUM($B$47:$DR$47) -> -46.5 | D67: =D64-SUM($B$47:$DR$47) -> -43 | E67: =E64-SUM($B$47:$DR$47) -> -39.5 | F67: =F64-SUM($B$47:$DR$47) -> -36 | G67: =G64-SUM($B$47:$DR$47) -> -32.5 | H67: =H64-SUM($B$47:$DR$47) -> -29 | I67: =I64-SUM($B$47:$DR$47) -> -25.5 | ... DR67: =DR64-SUM($B$47:$DR$47) -> 370
A68: Cash receipt negative flag | B68: =IF(B22<-Inputs!$B$33,Inputs!$B$35,Inputs!$B$34) -> 0 | C68: =IF(C22<-Inputs!$B$33,Inputs!$B$35,Inputs!$B$34) -> 0 | D68: =IF(D22<-Inputs!$B$33,Inputs!$B$35,Inputs!$B$34) -> 0 | E68: =IF(E22<-Inputs!$B$33,Inputs!$B$35,Inputs!$B$34) -> 0 | F68: =IF(F22<-Inputs!$B$33,Inputs!$B$35,Inputs!$B$34) -> 0 | G68: =IF(G22<-Inputs!$B$33,Inputs!$B$35,Inputs!$B$34) -> 0 | H68: =IF(H22<-Inputs!$B$33,Inputs!$B$35,Inputs!$B$34) -> 0 | I68: =IF(I22<-Inputs!$B$33,Inputs!$B$35,Inputs!$B$34) -> 0 | ... DR68: =IF(DR22<-Inputs!$B$33,Inputs!$B$35,Inputs!$B$34) -> 0

Sheet Headline annual
A1: Month index | B1: =Inputs!$B$34 -> 0 | C1: =B1+Inputs!$B$35 -> 1 | D1: =C1+Inputs!$B$35 -> 2 | E1: =D1+Inputs!$B$35 -> 3 | F1: =E1+Inputs!$B$35 -> 4 | G1: =F1+Inputs!$B$35 -> 5 | H1: =G1+Inputs!$B$35 -> 6 | I1: =H1+Inputs!$B$35 -> 7 | J1: =I1+Inputs!$B$35 -> 8 | ... L1: =K1+Inputs!$B$35 -> 10
A2: Model year | B2: =B1 -> 0 | C2: =C1 -> 1 | D2: =D1 -> 2 | E2: =E1 -> 3 | F2: =F1 -> 4 | G2: =G1 -> 5 | H2: =H1 -> 6 | I2: =I1 -> 7 | ... L2: =L1 -> 10
A3: Case target before VAT B | B3: =Headline!B3 -> 0 | C3: =SUM(Headline!C3:N3) -> 420 | D3: =SUM(Headline!O3:Z3) -> 420 | E3: =SUM(Headline!AA3:AL3) -> 420 | F3: =SUM(Headline!AM3:AX3) -> 420 | G3: =SUM(Headline!AY3:BJ3) -> 420 | H3: =SUM(Headline!BK3:BV3) -> 420 | I3: =SUM(Headline!BW3:CH3) -> 420 | J3: =SUM(Headline!CI3:CT3) -> 420 | K3: =SUM(Headline!CU3:DF3) -> 420 | L3: =SUM(Headline!DG3:DR3) -> 420
A4: Revenue base excluding VAT | B4: =Headline!B4 -> 0 | C4: =SUM(Headline!C4:N4) -> 420 | D4: =SUM(Headline!O4:Z4) -> 420 | E4: =SUM(Headline!AA4:AL4) -> 420 | F4: =SUM(Headline!AM4:AX4) -> 420 | G4: =SUM(Headline!AY4:BJ4) -> 420 | H4: =SUM(Headline!BK4:BV4) -> 420 | I4: =SUM(Headline!BW4:CH4) -> 420 | J4: =SUM(Headline!CI4:CT4) -> 420 | K4: =SUM(Headline!CU4:DF4) -> 420 | L4: =SUM(Headline!DG4:DR4) -> 420
A5: VAT excluded from base (informational) | B5: =Headline!B5 -> 0 | C5: =SUM(Headline!C5:N5) -> 0 | D5: =SUM(Headline!O5:Z5) -> 0 | E5: =SUM(Headline!AA5:AL5) -> 0 | F5: =SUM(Headline!AM5:AX5) -> 0 | G5: =SUM(Headline!AY5:BJ5) -> 0 | H5: =SUM(Headline!BK5:BV5) -> 0 | I5: =SUM(Headline!BW5:CH5) -> 0 | J5: =SUM(Headline!CI5:CT5) -> 0 | K5: =SUM(Headline!CU5:DF5) -> 0 | L5: =SUM(Headline!DG5:DR5) -> 0
A6: Pumps revenue | B6: =Headline!B6 -> 0 | C6: =SUM(Headline!C6:N6) -> 96 | D6: =SUM(Headline!O6:Z6) -> 96 | E6: =SUM(Headline!AA6:AL6) -> 96 | F6: =SUM(Headline!AM6:AX6) -> 96 | G6: =SUM(Headline!AY6:BJ6) -> 96 | H6: =SUM(Headline!BK6:BV6) -> 96 | I6: =SUM(Headline!BW6:CH6) -> 96 | J6: =SUM(Headline!CI6:CT6) -> 96 | K6: =SUM(Headline!CU6:DF6) -> 96 | L6: =SUM(Headline!DG6:DR6) -> 96
A7: Tankers revenue | B7: =Headline!B7 -> 0 | C7: =SUM(Headline!C7:N7) -> 36 | D7: =SUM(Headline!O7:Z7) -> 36 | E7: =SUM(Headline!AA7:AL7) -> 36 | F7: =SUM(Headline!AM7:AX7) -> 36 | G7: =SUM(Headline!AY7:BJ7) -> 36 | H7: =SUM(Headline!BK7:BV7) -> 36 | I7: =SUM(Headline!BW7:CH7) -> 36 | J7: =SUM(Headline!CI7:CT7) -> 36 | K7: =SUM(Headline!CU7:DF7) -> 36 | L7: =SUM(Headline!DG7:DR7) -> 36
A8: Depots revenue | B8: =Headline!B8 -> 0 | C8: =SUM(Headline!C8:N8) -> 12 | D8: =SUM(Headline!O8:Z8) -> 12 | E8: =SUM(Headline!AA8:AL8) -> 12 | F8: =SUM(Headline!AM8:AX8) -> 12 | G8: =SUM(Headline!AY8:BJ8) -> 12 | H8: =SUM(Headline!BK8:BV8) -> 12 | I8: =SUM(Headline!BW8:CH8) -> 12 | J8: =SUM(Headline!CI8:CT8) -> 12 | K8: =SUM(Headline!CU8:DF8) -> 12 | L8: =SUM(Headline!DG8:DR8) -> 12
A9: Retail scales revenue | B9: =Headline!B9 -> 0 | C9: =SUM(Headline!C9:N9) -> 54 | D9: =SUM(Headline!O9:Z9) -> 54 | E9: =SUM(Headline!AA9:AL9) -> 54 | F9: =SUM(Headline!AM9:AX9) -> 54 | G9: =SUM(Headline!AY9:BJ9) -> 54 | H9: =SUM(Headline!BK9:BV9) -> 54 | I9: =SUM(Headline!BW9:CH9) -> 54 | J9: =SUM(Headline!CI9:CT9) -> 54 | K9: =SUM(Headline!CU9:DF9) -> 54 | L9: =SUM(Headline!DG9:DR9) -> 54
A10: Scanners revenue | B10: =Headline!B10 -> 0 | C10: =SUM(Headline!C10:N10) -> 18 | D10: =SUM(Headline!O10:Z10) -> 18 | E10: =SUM(Headline!AA10:AL10) -> 18 | F10: =SUM(Headline!AM10:AX10) -> 18 | G10: =SUM(Headline!AY10:BJ10) -> 18 | H10: =SUM(Headline!BK10:BV10) -> 18 | I10: =SUM(Headline!BW10:CH10) -> 18 | J10: =SUM(Headline!CI10:CT10) -> 18 | K10: =SUM(Headline!CU10:DF10) -> 18 | L10: =SUM(Headline!DG10:DR10) -> 18
A11: Electricity meters revenue | B11: =Headline!B11 -> 0 | C11: =SUM(Headline!C11:N11) -> 60 | D11: =SUM(Headline!O11:Z11) -> 60 | E11: =SUM(Headline!AA11:AL11) -> 60 | F11: =SUM(Headline!AM11:AX11) -> 60 | G11: =SUM(Headline!AY11:BJ11) -> 60 | H11: =SUM(Headline!BK11:BV11) -> 60 | I11: =SUM(Headline!BW11:CH11) -> 60 | J11: =SUM(Headline!CI11:CT11) -> 60 | K11: =SUM(Headline!CU11:DF11) -> 60 | L11: =SUM(Headline!DG11:DR11) -> 60
A12: Telecom billing revenue | B12: =Headline!B12 -> 0 | C12: =SUM(Headline!C12:N12) -> 30 | D12: =SUM(Headline!O12:Z12) -> 30 | E12: =SUM(Headline!AA12:AL12) -> 30 | F12: =SUM(Headline!AM12:AX12) -> 30 | G12: =SUM(Headline!AY12:BJ12) -> 30 | H12: =SUM(Headline!BK12:BV12) -> 30 | I12: =SUM(Headline!BW12:CH12) -> 30 | J12: =SUM(Headline!CI12:CT12) -> 30 | K12: =SUM(Headline!CU12:DF12) -> 30 | L12: =SUM(Headline!DG12:DR12) -> 30
A13: Banking ICT revenue | B13: =Headline!B13 -> 0 | C13: =SUM(Headline!C13:N13) -> 18 | D13: =SUM(Headline!O13:Z13) -> 18 | E13: =SUM(Headline!AA13:AL13) -> 18 | F13: =SUM(Headline!AM13:AX13) -> 18 | G13: =SUM(Headline!AY13:BJ13) -> 18 | H13: =SUM(Headline!BK13:BV13) -> 18 | I13: =SUM(Headline!BW13:CH13) -> 18 | J13: =SUM(Headline!CI13:CT13) -> 18 | K13: =SUM(Headline!CU13:DF13) -> 18 | L13: =SUM(Headline!DG13:DR13) -> 18
A14: Manufacturing weighbridges revenue | B14: =Headline!B14 -> 0 | C14: =SUM(Headline!C14:N14) -> 36 | D14: =SUM(Headline!O14:Z14) -> 36 | E14: =SUM(Headline!AA14:AL14) -> 36 | F14: =SUM(Headline!AM14:AX14) -> 36 | G14: =SUM(Headline!AY14:BJ14) -> 36 | H14: =SUM(Headline!BK14:BV14) -> 36 | I14: =SUM(Headline!BW14:CH14) -> 36 | J14: =SUM(Headline!CI14:CT14) -> 36 | K14: =SUM(Headline!CU14:DF14) -> 36 | L14: =SUM(Headline!DG14:DR14) -> 36
... A19: Total stream revenue | B19: =Headline!B19 -> 0 | C19: =SUM(Headline!C19:N19) -> 420 | D19: =SUM(Headline!O19:Z19) -> 420 | E19: =SUM(Headline!AA19:AL19) -> 420 | F19: =SUM(Headline!AM19:AX19) -> 420 | G19: =SUM(Headline!AY19:BJ19) -> 420 | H19: =SUM(Headline!BK19:BV19) -> 420 | I19: =SUM(Headline!BW19:CH19) -> 420 | J19: =SUM(Headline!CI19:CT19) -> 420 | K19: =SUM(Headline!CU19:DF19) -> 420 | L19: =SUM(Headline!DG19:DR19) -> 420
A20: AR closing | B20: =Headline!B20 -> 0 | C20: =Headline!N20 -> 0 | D20: =Headline!Z20 -> 0 | E20: =Headline!AL20 -> 0 | F20: =Headline!AX20 -> 0 | G20: =Headline!BJ20 -> 0 | H20: =Headline!BV20 -> 0 | I20: =Headline!CH20 -> 0 | J20: =Headline!CT20 -> 0 | K20: =Headline!DF20 -> 0 | L20: =Headline!DR20 -> 0
A21: Change in AR | B21: =Headline!B21 -> 0 | C21: =SUM(Headline!C21:N21) -> 0 | D21: =SUM(Headline!O21:Z21) -> 0 | E21: =SUM(Headline!AA21:AL21) -> 0 | F21: =SUM(Headline!AM21:AX21) -> 0 | G21: =SUM(Headline!AY21:BJ21) -> 0 | H21: =SUM(Headline!BK21:BV21) -> 0 | I21: =SUM(Headline!BW21:CH21) -> 0 | J21: =SUM(Headline!CI21:CT21) -> 0 | K21: =SUM(Headline!CU21:DF21) -> 0 | L21: =SUM(Headline!DG21:DR21) -> 0
A22: Cash receipts | B22: =Headline!B22 -> 0 | C22: =SUM(Headline!C22:N22) -> 420 | D22: =SUM(Headline!O22:Z22) -> 420 | E22: =SUM(Headline!AA22:AL22) -> 420 | F22: =SUM(Headline!AM22:AX22) -> 420 | G22: =SUM(Headline!AY22:BJ22) -> 420 | H22: =SUM(Headline!BK22:BV22) -> 420 | I22: =SUM(Headline!BW22:CH22) -> 420 | J22: =SUM(Headline!CI22:CT22) -> 420 | K22: =SUM(Headline!CU22:DF22) -> 420 | L22: =SUM(Headline!DG22:DR22) -> 420
A23: Government allocation expense / cash paid | B23: =Headline!B23 -> 0 | C23: =SUM(Headline!C23:N23) -> 168 | D23: =SUM(Headline!O23:Z23) -> 168 | E23: =SUM(Headline!AA23:AL23) -> 168 | F23: =SUM(Headline!AM23:AX23) -> 168 | G23: =SUM(Headline!AY23:BJ23) -> 168 | H23: =SUM(Headline!BK23:BV23) -> 168 | I23: =SUM(Headline!BW23:CH23) -> 168 | J23: =SUM(Headline!CI23:CT23) -> 168 | K23: =SUM(Headline!CU23:DF23) -> 168 | L23: =SUM(Headline!DG23:DR23) -> 168
A24: Investor distribution entitlement | B24: =Headline!B24 -> 0 | C24: =SUM(Headline!C24:N24) -> 42 | D24: =SUM(Headline!O24:Z24) -> 42 | E24: =SUM(Headline!AA24:AL24) -> 42 | F24: =SUM(Headline!AM24:AX24) -> 42 | G24: =SUM(Headline!AY24:BJ24) -> 42 | H24: =SUM(Headline!BK24:BV24) -> 42 | I24: =SUM(Headline!BW24:CH24) -> 42 | J24: =SUM(Headline!CI24:CT24) -> 42 | K24: =SUM(Headline!CU24:DF24) -> 42 | L24: =SUM(Headline!DG24:DR24) -> 42
A25: CDS legal 50% of receipts (memo) | B25: =Headline!B25 -> 0 | C25: =SUM(Headline!C25:N25) -> 210 | D25: =SUM(Headline!O25:Z25) -> 210 | E25: =SUM(Headline!AA25:AL25) -> 210 | F25: =SUM(Headline!AM25:AX25) -> 210 | G25: =SUM(Headline!AY25:BJ25) -> 210 | H25: =SUM(Headline!BK25:BV25) -> 210 | I25: =SUM(Headline!BW25:CH25) -> 210 | J25: =SUM(Headline!CI25:CT25) -> 210 | K25: =SUM(Headline!CU25:DF25) -> 210 | L25: =SUM(Headline!DG25:DR25) -> 210
A26: OPEX reserve 20% receipts (memo) | B26: =Headline!B26 -> 0 | C26: =SUM(Headline!C26:N26) -> 84 | D26: =SUM(Headline!O26:Z26) -> 84 | E26: =SUM(Headline!AA26:AL26) -> 84 | F26: =SUM(Headline!AM26:AX26) -> 84 | G26: =SUM(Headline!AY26:BJ26) -> 84 | H26: =SUM(Headline!BK26:BV26) -> 84 | I26: =SUM(Headline!BW26:CH26) -> 84 | J26: =SUM(Headline!CI26:CT26) -> 84 | K26: =SUM(Headline!CU26:DF26) -> 84 | L26: =SUM(Headline!DG26:DR26) -> 84
A27: CDS distribution 30% receipts | B27: =Headline!B27 -> 0 | C27: =SUM(Headline!C27:N27) -> 126 | D27: =SUM(Headline!O27:Z27) -> 126 | E27: =SUM(Headline!AA27:AL27) -> 126 | F27: =SUM(Headline!AM27:AX27) -> 126 | G27: =SUM(Headline!AY27:BJ27) -> 126 | H27: =SUM(Headline!BK27:BV27) -> 126 | I27: =SUM(Headline!BW27:CH27) -> 126 | J27: =SUM(Headline!CI27:CT27) -> 126 | K27: =SUM(Headline!CU27:DF27) -> 126 | L27: =SUM(Headline!DG27:DR27) -> 126
A28: Personnel recurring OPEX | B28: =Headline!B28 -> 0 | C28: =SUM(Headline!C28:N28) -> 4.8 | D28: =SUM(Headline!O28:Z28) -> 4.8 | E28: =SUM(Headline!AA28:AL28) -> 4.8 | F28: =SUM(Headline!AM28:AX28) -> 4.8 | G28: =SUM(Headline!AY28:BJ28) -> 4.8 | H28: =SUM(Headline!BK28:BV28) -> 4.8 | I28: =SUM(Headline!BW28:CH28) -> 4.8 | J28: =SUM(Headline!CI28:CT28) -> 4.8 | K28: =SUM(Headline!CU28:DF28) -> 4.8 | L28: =SUM(Headline!DG28:DR28) -> 4.8
A29: Other fixed recurring OPEX | B29: =Headline!B29 -> 0 | C29: =SUM(Headline!C29:N29) -> 1.8 | D29: =SUM(Headline!O29:Z29) -> 1.8 | E29: =SUM(Headline!AA29:AL29) -> 1.8 | F29: =SUM(Headline!AM29:AX29) -> 1.8 | G29: =SUM(Headline!AY29:BJ29) -> 1.8 | H29: =SUM(Headline!BK29:BV29) -> 1.8 | I29: =SUM(Headline!BW29:CH29) -> 1.8 | J29: =SUM(Headline!CI29:CT29) -> 1.8 | K29: =SUM(Headline!CU29:DF29) -> 1.8 | L29: =SUM(Headline!DG29:DR29) -> 1.8
A30: Variable recurring OPEX | B30: =Headline!B30 -> 0 | C30: =SUM(Headline!C30:N30) -> 33.6 | D30: =SUM(Headline!O30:Z30) -> 33.6 | E30: =SUM(Headline!AA30:AL30) -> 33.6 | F30: =SUM(Headline!AM30:AX30) -> 33.6 | G30: =SUM(Headline!AY30:BJ30) -> 33.6 | H30: =SUM(Headline!BK30:BV30) -> 33.6 | I30: =SUM(Headline!BW30:CH30) -> 33.6 | J30: =SUM(Headline!CI30:CT30) -> 33.6 | K30: =SUM(Headline!CU30:DF30) -> 33.6 | L30: =SUM(Headline!DG30:DR30) -> 33.6
A31: Recurring OPEX total | B31: =Headline!B31 -> 0 | C31: =SUM(Headline!C31:N31) -> 40.2 | D31: =SUM(Headline!O31:Z31) -> 40.2 | E31: =SUM(Headline!AA31:AL31) -> 40.2 | F31: =SUM(Headline!AM31:AX31) -> 40.2 | G31: =SUM(Headline!AY31:BJ31) -> 40.2 | H31: =SUM(Headline!BK31:BV31) -> 40.2 | I31: =SUM(Headline!BW31:CH31) -> 40.2 | J31: =SUM(Headline!CI31:CT31) -> 40.2 | K31: =SUM(Headline!CU31:DF31) -> 40.2 | L31: =SUM(Headline!DG31:DR31) -> 40.2
A32: Launch expenses | B32: =Headline!B32 -> 0 | C32: =SUM(Headline!C32:N32) -> 7 | D32: =SUM(Headline!O32:Z32) -> 0 | E32: =SUM(Headline!AA32:AL32) -> 0 | F32: =SUM(Headline!AM32:AX32) -> 0 | G32: =SUM(Headline!AY32:BJ32) -> 0 | H32: =SUM(Headline!BK32:BV32) -> 0 | I32: =SUM(Headline!BW32:CH32) -> 0 | J32: =SUM(Headline!CI32:CT32) -> 0 | K32: =SUM(Headline!CU32:DF32) -> 0 | L32: =SUM(Headline!DG32:DR32) -> 0
... A42: Net income before owner distributions | B42: =Headline!B42 -> 0 | C42: =SUM(Headline!C42:N42) -> 140.09917 | D42: =SUM(Headline!O42:Z42) -> 141.9215 | E42: =SUM(Headline!AA42:AL42) -> 141.3335 | F42: =SUM(Headline!AM42:AX42) -> 140.7455 | G42: =SUM(Headline!AY42:BJ42) -> 140.1575 | H42: =SUM(Headline!BK42:BV42) -> 142.83033 | I42: =SUM(Headline!BW42:CH42) -> 145.32 | J42: =SUM(Headline!CI42:CT42) -> 145.32 | K42: =SUM(Headline!CU42:DF42) -> 145.32 | L42: =SUM(Headline!DG42:DR42) -> 145.32
A43: AP closing | B43: =Headline!B43 -> 0 | C43: =Headline!N43 -> 0 | D43: =Headline!Z43 -> 0 | E43: =Headline!AL43 -> 0 | F43: =Headline!AX43 -> 0 | G43: =Headline!BJ43 -> 0 | H43: =Headline!BV43 -> 0 | I43: =Headline!CH43 -> 0 | J43: =Headline!CT43 -> 0 | K43: =Headline!DF43 -> 0 | L43: =Headline!DR43 -> 0
A44: Change in AP | B44: =Headline!B44 -> 0 | C44: =SUM(Headline!C44:N44) -> 0 | D44: =SUM(Headline!O44:Z44) -> 0 | E44: =SUM(Headline!AA44:AL44) -> 0 | F44: =SUM(Headline!AM44:AX44) -> 0 | G44: =SUM(Headline!AY44:BJ44) -> 0 | H44: =SUM(Headline!BK44:BV44) -> 0 | I44: =SUM(Headline!BW44:CH44) -> 0 | J44: =SUM(Headline!CI44:CT44) -> 0 | K44: =SUM(Headline!CU44:DF44) -> 0 | L44: =SUM(Headline!DG44:DR44) -> 0
A45: CFO = NI + DA - change AR + change AP | B45: =Headline!B45 -> 0 | C45: =SUM(Headline!C45:N45) -> 144.7575 | D45: =SUM(Headline!O45:Z45) -> 150.9765 | E45: =SUM(Headline!AA45:AL45) -> 151.2285 | F45: =SUM(Headline!AM45:AX45) -> 151.4805 | G45: =SUM(Headline!AY45:BJ45) -> 151.7325 | H45: =SUM(Headline!BK45:BV45) -> 150.587 | I45: =SUM(Headline!BW45:CH45) -> 149.52 | J45: =SUM(Headline!CI45:CT45) -> 149.52 | K45: =SUM(Headline!CU45:DF45) -> 149.52 | L45: =SUM(Headline!DG45:DR45) -> 149.52
A46: CFI = capex outflow | B46: =Headline!B46 -> 0 | C46: =SUM(Headline!C46:N46) -> -43 | D46: =SUM(Headline!O46:Z46) -> -4.2 | E46: =SUM(Headline!AA46:AL46) -> -4.2 | F46: =SUM(Headline!AM46:AX46) -> -4.2 | G46: =SUM(Headline!AY46:BJ46) -> -4.2 | H46: =SUM(Headline!BK46:BV46) -> -4.2 | I46: =SUM(Headline!BW46:CH46) -> -4.2 | J46: =SUM(Headline!CI46:CT46) -> -4.2 | K46: =SUM(Headline!CU46:DF46) -> -4.2 | L46: =SUM(Headline!DG46:DR46) -> -4.2
A47: Investor capital contributed | B47: =Headline!B47 -> 50 | C47: =SUM(Headline!C47:N47) -> 0 | D47: =SUM(Headline!O47:Z47) -> 0 | E47: =SUM(Headline!AA47:AL47) -> 0 | F47: =SUM(Headline!AM47:AX47) -> 0 | G47: =SUM(Headline!AY47:BJ47) -> 0 | H47: =SUM(Headline!BK47:BV47) -> 0 | I47: =SUM(Headline!BW47:CH47) -> 0 | J47: =SUM(Headline!CI47:CT47) -> 0 | K47: =SUM(Headline!CU47:DF47) -> 0 | L47: =SUM(Headline!DG47:DR47) -> 0
A48: Owner distributions (investor + CDS) | B48: =Headline!B48 -> 0 | C48: =SUM(Headline!C48:N48) -> 168 | D48: =SUM(Headline!O48:Z48) -> 168 | E48: =SUM(Headline!AA48:AL48) -> 168 | F48: =SUM(Headline!AM48:AX48) -> 168 | G48: =SUM(Headline!AY48:BJ48) -> 168 | H48: =SUM(Headline!BK48:BV48) -> 168 | I48: =SUM(Headline!BW48:CH48) -> 168 | J48: =SUM(Headline!CI48:CT48) -> 168 | K48: =SUM(Headline!CU48:DF48) -> 168 | L48: =SUM(Headline!DG48:DR48) -> 168
A49: CFF = contributions - owner distributions | B49: =Headline!B49 -> 50 | C49: =SUM(Headline!C49:N49) -> -168 | D49: =SUM(Headline!O49:Z49) -> -168 | E49: =SUM(Headline!AA49:AL49) -> -168 | F49: =SUM(Headline!AM49:AX49) -> -168 | G49: =SUM(Headline!AY49:BJ49) -> -168 | H49: =SUM(Headline!BK49:BV49) -> -168 | I49: =SUM(Headline!BW49:CH49) -> -168 | J49: =SUM(Headline!CI49:CT49) -> -168 | K49: =SUM(Headline!CU49:DF49) -> -168 | L49: =SUM(Headline!DG49:DR49) -> -168
A50: Net cash flow | B50: =Headline!B50 -> 50 | C50: =SUM(Headline!C50:N50) -> -66.2425 | D50: =SUM(Headline!O50:Z50) -> -21.2235 | E50: =SUM(Headline!AA50:AL50) -> -20.9715 | F50: =SUM(Headline!AM50:AX50) -> -20.7195 | G50: =SUM(Headline!AY50:BJ50) -> -20.4675 | H50: =SUM(Headline!BK50:BV50) -> -21.613 | I50: =SUM(Headline!BW50:CH50) -> -22.68 | J50: =SUM(Headline!CI50:CT50) -> -22.68 | K50: =SUM(Headline!CU50:DF50) -> -22.68 | L50: =SUM(Headline!DG50:DR50) -> -22.68
A51: Opening unfinanced cash | B51: =Headline!B51 -> 0 | C51: =Headline!C51 -> 50 | D51: =Headline!O51 -> -16.2425 | E51: =Headline!AA51 -> -37.466 | F51: =Headline!AM51 -> -58.4375 | G51: =Headline!AY51 -> -79.157 | H51: =Headline!BK51 -> -99.6245 | I51: =Headline!BW51 -> -121.2375 | J51: =Headline!CI51 -> -143.9175 | K51: =Headline!CU51 -> -166.5975 | L51: =Headline!DG51 -> -189.2775
A52: Closing unfinanced cash | B52: =Headline!B52 -> 50 | C52: =Headline!N52 -> -16.2425 | D52: =Headline!Z52 -> -37.466 | E52: =Headline!AL52 -> -58.4375 | F52: =Headline!AX52 -> -79.157 | G52: =Headline!BJ52 -> -99.6245 | H52: =Headline!BV52 -> -121.2375 | I52: =Headline!CH52 -> -143.9175 | J52: =Headline!CT52 -> -166.5975 | K52: =Headline!DF52 -> -189.2775 | L52: =Headline!DR52 -> -211.9575
A53: Funding gap at period end | B53: =Headline!B53 -> 0 | C53: =Headline!N53 -> 16.2425 | D53: =Headline!Z53 -> 37.466 | E53: =Headline!AL53 -> 58.4375 | F53: =Headline!AX53 -> 79.157 | G53: =Headline!BJ53 -> 99.6245 | H53: =Headline!BV53 -> 121.2375 | I53: =Headline!CH53 -> 143.9175 | J53: =Headline!CT53 -> 166.5975 | K53: =Headline!DF53 -> 189.2775 | L53: =Headline!DR53 -> 211.9575
A54: PP&E closing net | B54: =Headline!B54 -> 0 | C54: =Headline!N54 -> 38.341667 | D54: =Headline!Z54 -> 33.486667 | E54: =Headline!AL54 -> 27.791667 | F54: =Headline!AX54 -> 21.256667 | G54: =Headline!BJ54 -> 13.881667 | H54: =Headline!BV54 -> 10.325 | I54: =Headline!CH54 -> 10.325 | J54: =Headline!CT54 -> 10.325 | K54: =Headline!DF54 -> 10.325 | L54: =Headline!DR54 -> 10.325
A55: Cumulative contributed capital | B55: =Headline!B55 -> 50 | C55: =Headline!N55 -> 50 | D55: =Headline!Z55 -> 50 | E55: =Headline!AL55 -> 50 | F55: =Headline!AX55 -> 50 | G55: =Headline!BJ55 -> 50 | H55: =Headline!BV55 -> 50 | I55: =Headline!CH55 -> 50 | J55: =Headline!CT55 -> 50 | K55: =Headline!DF55 -> 50 | L55: =Headline!DR55 -> 50
A56: Retained earnings after distributions | B56: =Headline!B56 -> 0 | C56: =Headline!N56 -> -27.900833 | D56: =Headline!Z56 -> -53.979333 | E56: =Headline!AL56 -> -80.645833 | F56: =Headline!AX56 -> -107.90033 | G56: =Headline!BJ56 -> -135.74283 | H56: =Headline!BV56 -> -160.9125 | I56: =Headline!CH56 -> -183.5925 | J56: =Headline!CT56 -> -206.2725 | K56: =Headline!DF56 -> -228.9525 | L56: =Headline!DR56 -> -251.6325
A57: Total assets (cash may be unfunded) | B57: =Headline!B57 -> 50 | C57: =Headline!N57 -> 22.099167 | D57: =Headline!Z57 -> -3.9793333 | E57: =Headline!AL57 -> -30.645833 | F57: =Headline!AX57 -> -57.900333 | G57: =Headline!BJ57 -> -85.742833 | H57: =Headline!BV57 -> -110.9125 | I57: =Headline!CH57 -> -133.5925 | J57: =Headline!CT57 -> -156.2725 | K57: =Headline!DF57 -> -178.9525 | L57: =Headline!DR57 -> -201.6325
A58: Total liabilities + equity | B58: =Headline!B58 -> 50 | C58: =Headline!N58 -> 22.099167 | D58: =Headline!Z58 -> -3.9793333 | E58: =Headline!AL58 -> -30.645833 | F58: =Headline!AX58 -> -57.900333 | G58: =Headline!BJ58 -> -85.742833 | H58: =Headline!BV58 -> -110.9125 | I58: =Headline!CH58 -> -133.5925 | J58: =Headline!CT58 -> -156.2725 | K58: =Headline!DF58 -> -178.9525 | L58: =Headline!DR58 -> -201.6325
A59: Balance sheet check | B59: =Headline!B59 -> 0 | C59: =SUM(Headline!C59:N59) -> 0 | D59: =SUM(Headline!O59:Z59) -> 1.3500312e-13 | E59: =SUM(Headline!AA59:AL59) -> 7.1054274e-14 | F59: =SUM(Headline!AM59:AX59) -> 0 | G59: =SUM(Headline!AY59:BJ59) -> 0 | H59: =SUM(Headline!BK59:BV59) -> 0 | I59: =SUM(Headline!BW59:CH59) -> 0 | J59: =SUM(Headline!CI59:CT59) -> 0 | K59: =SUM(Headline!CU59:DF59) -> 0 | L59: =SUM(Headline!DG59:DR59) -> 0
A60: Cash roll-forward check | B60: =Headline!B60 -> 0 | C60: =SUM(Headline!C60:N60) -> 0 | D60: =SUM(Headline!O60:Z60) -> 0 | E60: =SUM(Headline!AA60:AL60) -> 0 | F60: =SUM(Headline!AM60:AX60) -> 1.4210855e-14 | G60: =SUM(Headline!AY60:BJ60) -> 0 | H60: =SUM(Headline!BK60:BV60) -> 7.1054274e-15 | I60: =SUM(Headline!BW60:CH60) -> 1.1368684e-13 | J60: =SUM(Headline!CI60:CT60) -> 1.7053026e-13 | K60: =SUM(Headline!CU60:DF60) -> 1.7053026e-13 | L60: =SUM(Headline!DG60:DR60) -> 1.7053026e-13
A61: Allocation split check | B61: =Headline!B61 -> 0 | C61: =SUM(Headline!C61:N61) -> 0 | D61: =SUM(Headline!O61:Z61) -> 0 | E61: =SUM(Headline!AA61:AL61) -> 0 | F61: =SUM(Headline!AM61:AX61) -> 0 | G61: =SUM(Headline!AY61:BJ61) -> 0 | H61: =SUM(Headline!BK61:BV61) -> 0 | I61: =SUM(Headline!BW61:CH61) -> 0 | J61: =SUM(Headline!CI61:CT61) -> 0 | K61: =SUM(Headline!CU61:DF61) -> 0 | L61: =SUM(Headline!DG61:DR61) -> 0
A62: Investor net cash flow | B62: =Headline!B62 -> -50 | C62: =SUM(Headline!C62:N62) -> 42 | D62: =SUM(Headline!O62:Z62) -> 42 | E62: =SUM(Headline!AA62:AL62) -> 42 | F62: =SUM(Headline!AM62:AX62) -> 42 | G62: =SUM(Headline!AY62:BJ62) -> 42 | H62: =SUM(Headline!BK62:BV62) -> 42 | I62: =SUM(Headline!BW62:CH62) -> 42 | J62: =SUM(Headline!CI62:CT62) -> 42 | K62: =SUM(Headline!CU62:DF62) -> 42 | L62: =SUM(Headline!DG62:DR62) -> 42
A63: Investor cumulative net cash flow | B63: =Headline!B63 -> -50 | C63: =Headline!N63 -> -8 | D63: =Headline!Z63 -> 34 | E63: =Headline!AL63 -> 76 | F63: =Headline!AX63 -> 118 | G63: =Headline!BJ63 -> 160 | H63: =Headline!BV63 -> 202 | I63: =Headline!CH63 -> 244 | J63: =Headline!CT63 -> 286 | K63: =Headline!DF63 -> 328 | L63: =Headline!DR63 -> 370
A64: Investor cumulative distributions | B64: =Headline!B64 -> 0 | C64: =Headline!N64 -> 42 | D64: =Headline!Z64 -> 84 | E64: =Headline!AL64 -> 126 | F64: =Headline!AX64 -> 168 | G64: =Headline!BJ64 -> 210 | H64: =Headline!BV64 -> 252 | I64: =Headline!CH64 -> 294 | J64: =Headline!CT64 -> 336 | K64: =Headline!DF64 -> 378 | L64: =Headline!DR64 -> 420
A65: Gross share source entitlement | B65: =Headline!B65 -> 0 | C65: =SUM(Headline!C65:N65) -> 42 | D65: =SUM(Headline!O65:Z65) -> 42 | E65: =SUM(Headline!AA65:AL65) -> 42 | F65: =SUM(Headline!AM65:AX65) -> 42 | G65: =SUM(Headline!AY65:BJ65) -> 42 | H65: =SUM(Headline!BK65:BV65) -> 42 | I65: =SUM(Headline!BW65:CH65) -> 42 | J65: =SUM(Headline!CI65:CT65) -> 42 | K65: =SUM(Headline!CU65:DF65) -> 42 | L65: =SUM(Headline!DG65:DR65) -> 42
A66: Revenue stream tie check | B66: =Headline!B66 -> 0 | C66: =SUM(Headline!C66:N66) -> 0 | D66: =SUM(Headline!O66:Z66) -> 0 | E66: =SUM(Headline!AA66:AL66) -> 0 | F66: =SUM(Headline!AM66:AX66) -> 0 | G66: =SUM(Headline!AY66:BJ66) -> 0 | H66: =SUM(Headline!BK66:BV66) -> 0 | I66: =SUM(Headline!BW66:CH66) -> 0 | J66: =SUM(Headline!CI66:CT66) -> 0 | K66: =SUM(Headline!CU66:DF66) -> 0 | L66: =SUM(Headline!DG66:DR66) -> 0
A67: Investor CF after all committed funding reserved | B67: =Headline!B67 -> -50 | C67: =Headline!N67 -> -8 | D67: =Headline!Z67 -> 34 | E67: =Headline!AL67 -> 76 | F67: =Headline!AX67 -> 118 | G67: =Headline!BJ67 -> 160 | H67: =Headline!BV67 -> 202 | I67: =Headline!CH67 -> 244 | J67: =Headline!CT67 -> 286 | K67: =Headline!DF67 -> 328 | L67: =Headline!DR67 -> 370
A68: Cash receipt negative flag | B68: =Headline!B68 -> 0 | C68: =SUM(Headline!C68:N68) -> 0 | D68: =SUM(Headline!O68:Z68) -> 0 | E68: =SUM(Headline!AA68:AL68) -> 0 | F68: =SUM(Headline!AM68:AX68) -> 0 | G68: =SUM(Headline!AY68:BJ68) -> 0 | H68: =SUM(Headline!BK68:BV68) -> 0 | I68: =SUM(Headline!BW68:CH68) -> 0 | J68: =SUM(Headline!CI68:CT68) -> 0 | K68: =SUM(Headline!CU68:DF68) -> 0 | L68: =SUM(Headline!DG68:DR68) -> 0

Sheet Ramp
A1: Month index | B1: =Inputs!$B$34 -> 0 | C1: =B1+Inputs!$B$35 -> 1 | D1: =C1+Inputs!$B$35 -> 2 | E1: =D1+Inputs!$B$35 -> 3 | F1: =E1+Inputs!$B$35 -> 4 | G1: =F1+Inputs!$B$35 -> 5 | H1: =G1+Inputs!$B$35 -> 6 | I1: =H1+Inputs!$B$35 -> 7 | J1: =I1+Inputs!$B$35 -> 8 | ... DR1: =DQ1+Inputs!$B$35 -> 120
A2: Model year | B2: =ROUNDUP(B$1/Inputs!$B$2,Inputs!$B$34) -> 0 | C2: =ROUNDUP(C$1/Inputs!$B$2,Inputs!$B$34) -> 1 | D2: =ROUNDUP(D$1/Inputs!$B$2,Inputs!$B$34) -> 1 | E2: =ROUNDUP(E$1/Inputs!$B$2,Inputs!$B$34) -> 1 | F2: =ROUNDUP(F$1/Inputs!$B$2,Inputs!$B$34) -> 1 | G2: =ROUNDUP(G$1/Inputs!$B$2,Inputs!$B$34) -> 1 | H2: =ROUNDUP(H$1/Inputs!$B$2,Inputs!$B$34) -> 1 | I2: =ROUNDUP(I$1/Inputs!$B$2,Inputs!$B$34) -> 1 | ... DR2: =ROUNDUP(DR$1/Inputs!$B$2,Inputs!$B$34) -> 10
A3: Case target before VAT B | B3: =IF(B$1=Inputs!$B$34,Inputs!$B$34,IF(B$1<Inputs!$B$25,Inputs!$B$34,IF(B$1<Inputs!$B$26,Inputs!$B$28,IF(B$1<Inputs!$B$27,Inputs!$B$29,Streams!$E$15)))) -> 0 | C3: =IF(C$1=Inputs!$B$34,Inputs!$B$34,IF(C$1<Inputs!$B$25,Inputs!$B$34,IF(C$1<Inputs!$B$26,Inputs!$B$28,IF(C$1<Inputs!$B$27,Inputs!$B$29,Streams!$E$15)))) -> 0 | D3: =IF(D$1=Inputs!$B$34,Inputs!$B$34,IF(D$1<Inputs!$B$25,Inputs!$B$34,IF(D$1<Inputs!$B$26,Inputs!$B$28,IF(D$1<Inputs!$B$27,Inputs!$B$29,Streams!$E$15)))) -> 0 | E3: =IF(E$1=Inputs!$B$34,Inputs!$B$34,IF(E$1<Inputs!$B$25,Inputs!$B$34,IF(E$1<Inputs!$B$26,Inputs!$B$28,IF(E$1<Inputs!$B$27,Inputs!$B$29,Streams!$E$15)))) -> 0 | F3: =IF(F$1=Inputs!$B$34,Inputs!$B$34,IF(F$1<Inputs!$B$25,Inputs!$B$34,IF(F$1<Inputs!$B$26,Inputs!$B$28,IF(F$1<Inputs!$B$27,Inputs!$B$29,Streams!$E$15)))) -> 0 | G3: =IF(G$1=Inputs!$B$34,Inputs!$B$34,IF(G$1<Inputs!$B$25,Inputs!$B$34,IF(G$1<Inputs!$B$26,Inputs!$B$28,IF(G$1<Inputs!$B$27,Inputs!$B$29,Streams!$E$15)))) -> 0 | H3: =IF(H$1=Inputs!$B$34,Inputs!$B$34,IF(H$1<Inputs!$B$25,Inputs!$B$34,IF(H$1<Inputs!$B$26,Inputs!$B$28,IF(H$1<Inputs!$B$27,Inputs!$B$29,Streams!$E$15)))) -> 15 | I3: =IF(I$1=Inputs!$B$34,Inputs!$B$34,IF(I$1<Inputs!$B$25,Inputs!$B$34,IF(I$1<Inputs!$B$26,Inputs!$B$28,IF(I$1<Inputs!$B$27,Inputs!$B$29,Streams!$E$15)))) -> 15 | ... DR3: =IF(DR$1=Inputs!$B$34,Inputs!$B$34,IF(DR$1<Inputs!$B$25,Inputs!$B$34,IF(DR$1<Inputs!$B$26,Inputs!$B$28,IF(DR$1<Inputs!$B$27,Inputs!$B$29,Streams!$E$15)))) -> 35
A4: Revenue base excluding VAT | B4: =B3/(Inputs!$B$35+Inputs!$B$9*Inputs!$B$10) -> 0 | C4: =C3/(Inputs!$B$35+Inputs!$B$9*Inputs!$B$10) -> 0 | D4: =D3/(Inputs!$B$35+Inputs!$B$9*Inputs!$B$10) -> 0 | E4: =E3/(Inputs!$B$35+Inputs!$B$9*Inputs!$B$10) -> 0 | F4: =F3/(Inputs!$B$35+Inputs!$B$9*Inputs!$B$10) -> 0 | G4: =G3/(Inputs!$B$35+Inputs!$B$9*Inputs!$B$10) -> 0 | H4: =H3/(Inputs!$B$35+Inputs!$B$9*Inputs!$B$10) -> 15 | I4: =I3/(Inputs!$B$35+Inputs!$B$9*Inputs!$B$10) -> 15 | ... DR4: =DR3/(Inputs!$B$35+Inputs!$B$9*Inputs!$B$10) -> 35
A5: VAT excluded from base (informational) | B5: =B3-B4 -> 0 | C5: =C3-C4 -> 0 | D5: =D3-D4 -> 0 | E5: =E3-E4 -> 0 | F5: =F3-F4 -> 0 | G5: =G3-G4 -> 0 | H5: =H3-H4 -> 0 | I5: =I3-I4 -> 0 | ... DR5: =DR3-DR4 -> 0
A6: Pumps revenue | B6: =B4*Streams!$E$2/Streams!$E$15 -> 0 | C6: =C4*Streams!$E$2/Streams!$E$15 -> 0 | D6: =D4*Streams!$E$2/Streams!$E$15 -> 0 | E6: =E4*Streams!$E$2/Streams!$E$15 -> 0 | F6: =F4*Streams!$E$2/Streams!$E$15 -> 0 | G6: =G4*Streams!$E$2/Streams!$E$15 -> 0 | H6: =H4*Streams!$E$2/Streams!$E$15 -> 3.4285714 | I6: =I4*Streams!$E$2/Streams!$E$15 -> 3.4285714 | ... DR6: =DR4*Streams!$E$2/Streams!$E$15 -> 8
A7: Tankers revenue | B7: =B4*Streams!$E$3/Streams!$E$15 -> 0 | C7: =C4*Streams!$E$3/Streams!$E$15 -> 0 | D7: =D4*Streams!$E$3/Streams!$E$15 -> 0 | E7: =E4*Streams!$E$3/Streams!$E$15 -> 0 | F7: =F4*Streams!$E$3/Streams!$E$15 -> 0 | G7: =G4*Streams!$E$3/Streams!$E$15 -> 0 | H7: =H4*Streams!$E$3/Streams!$E$15 -> 1.2857143 | I7: =I4*Streams!$E$3/Streams!$E$15 -> 1.2857143 | ... DR7: =DR4*Streams!$E$3/Streams!$E$15 -> 3
A8: Depots revenue | B8: =B4*Streams!$E$4/Streams!$E$15 -> 0 | C8: =C4*Streams!$E$4/Streams!$E$15 -> 0 | D8: =D4*Streams!$E$4/Streams!$E$15 -> 0 | E8: =E4*Streams!$E$4/Streams!$E$15 -> 0 | F8: =F4*Streams!$E$4/Streams!$E$15 -> 0 | G8: =G4*Streams!$E$4/Streams!$E$15 -> 0 | H8: =H4*Streams!$E$4/Streams!$E$15 -> 0.42857143 | I8: =I4*Streams!$E$4/Streams!$E$15 -> 0.42857143 | ... DR8: =DR4*Streams!$E$4/Streams!$E$15 -> 1
A9: Retail scales revenue | B9: =B4*Streams!$E$5/Streams!$E$15 -> 0 | C9: =C4*Streams!$E$5/Streams!$E$15 -> 0 | D9: =D4*Streams!$E$5/Streams!$E$15 -> 0 | E9: =E4*Streams!$E$5/Streams!$E$15 -> 0 | F9: =F4*Streams!$E$5/Streams!$E$15 -> 0 | G9: =G4*Streams!$E$5/Streams!$E$15 -> 0 | H9: =H4*Streams!$E$5/Streams!$E$15 -> 1.9285714 | I9: =I4*Streams!$E$5/Streams!$E$15 -> 1.9285714 | ... DR9: =DR4*Streams!$E$5/Streams!$E$15 -> 4.5
A10: Scanners revenue | B10: =B4*Streams!$E$6/Streams!$E$15 -> 0 | C10: =C4*Streams!$E$6/Streams!$E$15 -> 0 | D10: =D4*Streams!$E$6/Streams!$E$15 -> 0 | E10: =E4*Streams!$E$6/Streams!$E$15 -> 0 | F10: =F4*Streams!$E$6/Streams!$E$15 -> 0 | G10: =G4*Streams!$E$6/Streams!$E$15 -> 0 | H10: =H4*Streams!$E$6/Streams!$E$15 -> 0.64285714 | I10: =I4*Streams!$E$6/Streams!$E$15 -> 0.64285714 | ... DR10: =DR4*Streams!$E$6/Streams!$E$15 -> 1.5
A11: Electricity meters revenue | B11: =B4*Streams!$E$7/Streams!$E$15 -> 0 | C11: =C4*Streams!$E$7/Streams!$E$15 -> 0 | D11: =D4*Streams!$E$7/Streams!$E$15 -> 0 | E11: =E4*Streams!$E$7/Streams!$E$15 -> 0 | F11: =F4*Streams!$E$7/Streams!$E$15 -> 0 | G11: =G4*Streams!$E$7/Streams!$E$15 -> 0 | H11: =H4*Streams!$E$7/Streams!$E$15 -> 2.1428571 | I11: =I4*Streams!$E$7/Streams!$E$15 -> 2.1428571 | ... DR11: =DR4*Streams!$E$7/Streams!$E$15 -> 5
A12: Telecom billing revenue | B12: =B4*Streams!$E$8/Streams!$E$15 -> 0 | C12: =C4*Streams!$E$8/Streams!$E$15 -> 0 | D12: =D4*Streams!$E$8/Streams!$E$15 -> 0 | E12: =E4*Streams!$E$8/Streams!$E$15 -> 0 | F12: =F4*Streams!$E$8/Streams!$E$15 -> 0 | G12: =G4*Streams!$E$8/Streams!$E$15 -> 0 | H12: =H4*Streams!$E$8/Streams!$E$15 -> 1.0714286 | I12: =I4*Streams!$E$8/Streams!$E$15 -> 1.0714286 | ... DR12: =DR4*Streams!$E$8/Streams!$E$15 -> 2.5
A13: Banking ICT revenue | B13: =B4*Streams!$E$9/Streams!$E$15 -> 0 | C13: =C4*Streams!$E$9/Streams!$E$15 -> 0 | D13: =D4*Streams!$E$9/Streams!$E$15 -> 0 | E13: =E4*Streams!$E$9/Streams!$E$15 -> 0 | F13: =F4*Streams!$E$9/Streams!$E$15 -> 0 | G13: =G4*Streams!$E$9/Streams!$E$15 -> 0 | H13: =H4*Streams!$E$9/Streams!$E$15 -> 0.64285714 | I13: =I4*Streams!$E$9/Streams!$E$15 -> 0.64285714 | ... DR13: =DR4*Streams!$E$9/Streams!$E$15 -> 1.5
A14: Manufacturing weighbridges revenue | B14: =B4*Streams!$E$10/Streams!$E$15 -> 0 | C14: =C4*Streams!$E$10/Streams!$E$15 -> 0 | D14: =D4*Streams!$E$10/Streams!$E$15 -> 0 | E14: =E4*Streams!$E$10/Streams!$E$15 -> 0 | F14: =F4*Streams!$E$10/Streams!$E$15 -> 0 | G14: =G4*Streams!$E$10/Streams!$E$15 -> 0 | H14: =H4*Streams!$E$10/Streams!$E$15 -> 1.2857143 | I14: =I4*Streams!$E$10/Streams!$E$15 -> 1.2857143 | ... DR14: =DR4*Streams!$E$10/Streams!$E$15 -> 3
A15: Aviation revenue | B15: =B4*Streams!$E$11/Streams!$E$15 -> 0 | C15: =C4*Streams!$E$11/Streams!$E$15 -> 0 | D15: =D4*Streams!$E$11/Streams!$E$15 -> 0 | E15: =E4*Streams!$E$11/Streams!$E$15 -> 0 | F15: =F4*Streams!$E$11/Streams!$E$15 -> 0 | G15: =G4*Streams!$E$11/Streams!$E$15 -> 0 | H15: =H4*Streams!$E$11/Streams!$E$15 -> 0.42857143 | I15: =I4*Streams!$E$11/Streams!$E$15 -> 0.42857143 | ... DR15: =DR4*Streams!$E$11/Streams!$E$15 -> 1
A16: Marine revenue | B16: =B4*Streams!$E$12/Streams!$E$15 -> 0 | C16: =C4*Streams!$E$12/Streams!$E$15 -> 0 | D16: =D4*Streams!$E$12/Streams!$E$15 -> 0 | E16: =E4*Streams!$E$12/Streams!$E$15 -> 0 | F16: =F4*Streams!$E$12/Streams!$E$15 -> 0 | G16: =G4*Streams!$E$12/Streams!$E$15 -> 0 | H16: =H4*Streams!$E$12/Streams!$E$15 -> 0.42857143 | I16: =I4*Streams!$E$12/Streams!$E$15 -> 0.42857143 | ... DR16: =DR4*Streams!$E$12/Streams!$E$15 -> 1
A17: Licensing revenue | B17: =B4*Streams!$E$13/Streams!$E$15 -> 0 | C17: =C4*Streams!$E$13/Streams!$E$15 -> 0 | D17: =D4*Streams!$E$13/Streams!$E$15 -> 0 | E17: =E4*Streams!$E$13/Streams!$E$15 -> 0 | F17: =F4*Streams!$E$13/Streams!$E$15 -> 0 | G17: =G4*Streams!$E$13/Streams!$E$15 -> 0 | H17: =H4*Streams!$E$13/Streams!$E$15 -> 0.85714286 | I17: =I4*Streams!$E$13/Streams!$E$15 -> 0.85714286 | ... DR17: =DR4*Streams!$E$13/Streams!$E$15 -> 2
A18: Pattern approval revenue | B18: =B4*Streams!$E$14/Streams!$E$15 -> 0 | C18: =C4*Streams!$E$14/Streams!$E$15 -> 0 | D18: =D4*Streams!$E$14/Streams!$E$15 -> 0 | E18: =E4*Streams!$E$14/Streams!$E$15 -> 0 | F18: =F4*Streams!$E$14/Streams!$E$15 -> 0 | G18: =G4*Streams!$E$14/Streams!$E$15 -> 0 | H18: =H4*Streams!$E$14/Streams!$E$15 -> 0.42857143 | I18: =I4*Streams!$E$14/Streams!$E$15 -> 0.42857143 | ... DR18: =DR4*Streams!$E$14/Streams!$E$15 -> 1
A19: Total stream revenue | B19: =SUM(B6:B18) -> 0 | C19: =SUM(C6:C18) -> 0 | D19: =SUM(D6:D18) -> 0 | E19: =SUM(E6:E18) -> 0 | F19: =SUM(F6:F18) -> 0 | G19: =SUM(G6:G18) -> 0 | H19: =SUM(H6:H18) -> 15 | I19: =SUM(I6:I18) -> 15 | ... DR19: =SUM(DR6:DR18) -> 35
A20: AR closing | B20: =B19*Inputs!$B$16/Inputs!$B$18 -> 0 | C20: =C19*Inputs!$B$16/Inputs!$B$18 -> 0 | D20: =D19*Inputs!$B$16/Inputs!$B$18 -> 0 | E20: =E19*Inputs!$B$16/Inputs!$B$18 -> 0 | F20: =F19*Inputs!$B$16/Inputs!$B$18 -> 0 | G20: =G19*Inputs!$B$16/Inputs!$B$18 -> 0 | H20: =H19*Inputs!$B$16/Inputs!$B$18 -> 0 | I20: =I19*Inputs!$B$16/Inputs!$B$18 -> 0 | ... DR20: =DR19*Inputs!$B$16/Inputs!$B$18 -> 0
A21: Change in AR | B21: =B20-Inputs!$B$34 -> 0 | C21: =C20-B20 -> 0 | D21: =D20-C20 -> 0 | E21: =E20-D20 -> 0 | F21: =F20-E20 -> 0 | G21: =G20-F20 -> 0 | H21: =H20-G20 -> 0 | I21: =I20-H20 -> 0 | J21: =J20-I20 -> 0 | ... DR21: =DR20-DQ20 -> 0
A22: Cash receipts | B22: =B19-B21 -> 0 | C22: =C19-C21 -> 0 | D22: =D19-D21 -> 0 | E22: =E19-E21 -> 0 | F22: =F19-F21 -> 0 | G22: =G19-G21 -> 0 | H22: =H19-H21 -> 15 | I22: =I19-I21 -> 15 | ... DR22: =DR19-DR21 -> 35
A23: Government allocation expense / cash paid | B23: =B19*Inputs!$B$4 -> 0 | C23: =C19*Inputs!$B$4 -> 0 | D23: =D19*Inputs!$B$4 -> 0 | E23: =E19*Inputs!$B$4 -> 0 | F23: =F19*Inputs!$B$4 -> 0 | G23: =G19*Inputs!$B$4 -> 0 | H23: =H19*Inputs!$B$4 -> 6 | I23: =I19*Inputs!$B$4 -> 6 | ... DR23: =DR19*Inputs!$B$4 -> 14
A24: Investor distribution entitlement | B24: =B22*Inputs!$B$5 -> 0 | C24: =C22*Inputs!$B$5 -> 0 | D24: =D22*Inputs!$B$5 -> 0 | E24: =E22*Inputs!$B$5 -> 0 | F24: =F22*Inputs!$B$5 -> 0 | G24: =G22*Inputs!$B$5 -> 0 | H24: =H22*Inputs!$B$5 -> 1.5 | I24: =I22*Inputs!$B$5 -> 1.5 | ... DR24: =DR22*Inputs!$B$5 -> 3.5
A25: CDS legal 50% of receipts (memo) | B25: =B22*Inputs!$B$6 -> 0 | C25: =C22*Inputs!$B$6 -> 0 | D25: =D22*Inputs!$B$6 -> 0 | E25: =E22*Inputs!$B$6 -> 0 | F25: =F22*Inputs!$B$6 -> 0 | G25: =G22*Inputs!$B$6 -> 0 | H25: =H22*Inputs!$B$6 -> 7.5 | I25: =I22*Inputs!$B$6 -> 7.5 | ... DR25: =DR22*Inputs!$B$6 -> 17.5
A26: OPEX reserve 20% receipts (memo) | B26: =B22*Inputs!$B$7 -> 0 | C26: =C22*Inputs!$B$7 -> 0 | D26: =D22*Inputs!$B$7 -> 0 | E26: =E22*Inputs!$B$7 -> 0 | F26: =F22*Inputs!$B$7 -> 0 | G26: =G22*Inputs!$B$7 -> 0 | H26: =H22*Inputs!$B$7 -> 3 | I26: =I22*Inputs!$B$7 -> 3 | ... DR26: =DR22*Inputs!$B$7 -> 7
A27: CDS distribution 30% receipts | B27: =B22*Inputs!$B$8 -> 0 | C27: =C22*Inputs!$B$8 -> 0 | D27: =D22*Inputs!$B$8 -> 0 | E27: =E22*Inputs!$B$8 -> 0 | F27: =F22*Inputs!$B$8 -> 0 | G27: =G22*Inputs!$B$8 -> 0 | H27: =H22*Inputs!$B$8 -> 4.5 | I27: =I22*Inputs!$B$8 -> 4.5 | ... DR27: =DR22*Inputs!$B$8 -> 10.5
A28: Personnel recurring OPEX | B28: =IF(B$1=Inputs!$B$34,Inputs!$B$34,Inputs!$B$12*Inputs!$B$13/Inputs!$B$32) -> 0 | C28: =IF(C$1=Inputs!$B$34,Inputs!$B$34,Inputs!$B$12*Inputs!$B$13/Inputs!$B$32) -> 0.4 | D28: =IF(D$1=Inputs!$B$34,Inputs!$B$34,Inputs!$B$12*Inputs!$B$13/Inputs!$B$32) -> 0.4 | E28: =IF(E$1=Inputs!$B$34,Inputs!$B$34,Inputs!$B$12*Inputs!$B$13/Inputs!$B$32) -> 0.4 | F28: =IF(F$1=Inputs!$B$34,Inputs!$B$34,Inputs!$B$12*Inputs!$B$13/Inputs!$B$32) -> 0.4 | G28: =IF(G$1=Inputs!$B$34,Inputs!$B$34,Inputs!$B$12*Inputs!$B$13/Inputs!$B$32) -> 0.4 | H28: =IF(H$1=Inputs!$B$34,Inputs!$B$34,Inputs!$B$12*Inputs!$B$13/Inputs!$B$32) -> 0.4 | I28: =IF(I$1=Inputs!$B$34,Inputs!$B$34,Inputs!$B$12*Inputs!$B$13/Inputs!$B$32) -> 0.4 | ... DR28: =IF(DR$1=Inputs!$B$34,Inputs!$B$34,Inputs!$B$12*Inputs!$B$13/Inputs!$B$32) -> 0.4
A29: Other fixed recurring OPEX | B29: =IF(B$1=Inputs!$B$34,Inputs!$B$34,Inputs!$B$14) -> 0 | C29: =IF(C$1=Inputs!$B$34,Inputs!$B$34,Inputs!$B$14) -> 0.15 | D29: =IF(D$1=Inputs!$B$34,Inputs!$B$34,Inputs!$B$14) -> 0.15 | E29: =IF(E$1=Inputs!$B$34,Inputs!$B$34,Inputs!$B$14) -> 0.15 | F29: =IF(F$1=Inputs!$B$34,Inputs!$B$34,Inputs!$B$14) -> 0.15 | G29: =IF(G$1=Inputs!$B$34,Inputs!$B$34,Inputs!$B$14) -> 0.15 | H29: =IF(H$1=Inputs!$B$34,Inputs!$B$34,Inputs!$B$14) -> 0.15 | I29: =IF(I$1=Inputs!$B$34,Inputs!$B$34,Inputs!$B$14) -> 0.15 | ... DR29: =IF(DR$1=Inputs!$B$34,Inputs!$B$34,Inputs!$B$14) -> 0.15
A30: Variable recurring OPEX | B30: =B19*Inputs!$B$15 -> 0 | C30: =C19*Inputs!$B$15 -> 0 | D30: =D19*Inputs!$B$15 -> 0 | E30: =E19*Inputs!$B$15 -> 0 | F30: =F19*Inputs!$B$15 -> 0 | G30: =G19*Inputs!$B$15 -> 0 | H30: =H19*Inputs!$B$15 -> 1.2 | I30: =I19*Inputs!$B$15 -> 1.2 | ... DR30: =DR19*Inputs!$B$15 -> 2.8
A31: Recurring OPEX total | B31: =SUM(B28:B30) -> 0 | C31: =SUM(C28:C30) -> 0.55 | D31: =SUM(D28:D30) -> 0.55 | E31: =SUM(E28:E30) -> 0.55 | F31: =SUM(F28:F30) -> 0.55 | G31: =SUM(G28:G30) -> 0.55 | H31: =SUM(H28:H30) -> 1.75 | I31: =SUM(I28:I30) -> 1.75 | ... DR31: =SUM(DR28:DR30) -> 3.35
A32: Launch expenses | B32: =IF(AND(B$1>Inputs!$B$34,B$1<=Inputs!$B$19),Funding!$B$8/Inputs!$B$19,Inputs!$B$34) -> 0 | C32: =IF(AND(C$1>Inputs!$B$34,C$1<=Inputs!$B$19),Funding!$B$8/Inputs!$B$19,Inputs!$B$34) -> 0.58333333 | D32: =IF(AND(D$1>Inputs!$B$34,D$1<=Inputs!$B$19),Funding!$B$8/Inputs!$B$19,Inputs!$B$34) -> 0.58333333 | E32: =IF(AND(E$1>Inputs!$B$34,E$1<=Inputs!$B$19),Funding!$B$8/Inputs!$B$19,Inputs!$B$34) -> 0.58333333 | F32: =IF(AND(F$1>Inputs!$B$34,F$1<=Inputs!$B$19),Funding!$B$8/Inputs!$B$19,Inputs!$B$34) -> 0.58333333 | G32: =IF(AND(G$1>Inputs!$B$34,G$1<=Inputs!$B$19),Funding!$B$8/Inputs!$B$19,Inputs!$B$34) -> 0.58333333 | H32: =IF(AND(H$1>Inputs!$B$34,H$1<=Inputs!$B$19),Funding!$B$8/Inputs!$B$19,Inputs!$B$34) -> 0.58333333 | I32: =IF(AND(I$1>Inputs!$B$34,I$1<=Inputs!$B$19),Funding!$B$8/Inputs!$B$19,Inputs!$B$34) -> 0.58333333 | ... DR32: =IF(AND(DR$1>Inputs!$B$34,DR$1<=Inputs!$B$19),Funding!$B$8/Inputs!$B$19,Inputs!$B$34) -> 0
A33: Total actual modeled OPEX | B33: =B31+B32 -> 0 | C33: =C31+C32 -> 1.1333333 | D33: =D31+D32 -> 1.1333333 | E33: =E31+E32 -> 1.1333333 | F33: =F31+F32 -> 1.1333333 | G33: =G31+G32 -> 1.1333333 | H33: =H31+H32 -> 2.3333333 | I33: =I31+I32 -> 2.3333333 | ... DR33: =DR31+DR32 -> 3.35
A34: Reserve less actual OPEX (memo) | B34: =B26-B33 -> 0 | C34: =C26-C33 -> -1.1333333 | D34: =D26-D33 -> -1.1333333 | E34: =E26-E33 -> -1.1333333 | F34: =F26-F33 -> -1.1333333 | G34: =G26-G33 -> -1.1333333 | H34: =H26-H33 -> 0.66666667 | I34: =I26-I33 -> 0.66666667 | ... DR34: =DR26-DR33 -> 3.65
A35: EBITDA after government allocation | B35: =B19-B23-B33 -> 0 | C35: =C19-C23-C33 -> -1.1333333 | D35: =D19-D23-D33 -> -1.1333333 | E35: =E19-E23-E33 -> -1.1333333 | F35: =F19-F23-F33 -> -1.1333333 | G35: =G19-G23-G33 -> -1.1333333 | H35: =H19-H23-H33 -> 6.6666667 | I35: =I19-I23-I33 -> 6.6666667 | ... DR35: =DR19-DR23-DR33 -> 17.65
A36: Initial capex | B36: =IF(AND(B$1>Inputs!$B$34,B$1<=Inputs!$B$19),Funding!$C$7/Inputs!$B$19,Inputs!$B$34) -> 0 | C36: =IF(AND(C$1>Inputs!$B$34,C$1<=Inputs!$B$19),Funding!$C$7/Inputs!$B$19,Inputs!$B$34) -> 3.5833333 | D36: =IF(AND(D$1>Inputs!$B$34,D$1<=Inputs!$B$19),Funding!$C$7/Inputs!$B$19,Inputs!$B$34) -> 3.5833333 | E36: =IF(AND(E$1>Inputs!$B$34,E$1<=Inputs!$B$19),Funding!$C$7/Inputs!$B$19,Inputs!$B$34) -> 3.5833333 | F36: =IF(AND(F$1>Inputs!$B$34,F$1<=Inputs!$B$19),Funding!$C$7/Inputs!$B$19,Inputs!$B$34) -> 3.5833333 | G36: =IF(AND(G$1>Inputs!$B$34,G$1<=Inputs!$B$19),Funding!$C$7/Inputs!$B$19,Inputs!$B$34) -> 3.5833333 | H36: =IF(AND(H$1>Inputs!$B$34,H$1<=Inputs!$B$19),Funding!$C$7/Inputs!$B$19,Inputs!$B$34) -> 3.5833333 | I36: =IF(AND(I$1>Inputs!$B$34,I$1<=Inputs!$B$19),Funding!$C$7/Inputs!$B$19,Inputs!$B$34) -> 3.5833333 | ... DR36: =IF(AND(DR$1>Inputs!$B$34,DR$1<=Inputs!$B$19),Funding!$C$7/Inputs!$B$19,Inputs!$B$34) -> 0
A37: Maintenance capex | B37: =IF(B$1>Inputs!$B$19,B19*Inputs!$B$21,Inputs!$B$34) -> 0 | C37: =IF(C$1>Inputs!$B$19,C19*Inputs!$B$21,Inputs!$B$34) -> 0 | D37: =IF(D$1>Inputs!$B$19,D19*Inputs!$B$21,Inputs!$B$34) -> 0 | E37: =IF(E$1>Inputs!$B$19,E19*Inputs!$B$21,Inputs!$B$34) -> 0 | F37: =IF(F$1>Inputs!$B$19,F19*Inputs!$B$21,Inputs!$B$34) -> 0 | G37: =IF(G$1>Inputs!$B$19,G19*Inputs!$B$21,Inputs!$B$34) -> 0 | H37: =IF(H$1>Inputs!$B$19,H19*Inputs!$B$21,Inputs!$B$34) -> 0 | I37: =IF(I$1>Inputs!$B$19,I19*Inputs!$B$21,Inputs!$B$34) -> 0 | ... DR37: =IF(DR$1>Inputs!$B$19,DR19*Inputs!$B$21,Inputs!$B$34) -> 0.35
A38: Total capex | B38: =B36+B37 -> 0 | C38: =C36+C37 -> 3.5833333 | D38: =D36+D37 -> 3.5833333 | E38: =E36+E37 -> 3.5833333 | F38: =F36+F37 -> 3.5833333 | G38: =G36+G37 -> 3.5833333 | H38: =H36+H37 -> 3.5833333 | I38: =I36+I37 -> 3.5833333 | ... DR38: =DR36+DR37 -> 0.35
A39: Depreciation | B39: =SUM(INDEX($B$38:B38,Inputs!$B$35,MAX(Inputs!$B$35,COLUMN()-Inputs!$B$20)): B38)/Inputs!$B$20 -> 0 | C39: =SUM(INDEX($B$38:C38,Inputs!$B$35,MAX(Inputs!$B$35,COLUMN()-Inputs!$B$20)): C38)/Inputs!$B$20 -> 0.059722222 | D39: =SUM(INDEX($B$38:D38,Inputs!$B$35,MAX(Inputs!$B$35,COLUMN()-Inputs!$B$20)): D38)/Inputs!$B$20 -> 0.11944444 | E39: =SUM(INDEX($B$38:E38,Inputs!$B$35,MAX(Inputs!$B$35,COLUMN()-Inputs!$B$20)): E38)/Inputs!$B$20 -> 0.17916667 | F39: =SUM(INDEX($B$38:F38,Inputs!$B$35,MAX(Inputs!$B$35,COLUMN()-Inputs!$B$20)): F38)/Inputs!$B$20 -> 0.23888889 | G39: =SUM(INDEX($B$38:G38,Inputs!$B$35,MAX(Inputs!$B$35,COLUMN()-Inputs!$B$20)): G38)/Inputs!$B$20 -> 0.29861111 | H39: =SUM(INDEX($B$38:H38,Inputs!$B$35,MAX(Inputs!$B$35,COLUMN()-Inputs!$B$20)): H38)/Inputs!$B$20 -> 0.35833333 | I39: =SUM(INDEX($B$38:I38,Inputs!$B$35,MAX(Inputs!$B$35,COLUMN()-Inputs!$B$20)): I38)/Inputs!$B$20 -> 0.41805556 | ... DR39: =SUM(INDEX($B$38:DR38,Inputs!$B$35,MAX(Inputs!$B$35,COLUMN()-Inputs!$B$20)): DR38)/Inputs!$B$20 -> 0.35
A40: EBIT | B40: =B35-B39 -> 0 | C40: =C35-C39 -> -1.1930556 | D40: =D35-D39 -> -1.2527778 | E40: =E35-E39 -> -1.3125 | F40: =F35-F39 -> -1.3722222 | G40: =G35-G39 -> -1.4319444 | H40: =H35-H39 -> 6.3083333 | I40: =I35-I39 -> 6.2486111 | ... DR40: =DR35-DR39 -> 17.3
A41: Cash tax / tax expense | B41: =MAX(Inputs!$B$34,B40)*Inputs!$B$11 -> 0 | C41: =MAX(Inputs!$B$34,C40)*Inputs!$B$11 -> 0 | D41: =MAX(Inputs!$B$34,D40)*Inputs!$B$11 -> 0 | E41: =MAX(Inputs!$B$34,E40)*Inputs!$B$11 -> 0 | F41: =MAX(Inputs!$B$34,F40)*Inputs!$B$11 -> 0 | G41: =MAX(Inputs!$B$34,G40)*Inputs!$B$11 -> 0 | H41: =MAX(Inputs!$B$34,H40)*Inputs!$B$11 -> 1.8925 | I41: =MAX(Inputs!$B$34,I40)*Inputs!$B$11 -> 1.8745833 | ... DR41: =MAX(Inputs!$B$34,DR40)*Inputs!$B$11 -> 5.19
A42: Net income before owner distributions | B42: =B40-B41 -> 0 | C42: =C40-C41 -> -1.1930556 | D42: =D40-D41 -> -1.2527778 | E42: =E40-E41 -> -1.3125 | F42: =F40-F41 -> -1.3722222 | G42: =G40-G41 -> -1.4319444 | H42: =H40-H41 -> 4.4158333 | I42: =I40-I41 -> 4.3740278 | ... DR42: =DR40-DR41 -> 12.11
A43: AP closing | B43: =B31*Inputs!$B$17/Inputs!$B$18 -> 0 | C43: =C31*Inputs!$B$17/Inputs!$B$18 -> 0 | D43: =D31*Inputs!$B$17/Inputs!$B$18 -> 0 | E43: =E31*Inputs!$B$17/Inputs!$B$18 -> 0 | F43: =F31*Inputs!$B$17/Inputs!$B$18 -> 0 | G43: =G31*Inputs!$B$17/Inputs!$B$18 -> 0 | H43: =H31*Inputs!$B$17/Inputs!$B$18 -> 0 | I43: =I31*Inputs!$B$17/Inputs!$B$18 -> 0 | ... DR43: =DR31*Inputs!$B$17/Inputs!$B$18 -> 0
A44: Change in AP | B44: =B43-Inputs!$B$34 -> 0 | C44: =C43-B43 -> 0 | D44: =D43-C43 -> 0 | E44: =E43-D43 -> 0 | F44: =F43-E43 -> 0 | G44: =G43-F43 -> 0 | H44: =H43-G43 -> 0 | I44: =I43-H43 -> 0 | J44: =J43-I43 -> 0 | ... DR44: =DR43-DQ43 -> 0
A45: CFO = NI + DA - change AR + change AP | B45: =B42+B39-B21+B44 -> 0 | C45: =C42+C39-C21+C44 -> -1.1333333 | D45: =D42+D39-D21+D44 -> -1.1333333 | E45: =E42+E39-E21+E44 -> -1.1333333 | F45: =F42+F39-F21+F44 -> -1.1333333 | G45: =G42+G39-G21+G44 -> -1.1333333 | H45: =H42+H39-H21+H44 -> 4.7741667 | I45: =I42+I39-I21+I44 -> 4.7920833 | ... DR45: =DR42+DR39-DR21+DR44 -> 12.46
A46: CFI = capex outflow | B46: =-B38 -> 0 | C46: =-C38 -> -3.5833333 | D46: =-D38 -> -3.5833333 | E46: =-E38 -> -3.5833333 | F46: =-F38 -> -3.5833333 | G46: =-G38 -> -3.5833333 | H46: =-H38 -> -3.5833333 | I46: =-I38 -> -3.5833333 | ... DR46: =-DR38 -> -0.35
A47: Investor capital contributed | B47: =IF(B$1=Inputs!$B$34,Inputs!$B$22,IF(B$1=Inputs!$B$24,Inputs!$B$23,Inputs!$B$34)) -> 25 | C47: =IF(C$1=Inputs!$B$34,Inputs!$B$22,IF(C$1=Inputs!$B$24,Inputs!$B$23,Inputs!$B$34)) -> 0 | D47: =IF(D$1=Inputs!$B$34,Inputs!$B$22,IF(D$1=Inputs!$B$24,Inputs!$B$23,Inputs!$B$34)) -> 0 | E47: =IF(E$1=Inputs!$B$34,Inputs!$B$22,IF(E$1=Inputs!$B$24,Inputs!$B$23,Inputs!$B$34)) -> 0 | F47: =IF(F$1=Inputs!$B$34,Inputs!$B$22,IF(F$1=Inputs!$B$24,Inputs!$B$23,Inputs!$B$34)) -> 0 | G47: =IF(G$1=Inputs!$B$34,Inputs!$B$22,IF(G$1=Inputs!$B$24,Inputs!$B$23,Inputs!$B$34)) -> 0 | H47: =IF(H$1=Inputs!$B$34,Inputs!$B$22,IF(H$1=Inputs!$B$24,Inputs!$B$23,Inputs!$B$34)) -> 0 | I47: =IF(I$1=Inputs!$B$34,Inputs!$B$22,IF(I$1=Inputs!$B$24,Inputs!$B$23,Inputs!$B$34)) -> 0 | ... DR47: =IF(DR$1=Inputs!$B$34,Inputs!$B$22,IF(DR$1=Inputs!$B$24,Inputs!$B$23,Inputs!$B$34)) -> 0
A48: Owner distributions (investor + CDS) | B48: =B24+B27 -> 0 | C48: =C24+C27 -> 0 | D48: =D24+D27 -> 0 | E48: =E24+E27 -> 0 | F48: =F24+F27 -> 0 | G48: =G24+G27 -> 0 | H48: =H24+H27 -> 6 | I48: =I24+I27 -> 6 | ... DR48: =DR24+DR27 -> 14
A49: CFF = contributions - owner distributions | B49: =B47-B48 -> 25 | C49: =C47-C48 -> 0 | D49: =D47-D48 -> 0 | E49: =E47-E48 -> 0 | F49: =F47-F48 -> 0 | G49: =G47-G48 -> 0 | H49: =H47-H48 -> -6 | I49: =I47-I48 -> -6 | ... DR49: =DR47-DR48 -> -14
A50: Net cash flow | B50: =SUM(B45:B46)+B49 -> 25 | C50: =SUM(C45:C46)+C49 -> -4.7166667 | D50: =SUM(D45:D46)+D49 -> -4.7166667 | E50: =SUM(E45:E46)+E49 -> -4.7166667 | F50: =SUM(F45:F46)+F49 -> -4.7166667 | G50: =SUM(G45:G46)+G49 -> -4.7166667 | H50: =SUM(H45:H46)+H49 -> -4.8091667 | I50: =SUM(I45:I46)+I49 -> -4.79125 | ... DR50: =SUM(DR45:DR46)+DR49 -> -1.89
A51: Opening unfinanced cash | B51: =Inputs!$B$34 -> 0 | C51: =B52 -> 25 | D51: =C52 -> 20.283333 | E51: =D52 -> 15.566667 | F51: =E52 -> 10.85 | G51: =F52 -> 6.1333333 | H51: =G52 -> 1.4166667 | I51: =H52 -> -3.3925 | J51: =I52 -> -8.18375 | ... DR51: =DQ52 -> -202.49625
A52: Closing unfinanced cash | B52: =B51+B50 -> 25 | C52: =C51+C50 -> 20.283333 | D52: =D51+D50 -> 15.566667 | E52: =E51+E50 -> 10.85 | F52: =F51+F50 -> 6.1333333 | G52: =G51+G50 -> 1.4166667 | H52: =H51+H50 -> -3.3925 | I52: =I51+I50 -> -8.18375 | ... DR52: =DR51+DR50 -> -204.38625
A53: Funding gap at period end | B53: =MAX(Inputs!$B$34,-B52) -> 0 | C53: =MAX(Inputs!$B$34,-C52) -> 0 | D53: =MAX(Inputs!$B$34,-D52) -> 0 | E53: =MAX(Inputs!$B$34,-E52) -> 0 | F53: =MAX(Inputs!$B$34,-F52) -> 0 | G53: =MAX(Inputs!$B$34,-G52) -> 0 | H53: =MAX(Inputs!$B$34,-H52) -> 3.3925 | I53: =MAX(Inputs!$B$34,-I52) -> 8.18375 | ... DR53: =MAX(Inputs!$B$34,-DR52) -> 204.38625
A54: PP&E closing net | B54: =B38-B39 -> 0 | C54: =B54+C38-C39 -> 3.5236111 | D54: =C54+D38-D39 -> 6.9875 | E54: =D54+E38-E39 -> 10.391667 | F54: =E54+F38-F39 -> 13.736111 | G54: =F54+G38-G39 -> 17.020833 | H54: =G54+H38-H39 -> 20.245833 | I54: =H54+I38-I39 -> 23.411111 | J54: =I54+J38-J39 -> 26.516667 | ... DR54: =DQ54+DR38-DR39 -> 10.325
A55: Cumulative contributed capital | B55: =SUM($B47:B47) -> 25 | C55: =SUM($B47:C47) -> 25 | D55: =SUM($B47:D47) -> 25 | E55: =SUM($B47:E47) -> 25 | F55: =SUM($B47:F47) -> 25 | G55: =SUM($B47:G47) -> 25 | H55: =SUM($B47:H47) -> 25 | I55: =SUM($B47:I47) -> 25 | ... DR55: =SUM($B47:DR47) -> 50
A56: Retained earnings after distributions | B56: =B42-B48 -> 0 | C56: =B56+C42-C48 -> -1.1930556 | D56: =C56+D42-D48 -> -2.4458333 | E56: =D56+E42-E48 -> -3.7583333 | F56: =E56+F42-F48 -> -5.1305556 | G56: =F56+G42-G48 -> -6.5625 | H56: =G56+H42-H48 -> -8.1466667 | I56: =H56+I42-I48 -> -9.7726389 | J56: =I56+J42-J48 -> -11.440417 | ... DR56: =DQ56+DR42-DR48 -> -244.06125
A57: Total assets (cash may be unfunded) | B57: =B52+B20+B54 -> 25 | C57: =C52+C20+C54 -> 23.806944 | D57: =D52+D20+D54 -> 22.554167 | E57: =E52+E20+E54 -> 21.241667 | F57: =F52+F20+F54 -> 19.869444 | G57: =G52+G20+G54 -> 18.4375 | H57: =H52+H20+H54 -> 16.853333 | I57: =I52+I20+I54 -> 15.227361 | ... DR57: =DR52+DR20+DR54 -> -194.06125
A58: Total liabilities + equity | B58: =B43+B55+B56 -> 25 | C58: =C43+C55+C56 -> 23.806944 | D58: =D43+D55+D56 -> 22.554167 | E58: =E43+E55+E56 -> 21.241667 | F58: =F43+F55+F56 -> 19.869444 | G58: =G43+G55+G56 -> 18.4375 | H58: =H43+H55+H56 -> 16.853333 | I58: =I43+I55+I56 -> 15.227361 | ... DR58: =DR43+DR55+DR56 -> -194.06125
A59: Balance sheet check | B59: =B57-B58 -> 0 | C59: =C57-C58 -> 0 | D59: =D57-D58 -> 0 | E59: =E57-E58 -> 0 | F59: =F57-F58 -> 0 | G59: =G57-G58 -> 0 | H59: =H57-H58 -> 0 | I59: =I57-I58 -> 0 | ... DR59: =DR57-DR58 -> 0
A60: Cash roll-forward check | B60: =B52-B51-B50 -> 0 | C60: =C52-C51-C50 -> 0 | D60: =D52-D51-D50 -> 0 | E60: =E52-E51-E50 -> 0 | F60: =F52-F51-F50 -> 0 | G60: =G52-G51-G50 -> 0 | H60: =H52-H51-H50 -> 0 | I60: =I52-I51-I50 -> 0 | ... DR60: =DR52-DR51-DR50 -> 1.4210855e-14
A61: Allocation split check | B61: =B25-B26-B27 -> 0 | C61: =C25-C26-C27 -> 0 | D61: =D25-D26-D27 -> 0 | E61: =E25-E26-E27 -> 0 | F61: =F25-F26-F27 -> 0 | G61: =G25-G26-G27 -> 0 | H61: =H25-H26-H27 -> 0 | I61: =I25-I26-I27 -> 0 | ... DR61: =DR25-DR26-DR27 -> 0
A62: Investor net cash flow | B62: =B24-B47 -> -25 | C62: =C24-C47 -> 0 | D62: =D24-D47 -> 0 | E62: =E24-E47 -> 0 | F62: =F24-F47 -> 0 | G62: =G24-G47 -> 0 | H62: =H24-H47 -> 1.5 | I62: =I24-I47 -> 1.5 | ... DR62: =DR24-DR47 -> 3.5
A63: Investor cumulative net cash flow | B63: =SUM($B62:B62) -> -25 | C63: =SUM($B62:C62) -> -25 | D63: =SUM($B62:D62) -> -25 | E63: =SUM($B62:E62) -> -25 | F63: =SUM($B62:F62) -> -25 | G63: =SUM($B62:G62) -> -25 | H63: =SUM($B62:H62) -> -23.5 | I63: =SUM($B62:I62) -> -22 | ... DR63: =SUM($B62:DR62) -> 343.5
A64: Investor cumulative distributions | B64: =SUM($B24:B24) -> 0 | C64: =SUM($B24:C24) -> 0 | D64: =SUM($B24:D24) -> 0 | E64: =SUM($B24:E24) -> 0 | F64: =SUM($B24:F24) -> 0 | G64: =SUM($B24:G24) -> 0 | H64: =SUM($B24:H24) -> 1.5 | I64: =SUM($B24:I24) -> 3 | ... DR64: =SUM($B24:DR24) -> 393.5
A65: Gross share source entitlement | B65: =B19*Inputs!$B$5 -> 0 | C65: =C19*Inputs!$B$5 -> 0 | D65: =D19*Inputs!$B$5 -> 0 | E65: =E19*Inputs!$B$5 -> 0 | F65: =F19*Inputs!$B$5 -> 0 | G65: =G19*Inputs!$B$5 -> 0 | H65: =H19*Inputs!$B$5 -> 1.5 | I65: =I19*Inputs!$B$5 -> 1.5 | ... DR65: =DR19*Inputs!$B$5 -> 3.5
A66: Revenue stream tie check | B66: =B19-B4 -> 0 | C66: =C19-C4 -> 0 | D66: =D19-D4 -> 0 | E66: =E19-E4 -> 0 | F66: =F19-F4 -> 0 | G66: =G19-G4 -> 0 | H66: =H19-H4 -> 0 | I66: =I19-I4 -> 0 | ... DR66: =DR19-DR4 -> 0
A67: Investor CF after all committed funding reserved | B67: =B64-SUM($B$47:$DR$47) -> -50 | C67: =C64-SUM($B$47:$DR$47) -> -50 | D67: =D64-SUM($B$47:$DR$47) -> -50 | E67: =E64-SUM($B$47:$DR$47) -> -50 | F67: =F64-SUM($B$47:$DR$47) -> -50 | G67: =G64-SUM($B$47:$DR$47) -> -50 | H67: =H64-SUM($B$47:$DR$47) -> -48.5 | I67: =I64-SUM($B$47:$DR$47) -> -47 | ... DR67: =DR64-SUM($B$47:$DR$47) -> 343.5
A68: Cash receipt negative flag | B68: =IF(B22<-Inputs!$B$33,Inputs!$B$35,Inputs!$B$34) -> 0 | C68: =IF(C22<-Inputs!$B$33,Inputs!$B$35,Inputs!$B$34) -> 0 | D68: =IF(D22<-Inputs!$B$33,Inputs!$B$35,Inputs!$B$34) -> 0 | E68: =IF(E22<-Inputs!$B$33,Inputs!$B$35,Inputs!$B$34) -> 0 | F68: =IF(F22<-Inputs!$B$33,Inputs!$B$35,Inputs!$B$34) -> 0 | G68: =IF(G22<-Inputs!$B$33,Inputs!$B$35,Inputs!$B$34) -> 0 | H68: =IF(H22<-Inputs!$B$33,Inputs!$B$35,Inputs!$B$34) -> 0 | I68: =IF(I22<-Inputs!$B$33,Inputs!$B$35,Inputs!$B$34) -> 0 | ... DR68: =IF(DR22<-Inputs!$B$33,Inputs!$B$35,Inputs!$B$34) -> 0

Sheet Ramp annual
A1: Month index | B1: =Inputs!$B$34 -> 0 | C1: =B1+Inputs!$B$35 -> 1 | D1: =C1+Inputs!$B$35 -> 2 | E1: =D1+Inputs!$B$35 -> 3 | F1: =E1+Inputs!$B$35 -> 4 | G1: =F1+Inputs!$B$35 -> 5 | H1: =G1+Inputs!$B$35 -> 6 | I1: =H1+Inputs!$B$35 -> 7 | J1: =I1+Inputs!$B$35 -> 8 | ... L1: =K1+Inputs!$B$35 -> 10
A2: Model year | B2: =B1 -> 0 | C2: =C1 -> 1 | D2: =D1 -> 2 | E2: =E1 -> 3 | F2: =F1 -> 4 | G2: =G1 -> 5 | H2: =H1 -> 6 | I2: =I1 -> 7 | ... L2: =L1 -> 10
A3: Case target before VAT B | B3: =Ramp!B3 -> 0 | C3: =SUM(Ramp!C3:N3) -> 155 | D3: =SUM(Ramp!O3:Z3) -> 420 | E3: =SUM(Ramp!AA3:AL3) -> 420 | F3: =SUM(Ramp!AM3:AX3) -> 420 | G3: =SUM(Ramp!AY3:BJ3) -> 420 | H3: =SUM(Ramp!BK3:BV3) -> 420 | I3: =SUM(Ramp!BW3:CH3) -> 420 | J3: =SUM(Ramp!CI3:CT3) -> 420 | K3: =SUM(Ramp!CU3:DF3) -> 420 | L3: =SUM(Ramp!DG3:DR3) -> 420
A4: Revenue base excluding VAT | B4: =Ramp!B4 -> 0 | C4: =SUM(Ramp!C4:N4) -> 155 | D4: =SUM(Ramp!O4:Z4) -> 420 | E4: =SUM(Ramp!AA4:AL4) -> 420 | F4: =SUM(Ramp!AM4:AX4) -> 420 | G4: =SUM(Ramp!AY4:BJ4) -> 420 | H4: =SUM(Ramp!BK4:BV4) -> 420 | I4: =SUM(Ramp!BW4:CH4) -> 420 | J4: =SUM(Ramp!CI4:CT4) -> 420 | K4: =SUM(Ramp!CU4:DF4) -> 420 | L4: =SUM(Ramp!DG4:DR4) -> 420
A5: VAT excluded from base (informational) | B5: =Ramp!B5 -> 0 | C5: =SUM(Ramp!C5:N5) -> 0 | D5: =SUM(Ramp!O5:Z5) -> 0 | E5: =SUM(Ramp!AA5:AL5) -> 0 | F5: =SUM(Ramp!AM5:AX5) -> 0 | G5: =SUM(Ramp!AY5:BJ5) -> 0 | H5: =SUM(Ramp!BK5:BV5) -> 0 | I5: =SUM(Ramp!BW5:CH5) -> 0 | J5: =SUM(Ramp!CI5:CT5) -> 0 | K5: =SUM(Ramp!CU5:DF5) -> 0 | L5: =SUM(Ramp!DG5:DR5) -> 0
A6: Pumps revenue | B6: =Ramp!B6 -> 0 | C6: =SUM(Ramp!C6:N6) -> 35.428571 | D6: =SUM(Ramp!O6:Z6) -> 96 | E6: =SUM(Ramp!AA6:AL6) -> 96 | F6: =SUM(Ramp!AM6:AX6) -> 96 | G6: =SUM(Ramp!AY6:BJ6) -> 96 | H6: =SUM(Ramp!BK6:BV6) -> 96 | I6: =SUM(Ramp!BW6:CH6) -> 96 | J6: =SUM(Ramp!CI6:CT6) -> 96 | K6: =SUM(Ramp!CU6:DF6) -> 96 | L6: =SUM(Ramp!DG6:DR6) -> 96
A7: Tankers revenue | B7: =Ramp!B7 -> 0 | C7: =SUM(Ramp!C7:N7) -> 13.285714 | D7: =SUM(Ramp!O7:Z7) -> 36 | E7: =SUM(Ramp!AA7:AL7) -> 36 | F7: =SUM(Ramp!AM7:AX7) -> 36 | G7: =SUM(Ramp!AY7:BJ7) -> 36 | H7: =SUM(Ramp!BK7:BV7) -> 36 | I7: =SUM(Ramp!BW7:CH7) -> 36 | J7: =SUM(Ramp!CI7:CT7) -> 36 | K7: =SUM(Ramp!CU7:DF7) -> 36 | L7: =SUM(Ramp!DG7:DR7) -> 36
A8: Depots revenue | B8: =Ramp!B8 -> 0 | C8: =SUM(Ramp!C8:N8) -> 4.4285714 | D8: =SUM(Ramp!O8:Z8) -> 12 | E8: =SUM(Ramp!AA8:AL8) -> 12 | F8: =SUM(Ramp!AM8:AX8) -> 12 | G8: =SUM(Ramp!AY8:BJ8) -> 12 | H8: =SUM(Ramp!BK8:BV8) -> 12 | I8: =SUM(Ramp!BW8:CH8) -> 12 | J8: =SUM(Ramp!CI8:CT8) -> 12 | K8: =SUM(Ramp!CU8:DF8) -> 12 | L8: =SUM(Ramp!DG8:DR8) -> 12
A9: Retail scales revenue | B9: =Ramp!B9 -> 0 | C9: =SUM(Ramp!C9:N9) -> 19.928571 | D9: =SUM(Ramp!O9:Z9) -> 54 | E9: =SUM(Ramp!AA9:AL9) -> 54 | F9: =SUM(Ramp!AM9:AX9) -> 54 | G9: =SUM(Ramp!AY9:BJ9) -> 54 | H9: =SUM(Ramp!BK9:BV9) -> 54 | I9: =SUM(Ramp!BW9:CH9) -> 54 | J9: =SUM(Ramp!CI9:CT9) -> 54 | K9: =SUM(Ramp!CU9:DF9) -> 54 | L9: =SUM(Ramp!DG9:DR9) -> 54
A10: Scanners revenue | B10: =Ramp!B10 -> 0 | C10: =SUM(Ramp!C10:N10) -> 6.6428571 | D10: =SUM(Ramp!O10:Z10) -> 18 | E10: =SUM(Ramp!AA10:AL10) -> 18 | F10: =SUM(Ramp!AM10:AX10) -> 18 | G10: =SUM(Ramp!AY10:BJ10) -> 18 | H10: =SUM(Ramp!BK10:BV10) -> 18 | I10: =SUM(Ramp!BW10:CH10) -> 18 | J10: =SUM(Ramp!CI10:CT10) -> 18 | K10: =SUM(Ramp!CU10:DF10) -> 18 | L10: =SUM(Ramp!DG10:DR10) -> 18
A11: Electricity meters revenue | B11: =Ramp!B11 -> 0 | C11: =SUM(Ramp!C11:N11) -> 22.142857 | D11: =SUM(Ramp!O11:Z11) -> 60 | E11: =SUM(Ramp!AA11:AL11) -> 60 | F11: =SUM(Ramp!AM11:AX11) -> 60 | G11: =SUM(Ramp!AY11:BJ11) -> 60 | H11: =SUM(Ramp!BK11:BV11) -> 60 | I11: =SUM(Ramp!BW11:CH11) -> 60 | J11: =SUM(Ramp!CI11:CT11) -> 60 | K11: =SUM(Ramp!CU11:DF11) -> 60 | L11: =SUM(Ramp!DG11:DR11) -> 60
A12: Telecom billing revenue | B12: =Ramp!B12 -> 0 | C12: =SUM(Ramp!C12:N12) -> 11.071429 | D12: =SUM(Ramp!O12:Z12) -> 30 | E12: =SUM(Ramp!AA12:AL12) -> 30 | F12: =SUM(Ramp!AM12:AX12) -> 30 | G12: =SUM(Ramp!AY12:BJ12) -> 30 | H12: =SUM(Ramp!BK12:BV12) -> 30 | I12: =SUM(Ramp!BW12:CH12) -> 30 | J12: =SUM(Ramp!CI12:CT12) -> 30 | K12: =SUM(Ramp!CU12:DF12) -> 30 | L12: =SUM(Ramp!DG12:DR12) -> 30
A13: Banking ICT revenue | B13: =Ramp!B13 -> 0 | C13: =SUM(Ramp!C13:N13) -> 6.6428571 | D13: =SUM(Ramp!O13:Z13) -> 18 | E13: =SUM(Ramp!AA13:AL13) -> 18 | F13: =SUM(Ramp!AM13:AX13) -> 18 | G13: =SUM(Ramp!AY13:BJ13) -> 18 | H13: =SUM(Ramp!BK13:BV13) -> 18 | I13: =SUM(Ramp!BW13:CH13) -> 18 | J13: =SUM(Ramp!CI13:CT13) -> 18 | K13: =SUM(Ramp!CU13:DF13) -> 18 | L13: =SUM(Ramp!DG13:DR13) -> 18
A14: Manufacturing weighbridges revenue | B14: =Ramp!B14 -> 0 | C14: =SUM(Ramp!C14:N14) -> 13.285714 | D14: =SUM(Ramp!O14:Z14) -> 36 | E14: =SUM(Ramp!AA14:AL14) -> 36 | F14: =SUM(Ramp!AM14:AX14) -> 36 | G14: =SUM(Ramp!AY14:BJ14) -> 36 | H14: =SUM(Ramp!BK14:BV14) -> 36 | I14: =SUM(Ramp!BW14:CH14) -> 36 | J14: =SUM(Ramp!CI14:CT14) -> 36 | K14: =SUM(Ramp!CU14:DF14) -> 36 | L14: =SUM(Ramp!DG14:DR14) -> 36
... A19: Total stream revenue | B19: =Ramp!B19 -> 0 | C19: =SUM(Ramp!C19:N19) -> 155 | D19: =SUM(Ramp!O19:Z19) -> 420 | E19: =SUM(Ramp!AA19:AL19) -> 420 | F19: =SUM(Ramp!AM19:AX19) -> 420 | G19: =SUM(Ramp!AY19:BJ19) -> 420 | H19: =SUM(Ramp!BK19:BV19) -> 420 | I19: =SUM(Ramp!BW19:CH19) -> 420 | J19: =SUM(Ramp!CI19:CT19) -> 420 | K19: =SUM(Ramp!CU19:DF19) -> 420 | L19: =SUM(Ramp!DG19:DR19) -> 420
A20: AR closing | B20: =Ramp!B20 -> 0 | C20: =Ramp!N20 -> 0 | D20: =Ramp!Z20 -> 0 | E20: =Ramp!AL20 -> 0 | F20: =Ramp!AX20 -> 0 | G20: =Ramp!BJ20 -> 0 | H20: =Ramp!BV20 -> 0 | I20: =Ramp!CH20 -> 0 | J20: =Ramp!CT20 -> 0 | K20: =Ramp!DF20 -> 0 | L20: =Ramp!DR20 -> 0
A21: Change in AR | B21: =Ramp!B21 -> 0 | C21: =SUM(Ramp!C21:N21) -> 0 | D21: =SUM(Ramp!O21:Z21) -> 0 | E21: =SUM(Ramp!AA21:AL21) -> 0 | F21: =SUM(Ramp!AM21:AX21) -> 0 | G21: =SUM(Ramp!AY21:BJ21) -> 0 | H21: =SUM(Ramp!BK21:BV21) -> 0 | I21: =SUM(Ramp!BW21:CH21) -> 0 | J21: =SUM(Ramp!CI21:CT21) -> 0 | K21: =SUM(Ramp!CU21:DF21) -> 0 | L21: =SUM(Ramp!DG21:DR21) -> 0
A22: Cash receipts | B22: =Ramp!B22 -> 0 | C22: =SUM(Ramp!C22:N22) -> 155 | D22: =SUM(Ramp!O22:Z22) -> 420 | E22: =SUM(Ramp!AA22:AL22) -> 420 | F22: =SUM(Ramp!AM22:AX22) -> 420 | G22: =SUM(Ramp!AY22:BJ22) -> 420 | H22: =SUM(Ramp!BK22:BV22) -> 420 | I22: =SUM(Ramp!BW22:CH22) -> 420 | J22: =SUM(Ramp!CI22:CT22) -> 420 | K22: =SUM(Ramp!CU22:DF22) -> 420 | L22: =SUM(Ramp!DG22:DR22) -> 420
A23: Government allocation expense / cash paid | B23: =Ramp!B23 -> 0 | C23: =SUM(Ramp!C23:N23) -> 62 | D23: =SUM(Ramp!O23:Z23) -> 168 | E23: =SUM(Ramp!AA23:AL23) -> 168 | F23: =SUM(Ramp!AM23:AX23) -> 168 | G23: =SUM(Ramp!AY23:BJ23) -> 168 | H23: =SUM(Ramp!BK23:BV23) -> 168 | I23: =SUM(Ramp!BW23:CH23) -> 168 | J23: =SUM(Ramp!CI23:CT23) -> 168 | K23: =SUM(Ramp!CU23:DF23) -> 168 | L23: =SUM(Ramp!DG23:DR23) -> 168
A24: Investor distribution entitlement | B24: =Ramp!B24 -> 0 | C24: =SUM(Ramp!C24:N24) -> 15.5 | D24: =SUM(Ramp!O24:Z24) -> 42 | E24: =SUM(Ramp!AA24:AL24) -> 42 | F24: =SUM(Ramp!AM24:AX24) -> 42 | G24: =SUM(Ramp!AY24:BJ24) -> 42 | H24: =SUM(Ramp!BK24:BV24) -> 42 | I24: =SUM(Ramp!BW24:CH24) -> 42 | J24: =SUM(Ramp!CI24:CT24) -> 42 | K24: =SUM(Ramp!CU24:DF24) -> 42 | L24: =SUM(Ramp!DG24:DR24) -> 42
A25: CDS legal 50% of receipts (memo) | B25: =Ramp!B25 -> 0 | C25: =SUM(Ramp!C25:N25) -> 77.5 | D25: =SUM(Ramp!O25:Z25) -> 210 | E25: =SUM(Ramp!AA25:AL25) -> 210 | F25: =SUM(Ramp!AM25:AX25) -> 210 | G25: =SUM(Ramp!AY25:BJ25) -> 210 | H25: =SUM(Ramp!BK25:BV25) -> 210 | I25: =SUM(Ramp!BW25:CH25) -> 210 | J25: =SUM(Ramp!CI25:CT25) -> 210 | K25: =SUM(Ramp!CU25:DF25) -> 210 | L25: =SUM(Ramp!DG25:DR25) -> 210
A26: OPEX reserve 20% receipts (memo) | B26: =Ramp!B26 -> 0 | C26: =SUM(Ramp!C26:N26) -> 31 | D26: =SUM(Ramp!O26:Z26) -> 84 | E26: =SUM(Ramp!AA26:AL26) -> 84 | F26: =SUM(Ramp!AM26:AX26) -> 84 | G26: =SUM(Ramp!AY26:BJ26) -> 84 | H26: =SUM(Ramp!BK26:BV26) -> 84 | I26: =SUM(Ramp!BW26:CH26) -> 84 | J26: =SUM(Ramp!CI26:CT26) -> 84 | K26: =SUM(Ramp!CU26:DF26) -> 84 | L26: =SUM(Ramp!DG26:DR26) -> 84
A27: CDS distribution 30% receipts | B27: =Ramp!B27 -> 0 | C27: =SUM(Ramp!C27:N27) -> 46.5 | D27: =SUM(Ramp!O27:Z27) -> 126 | E27: =SUM(Ramp!AA27:AL27) -> 126 | F27: =SUM(Ramp!AM27:AX27) -> 126 | G27: =SUM(Ramp!AY27:BJ27) -> 126 | H27: =SUM(Ramp!BK27:BV27) -> 126 | I27: =SUM(Ramp!BW27:CH27) -> 126 | J27: =SUM(Ramp!CI27:CT27) -> 126 | K27: =SUM(Ramp!CU27:DF27) -> 126 | L27: =SUM(Ramp!DG27:DR27) -> 126
A28: Personnel recurring OPEX | B28: =Ramp!B28 -> 0 | C28: =SUM(Ramp!C28:N28) -> 4.8 | D28: =SUM(Ramp!O28:Z28) -> 4.8 | E28: =SUM(Ramp!AA28:AL28) -> 4.8 | F28: =SUM(Ramp!AM28:AX28) -> 4.8 | G28: =SUM(Ramp!AY28:BJ28) -> 4.8 | H28: =SUM(Ramp!BK28:BV28) -> 4.8 | I28: =SUM(Ramp!BW28:CH28) -> 4.8 | J28: =SUM(Ramp!CI28:CT28) -> 4.8 | K28: =SUM(Ramp!CU28:DF28) -> 4.8 | L28: =SUM(Ramp!DG28:DR28) -> 4.8
A29: Other fixed recurring OPEX | B29: =Ramp!B29 -> 0 | C29: =SUM(Ramp!C29:N29) -> 1.8 | D29: =SUM(Ramp!O29:Z29) -> 1.8 | E29: =SUM(Ramp!AA29:AL29) -> 1.8 | F29: =SUM(Ramp!AM29:AX29) -> 1.8 | G29: =SUM(Ramp!AY29:BJ29) -> 1.8 | H29: =SUM(Ramp!BK29:BV29) -> 1.8 | I29: =SUM(Ramp!BW29:CH29) -> 1.8 | J29: =SUM(Ramp!CI29:CT29) -> 1.8 | K29: =SUM(Ramp!CU29:DF29) -> 1.8 | L29: =SUM(Ramp!DG29:DR29) -> 1.8
A30: Variable recurring OPEX | B30: =Ramp!B30 -> 0 | C30: =SUM(Ramp!C30:N30) -> 12.4 | D30: =SUM(Ramp!O30:Z30) -> 33.6 | E30: =SUM(Ramp!AA30:AL30) -> 33.6 | F30: =SUM(Ramp!AM30:AX30) -> 33.6 | G30: =SUM(Ramp!AY30:BJ30) -> 33.6 | H30: =SUM(Ramp!BK30:BV30) -> 33.6 | I30: =SUM(Ramp!BW30:CH30) -> 33.6 | J30: =SUM(Ramp!CI30:CT30) -> 33.6 | K30: =SUM(Ramp!CU30:DF30) -> 33.6 | L30: =SUM(Ramp!DG30:DR30) -> 33.6
A31: Recurring OPEX total | B31: =Ramp!B31 -> 0 | C31: =SUM(Ramp!C31:N31) -> 19 | D31: =SUM(Ramp!O31:Z31) -> 40.2 | E31: =SUM(Ramp!AA31:AL31) -> 40.2 | F31: =SUM(Ramp!AM31:AX31) -> 40.2 | G31: =SUM(Ramp!AY31:BJ31) -> 40.2 | H31: =SUM(Ramp!BK31:BV31) -> 40.2 | I31: =SUM(Ramp!BW31:CH31) -> 40.2 | J31: =SUM(Ramp!CI31:CT31) -> 40.2 | K31: =SUM(Ramp!CU31:DF31) -> 40.2 | L31: =SUM(Ramp!DG31:DR31) -> 40.2
A32: Launch expenses | B32: =Ramp!B32 -> 0 | C32: =SUM(Ramp!C32:N32) -> 7 | D32: =SUM(Ramp!O32:Z32) -> 0 | E32: =SUM(Ramp!AA32:AL32) -> 0 | F32: =SUM(Ramp!AM32:AX32) -> 0 | G32: =SUM(Ramp!AY32:BJ32) -> 0 | H32: =SUM(Ramp!BK32:BV32) -> 0 | I32: =SUM(Ramp!BW32:CH32) -> 0 | J32: =SUM(Ramp!CI32:CT32) -> 0 | K32: =SUM(Ramp!CU32:DF32) -> 0 | L32: =SUM(Ramp!DG32:DR32) -> 0
... A42: Net income before owner distributions | B42: =Ramp!B42 -> 0 | C42: =SUM(Ramp!C42:N42) -> 41.670417 | D42: =SUM(Ramp!O42:Z42) -> 141.9215 | E42: =SUM(Ramp!AA42:AL42) -> 141.3335 | F42: =SUM(Ramp!AM42:AX42) -> 140.7455 | G42: =SUM(Ramp!AY42:BJ42) -> 140.1575 | H42: =SUM(Ramp!BK42:BV42) -> 142.83033 | I42: =SUM(Ramp!BW42:CH42) -> 145.32 | J42: =SUM(Ramp!CI42:CT42) -> 145.32 | K42: =SUM(Ramp!CU42:DF42) -> 145.32 | L42: =SUM(Ramp!DG42:DR42) -> 145.32
A43: AP closing | B43: =Ramp!B43 -> 0 | C43: =Ramp!N43 -> 0 | D43: =Ramp!Z43 -> 0 | E43: =Ramp!AL43 -> 0 | F43: =Ramp!AX43 -> 0 | G43: =Ramp!BJ43 -> 0 | H43: =Ramp!BV43 -> 0 | I43: =Ramp!CH43 -> 0 | J43: =Ramp!CT43 -> 0 | K43: =Ramp!DF43 -> 0 | L43: =Ramp!DR43 -> 0
A44: Change in AP | B44: =Ramp!B44 -> 0 | C44: =SUM(Ramp!C44:N44) -> 0 | D44: =SUM(Ramp!O44:Z44) -> 0 | E44: =SUM(Ramp!AA44:AL44) -> 0 | F44: =SUM(Ramp!AM44:AX44) -> 0 | G44: =SUM(Ramp!AY44:BJ44) -> 0 | H44: =SUM(Ramp!BK44:BV44) -> 0 | I44: =SUM(Ramp!BW44:CH44) -> 0 | J44: =SUM(Ramp!CI44:CT44) -> 0 | K44: =SUM(Ramp!CU44:DF44) -> 0 | L44: =SUM(Ramp!DG44:DR44) -> 0
A45: CFO = NI + DA - change AR + change AP | B45: =Ramp!B45 -> 0 | C45: =SUM(Ramp!C45:N45) -> 46.32875 | D45: =SUM(Ramp!O45:Z45) -> 150.9765 | E45: =SUM(Ramp!AA45:AL45) -> 151.2285 | F45: =SUM(Ramp!AM45:AX45) -> 151.4805 | G45: =SUM(Ramp!AY45:BJ45) -> 151.7325 | H45: =SUM(Ramp!BK45:BV45) -> 150.587 | I45: =SUM(Ramp!BW45:CH45) -> 149.52 | J45: =SUM(Ramp!CI45:CT45) -> 149.52 | K45: =SUM(Ramp!CU45:DF45) -> 149.52 | L45: =SUM(Ramp!DG45:DR45) -> 149.52
A46: CFI = capex outflow | B46: =Ramp!B46 -> 0 | C46: =SUM(Ramp!C46:N46) -> -43 | D46: =SUM(Ramp!O46:Z46) -> -4.2 | E46: =SUM(Ramp!AA46:AL46) -> -4.2 | F46: =SUM(Ramp!AM46:AX46) -> -4.2 | G46: =SUM(Ramp!AY46:BJ46) -> -4.2 | H46: =SUM(Ramp!BK46:BV46) -> -4.2 | I46: =SUM(Ramp!BW46:CH46) -> -4.2 | J46: =SUM(Ramp!CI46:CT46) -> -4.2 | K46: =SUM(Ramp!CU46:DF46) -> -4.2 | L46: =SUM(Ramp!DG46:DR46) -> -4.2
A47: Investor capital contributed | B47: =Ramp!B47 -> 25 | C47: =SUM(Ramp!C47:N47) -> 25 | D47: =SUM(Ramp!O47:Z47) -> 0 | E47: =SUM(Ramp!AA47:AL47) -> 0 | F47: =SUM(Ramp!AM47:AX47) -> 0 | G47: =SUM(Ramp!AY47:BJ47) -> 0 | H47: =SUM(Ramp!BK47:BV47) -> 0 | I47: =SUM(Ramp!BW47:CH47) -> 0 | J47: =SUM(Ramp!CI47:CT47) -> 0 | K47: =SUM(Ramp!CU47:DF47) -> 0 | L47: =SUM(Ramp!DG47:DR47) -> 0
A48: Owner distributions (investor + CDS) | B48: =Ramp!B48 -> 0 | C48: =SUM(Ramp!C48:N48) -> 62 | D48: =SUM(Ramp!O48:Z48) -> 168 | E48: =SUM(Ramp!AA48:AL48) -> 168 | F48: =SUM(Ramp!AM48:AX48) -> 168 | G48: =SUM(Ramp!AY48:BJ48) -> 168 | H48: =SUM(Ramp!BK48:BV48) -> 168 | I48: =SUM(Ramp!BW48:CH48) -> 168 | J48: =SUM(Ramp!CI48:CT48) -> 168 | K48: =SUM(Ramp!CU48:DF48) -> 168 | L48: =SUM(Ramp!DG48:DR48) -> 168
A49: CFF = contributions - owner distributions | B49: =Ramp!B49 -> 25 | C49: =SUM(Ramp!C49:N49) -> -37 | D49: =SUM(Ramp!O49:Z49) -> -168 | E49: =SUM(Ramp!AA49:AL49) -> -168 | F49: =SUM(Ramp!AM49:AX49) -> -168 | G49: =SUM(Ramp!AY49:BJ49) -> -168 | H49: =SUM(Ramp!BK49:BV49) -> -168 | I49: =SUM(Ramp!BW49:CH49) -> -168 | J49: =SUM(Ramp!CI49:CT49) -> -168 | K49: =SUM(Ramp!CU49:DF49) -> -168 | L49: =SUM(Ramp!DG49:DR49) -> -168
A50: Net cash flow | B50: =Ramp!B50 -> 25 | C50: =SUM(Ramp!C50:N50) -> -33.67125 | D50: =SUM(Ramp!O50:Z50) -> -21.2235 | E50: =SUM(Ramp!AA50:AL50) -> -20.9715 | F50: =SUM(Ramp!AM50:AX50) -> -20.7195 | G50: =SUM(Ramp!AY50:BJ50) -> -20.4675 | H50: =SUM(Ramp!BK50:BV50) -> -21.613 | I50: =SUM(Ramp!BW50:CH50) -> -22.68 | J50: =SUM(Ramp!CI50:CT50) -> -22.68 | K50: =SUM(Ramp!CU50:DF50) -> -22.68 | L50: =SUM(Ramp!DG50:DR50) -> -22.68
A51: Opening unfinanced cash | B51: =Ramp!B51 -> 0 | C51: =Ramp!C51 -> 25 | D51: =Ramp!O51 -> -8.67125 | E51: =Ramp!AA51 -> -29.89475 | F51: =Ramp!AM51 -> -50.86625 | G51: =Ramp!AY51 -> -71.58575 | H51: =Ramp!BK51 -> -92.05325 | I51: =Ramp!BW51 -> -113.66625 | J51: =Ramp!CI51 -> -136.34625 | K51: =Ramp!CU51 -> -159.02625 | L51: =Ramp!DG51 -> -181.70625
A52: Closing unfinanced cash | B52: =Ramp!B52 -> 25 | C52: =Ramp!N52 -> -8.67125 | D52: =Ramp!Z52 -> -29.89475 | E52: =Ramp!AL52 -> -50.86625 | F52: =Ramp!AX52 -> -71.58575 | G52: =Ramp!BJ52 -> -92.05325 | H52: =Ramp!BV52 -> -113.66625 | I52: =Ramp!CH52 -> -136.34625 | J52: =Ramp!CT52 -> -159.02625 | K52: =Ramp!DF52 -> -181.70625 | L52: =Ramp!DR52 -> -204.38625
A53: Funding gap at period end | B53: =Ramp!B53 -> 0 | C53: =Ramp!N53 -> 8.67125 | D53: =Ramp!Z53 -> 29.89475 | E53: =Ramp!AL53 -> 50.86625 | F53: =Ramp!AX53 -> 71.58575 | G53: =Ramp!BJ53 -> 92.05325 | H53: =Ramp!BV53 -> 113.66625 | I53: =Ramp!CH53 -> 136.34625 | J53: =Ramp!CT53 -> 159.02625 | K53: =Ramp!DF53 -> 181.70625 | L53: =Ramp!DR53 -> 204.38625
A54: PP&E closing net | B54: =Ramp!B54 -> 0 | C54: =Ramp!N54 -> 38.341667 | D54: =Ramp!Z54 -> 33.486667 | E54: =Ramp!AL54 -> 27.791667 | F54: =Ramp!AX54 -> 21.256667 | G54: =Ramp!BJ54 -> 13.881667 | H54: =Ramp!BV54 -> 10.325 | I54: =Ramp!CH54 -> 10.325 | J54: =Ramp!CT54 -> 10.325 | K54: =Ramp!DF54 -> 10.325 | L54: =Ramp!DR54 -> 10.325
A55: Cumulative contributed capital | B55: =Ramp!B55 -> 25 | C55: =Ramp!N55 -> 50 | D55: =Ramp!Z55 -> 50 | E55: =Ramp!AL55 -> 50 | F55: =Ramp!AX55 -> 50 | G55: =Ramp!BJ55 -> 50 | H55: =Ramp!BV55 -> 50 | I55: =Ramp!CH55 -> 50 | J55: =Ramp!CT55 -> 50 | K55: =Ramp!DF55 -> 50 | L55: =Ramp!DR55 -> 50
A56: Retained earnings after distributions | B56: =Ramp!B56 -> 0 | C56: =Ramp!N56 -> -20.329583 | D56: =Ramp!Z56 -> -46.408083 | E56: =Ramp!AL56 -> -73.074583 | F56: =Ramp!AX56 -> -100.32908 | G56: =Ramp!BJ56 -> -128.17158 | H56: =Ramp!BV56 -> -153.34125 | I56: =Ramp!CH56 -> -176.02125 | J56: =Ramp!CT56 -> -198.70125 | K56: =Ramp!DF56 -> -221.38125 | L56: =Ramp!DR56 -> -244.06125
A57: Total assets (cash may be unfunded) | B57: =Ramp!B57 -> 25 | C57: =Ramp!N57 -> 29.670417 | D57: =Ramp!Z57 -> 3.5919167 | E57: =Ramp!AL57 -> -23.074583 | F57: =Ramp!AX57 -> -50.329083 | G57: =Ramp!BJ57 -> -78.171583 | H57: =Ramp!BV57 -> -103.34125 | I57: =Ramp!CH57 -> -126.02125 | J57: =Ramp!CT57 -> -148.70125 | K57: =Ramp!DF57 -> -171.38125 | L57: =Ramp!DR57 -> -194.06125
A58: Total liabilities + equity | B58: =Ramp!B58 -> 25 | C58: =Ramp!N58 -> 29.670417 | D58: =Ramp!Z58 -> 3.5919167 | E58: =Ramp!AL58 -> -23.074583 | F58: =Ramp!AX58 -> -50.329083 | G58: =Ramp!BJ58 -> -78.171583 | H58: =Ramp!BV58 -> -103.34125 | I58: =Ramp!CH58 -> -126.02125 | J58: =Ramp!CT58 -> -148.70125 | K58: =Ramp!DF58 -> -171.38125 | L58: =Ramp!DR58 -> -194.06125
A59: Balance sheet check | B59: =Ramp!B59 -> 0 | C59: =SUM(Ramp!C59:N59) -> 0 | D59: =SUM(Ramp!O59:Z59) -> 8.5265128e-14 | E59: =SUM(Ramp!AA59:AL59) -> 3.0198066e-13 | F59: =SUM(Ramp!AM59:AX59) -> 0 | G59: =SUM(Ramp!AY59:BJ59) -> 0 | H59: =SUM(Ramp!BK59:BV59) -> 0 | I59: =SUM(Ramp!BW59:CH59) -> 0 | J59: =SUM(Ramp!CI59:CT59) -> 0 | K59: =SUM(Ramp!CU59:DF59) -> 0 | L59: =SUM(Ramp!DG59:DR59) -> 0
A60: Cash roll-forward check | B60: =Ramp!B60 -> 0 | C60: =SUM(Ramp!C60:N60) -> 0 | D60: =SUM(Ramp!O60:Z60) -> 0 | E60: =SUM(Ramp!AA60:AL60) -> 0 | F60: =SUM(Ramp!AM60:AX60) -> 0 | G60: =SUM(Ramp!AY60:BJ60) -> -1.4210855e-14 | H60: =SUM(Ramp!BK60:BV60) -> 7.1054274e-15 | I60: =SUM(Ramp!BW60:CH60) -> 2.8421709e-14 | J60: =SUM(Ramp!CI60:CT60) -> 1.7053026e-13 | K60: =SUM(Ramp!CU60:DF60) -> 1.7053026e-13 | L60: =SUM(Ramp!DG60:DR60) -> 1.7053026e-13
A61: Allocation split check | B61: =Ramp!B61 -> 0 | C61: =SUM(Ramp!C61:N61) -> 0 | D61: =SUM(Ramp!O61:Z61) -> 0 | E61: =SUM(Ramp!AA61:AL61) -> 0 | F61: =SUM(Ramp!AM61:AX61) -> 0 | G61: =SUM(Ramp!AY61:BJ61) -> 0 | H61: =SUM(Ramp!BK61:BV61) -> 0 | I61: =SUM(Ramp!BW61:CH61) -> 0 | J61: =SUM(Ramp!CI61:CT61) -> 0 | K61: =SUM(Ramp!CU61:DF61) -> 0 | L61: =SUM(Ramp!DG61:DR61) -> 0
A62: Investor net cash flow | B62: =Ramp!B62 -> -25 | C62: =SUM(Ramp!C62:N62) -> -9.5 | D62: =SUM(Ramp!O62:Z62) -> 42 | E62: =SUM(Ramp!AA62:AL62) -> 42 | F62: =SUM(Ramp!AM62:AX62) -> 42 | G62: =SUM(Ramp!AY62:BJ62) -> 42 | H62: =SUM(Ramp!BK62:BV62) -> 42 | I62: =SUM(Ramp!BW62:CH62) -> 42 | J62: =SUM(Ramp!CI62:CT62) -> 42 | K62: =SUM(Ramp!CU62:DF62) -> 42 | L62: =SUM(Ramp!DG62:DR62) -> 42
A63: Investor cumulative net cash flow | B63: =Ramp!B63 -> -25 | C63: =Ramp!N63 -> -34.5 | D63: =Ramp!Z63 -> 7.5 | E63: =Ramp!AL63 -> 49.5 | F63: =Ramp!AX63 -> 91.5 | G63: =Ramp!BJ63 -> 133.5 | H63: =Ramp!BV63 -> 175.5 | I63: =Ramp!CH63 -> 217.5 | J63: =Ramp!CT63 -> 259.5 | K63: =Ramp!DF63 -> 301.5 | L63: =Ramp!DR63 -> 343.5
A64: Investor cumulative distributions | B64: =Ramp!B64 -> 0 | C64: =Ramp!N64 -> 15.5 | D64: =Ramp!Z64 -> 57.5 | E64: =Ramp!AL64 -> 99.5 | F64: =Ramp!AX64 -> 141.5 | G64: =Ramp!BJ64 -> 183.5 | H64: =Ramp!BV64 -> 225.5 | I64: =Ramp!CH64 -> 267.5 | J64: =Ramp!CT64 -> 309.5 | K64: =Ramp!DF64 -> 351.5 | L64: =Ramp!DR64 -> 393.5
A65: Gross share source entitlement | B65: =Ramp!B65 -> 0 | C65: =SUM(Ramp!C65:N65) -> 15.5 | D65: =SUM(Ramp!O65:Z65) -> 42 | E65: =SUM(Ramp!AA65:AL65) -> 42 | F65: =SUM(Ramp!AM65:AX65) -> 42 | G65: =SUM(Ramp!AY65:BJ65) -> 42 | H65: =SUM(Ramp!BK65:BV65) -> 42 | I65: =SUM(Ramp!BW65:CH65) -> 42 | J65: =SUM(Ramp!CI65:CT65) -> 42 | K65: =SUM(Ramp!CU65:DF65) -> 42 | L65: =SUM(Ramp!DG65:DR65) -> 42
A66: Revenue stream tie check | B66: =Ramp!B66 -> 0 | C66: =SUM(Ramp!C66:N66) -> 0 | D66: =SUM(Ramp!O66:Z66) -> 0 | E66: =SUM(Ramp!AA66:AL66) -> 0 | F66: =SUM(Ramp!AM66:AX66) -> 0 | G66: =SUM(Ramp!AY66:BJ66) -> 0 | H66: =SUM(Ramp!BK66:BV66) -> 0 | I66: =SUM(Ramp!BW66:CH66) -> 0 | J66: =SUM(Ramp!CI66:CT66) -> 0 | K66: =SUM(Ramp!CU66:DF66) -> 0 | L66: =SUM(Ramp!DG66:DR66) -> 0
A67: Investor CF after all committed funding reserved | B67: =Ramp!B67 -> -50 | C67: =Ramp!N67 -> -34.5 | D67: =Ramp!Z67 -> 7.5 | E67: =Ramp!AL67 -> 49.5 | F67: =Ramp!AX67 -> 91.5 | G67: =Ramp!BJ67 -> 133.5 | H67: =Ramp!BV67 -> 175.5 | I67: =Ramp!CH67 -> 217.5 | J67: =Ramp!CT67 -> 259.5 | K67: =Ramp!DF67 -> 301.5 | L67: =Ramp!DR67 -> 343.5
A68: Cash receipt negative flag | B68: =Ramp!B68 -> 0 | C68: =SUM(Ramp!C68:N68) -> 0 | D68: =SUM(Ramp!O68:Z68) -> 0 | E68: =SUM(Ramp!AA68:AL68) -> 0 | F68: =SUM(Ramp!AM68:AX68) -> 0 | G68: =SUM(Ramp!AY68:BJ68) -> 0 | H68: =SUM(Ramp!BK68:BV68) -> 0 | I68: =SUM(Ramp!BW68:CH68) -> 0 | J68: =SUM(Ramp!CI68:CT68) -> 0 | K68: =SUM(Ramp!CU68:DF68) -> 0 | L68: =SUM(Ramp!DG68:DR68) -> 0

Sheet Downside
A1: Month index | B1: =Inputs!$B$34 -> 0 | C1: =B1+Inputs!$B$35 -> 1 | D1: =C1+Inputs!$B$35 -> 2 | E1: =D1+Inputs!$B$35 -> 3 | F1: =E1+Inputs!$B$35 -> 4 | G1: =F1+Inputs!$B$35 -> 5 | H1: =G1+Inputs!$B$35 -> 6 | I1: =H1+Inputs!$B$35 -> 7 | J1: =I1+Inputs!$B$35 -> 8 | ... DR1: =DQ1+Inputs!$B$35 -> 120
A2: Model year | B2: =ROUNDUP(B$1/Inputs!$B$2,Inputs!$B$34) -> 0 | C2: =ROUNDUP(C$1/Inputs!$B$2,Inputs!$B$34) -> 1 | D2: =ROUNDUP(D$1/Inputs!$B$2,Inputs!$B$34) -> 1 | E2: =ROUNDUP(E$1/Inputs!$B$2,Inputs!$B$34) -> 1 | F2: =ROUNDUP(F$1/Inputs!$B$2,Inputs!$B$34) -> 1 | G2: =ROUNDUP(G$1/Inputs!$B$2,Inputs!$B$34) -> 1 | H2: =ROUNDUP(H$1/Inputs!$B$2,Inputs!$B$34) -> 1 | I2: =ROUNDUP(I$1/Inputs!$B$2,Inputs!$B$34) -> 1 | ... DR2: =ROUNDUP(DR$1/Inputs!$B$2,Inputs!$B$34) -> 10
A3: Case target before VAT B | B3: =IF(B$1=Inputs!$B$34,Inputs!$B$34,(IF((B$1-Inputs!$B$31)<Inputs!$B$25,Inputs!$B$34,IF((B$1-Inputs!$B$31)<Inputs!$B$26,Inputs!$B$28,IF((B$1-Inputs!$B$31)<Inputs!$B$27,Inputs!$B$29,Streams!$E$15))))*Inputs!$B$30) -> 0 | C3: =IF(C$1=Inputs!$B$34,Inputs!$B$34,(IF((C$1-Inputs!$B$31)<Inputs!$B$25,Inputs!$B$34,IF((C$1-Inputs!$B$31)<Inputs!$B$26,Inputs!$B$28,IF((C$1-Inputs!$B$31)<Inputs!$B$27,Inputs!$B$29,Streams!$E$15))))*Inputs!$B$30) -> 0 | D3: =IF(D$1=Inputs!$B$34,Inputs!$B$34,(IF((D$1-Inputs!$B$31)<Inputs!$B$25,Inputs!$B$34,IF((D$1-Inputs!$B$31)<Inputs!$B$26,Inputs!$B$28,IF((D$1-Inputs!$B$31)<Inputs!$B$27,Inputs!$B$29,Streams!$E$15))))*Inputs!$B$30) -> 0 | E3: =IF(E$1=Inputs!$B$34,Inputs!$B$34,(IF((E$1-Inputs!$B$31)<Inputs!$B$25,Inputs!$B$34,IF((E$1-Inputs!$B$31)<Inputs!$B$26,Inputs!$B$28,IF((E$1-Inputs!$B$31)<Inputs!$B$27,Inputs!$B$29,Streams!$E$15))))*Inputs!$B$30) -> 0 | F3: =IF(F$1=Inputs!$B$34,Inputs!$B$34,(IF((F$1-Inputs!$B$31)<Inputs!$B$25,Inputs!$B$34,IF((F$1-Inputs!$B$31)<Inputs!$B$26,Inputs!$B$28,IF((F$1-Inputs!$B$31)<Inputs!$B$27,Inputs!$B$29,Streams!$E$15))))*Inputs!$B$30) -> 0 | G3: =IF(G$1=Inputs!$B$34,Inputs!$B$34,(IF((G$1-Inputs!$B$31)<Inputs!$B$25,Inputs!$B$34,IF((G$1-Inputs!$B$31)<Inputs!$B$26,Inputs!$B$28,IF((G$1-Inputs!$B$31)<Inputs!$B$27,Inputs!$B$29,Streams!$E$15))))*Inputs!$B$30) -> 0 | H3: =IF(H$1=Inputs!$B$34,Inputs!$B$34,(IF((H$1-Inputs!$B$31)<Inputs!$B$25,Inputs!$B$34,IF((H$1-Inputs!$B$31)<Inputs!$B$26,Inputs!$B$28,IF((H$1-Inputs!$B$31)<Inputs!$B$27,Inputs!$B$29,Streams!$E$15))))*Inputs!$B$30) -> 0 | I3: =IF(I$1=Inputs!$B$34,Inputs!$B$34,(IF((I$1-Inputs!$B$31)<Inputs!$B$25,Inputs!$B$34,IF((I$1-Inputs!$B$31)<Inputs!$B$26,Inputs!$B$28,IF((I$1-Inputs!$B$31)<Inputs!$B$27,Inputs!$B$29,Streams!$E$15))))*Inputs!$B$30) -> 0 | ... DR3: =IF(DR$1=Inputs!$B$34,Inputs!$B$34,(IF((DR$1-Inputs!$B$31)<Inputs!$B$25,Inputs!$B$34,IF((DR$1-Inputs!$B$31)<Inputs!$B$26,Inputs!$B$28,IF((DR$1-Inputs!$B$31)<Inputs!$B$27,Inputs!$B$29,Streams!$E$15))))*Inputs!$B$30) -> 21
A4: Revenue base excluding VAT | B4: =B3/(Inputs!$B$35+Inputs!$B$9*Inputs!$B$10) -> 0 | C4: =C3/(Inputs!$B$35+Inputs!$B$9*Inputs!$B$10) -> 0 | D4: =D3/(Inputs!$B$35+Inputs!$B$9*Inputs!$B$10) -> 0 | E4: =E3/(Inputs!$B$35+Inputs!$B$9*Inputs!$B$10) -> 0 | F4: =F3/(Inputs!$B$35+Inputs!$B$9*Inputs!$B$10) -> 0 | G4: =G3/(Inputs!$B$35+Inputs!$B$9*Inputs!$B$10) -> 0 | H4: =H3/(Inputs!$B$35+Inputs!$B$9*Inputs!$B$10) -> 0 | I4: =I3/(Inputs!$B$35+Inputs!$B$9*Inputs!$B$10) -> 0 | ... DR4: =DR3/(Inputs!$B$35+Inputs!$B$9*Inputs!$B$10) -> 21
A5: VAT excluded from base (informational) | B5: =B3-B4 -> 0 | C5: =C3-C4 -> 0 | D5: =D3-D4 -> 0 | E5: =E3-E4 -> 0 | F5: =F3-F4 -> 0 | G5: =G3-G4 -> 0 | H5: =H3-H4 -> 0 | I5: =I3-I4 -> 0 | ... DR5: =DR3-DR4 -> 0
A6: Pumps revenue | B6: =B4*Streams!$E$2/Streams!$E$15 -> 0 | C6: =C4*Streams!$E$2/Streams!$E$15 -> 0 | D6: =D4*Streams!$E$2/Streams!$E$15 -> 0 | E6: =E4*Streams!$E$2/Streams!$E$15 -> 0 | F6: =F4*Streams!$E$2/Streams!$E$15 -> 0 | G6: =G4*Streams!$E$2/Streams!$E$15 -> 0 | H6: =H4*Streams!$E$2/Streams!$E$15 -> 0 | I6: =I4*Streams!$E$2/Streams!$E$15 -> 0 | ... DR6: =DR4*Streams!$E$2/Streams!$E$15 -> 4.8
A7: Tankers revenue | B7: =B4*Streams!$E$3/Streams!$E$15 -> 0 | C7: =C4*Streams!$E$3/Streams!$E$15 -> 0 | D7: =D4*Streams!$E$3/Streams!$E$15 -> 0 | E7: =E4*Streams!$E$3/Streams!$E$15 -> 0 | F7: =F4*Streams!$E$3/Streams!$E$15 -> 0 | G7: =G4*Streams!$E$3/Streams!$E$15 -> 0 | H7: =H4*Streams!$E$3/Streams!$E$15 -> 0 | I7: =I4*Streams!$E$3/Streams!$E$15 -> 0 | ... DR7: =DR4*Streams!$E$3/Streams!$E$15 -> 1.8
A8: Depots revenue | B8: =B4*Streams!$E$4/Streams!$E$15 -> 0 | C8: =C4*Streams!$E$4/Streams!$E$15 -> 0 | D8: =D4*Streams!$E$4/Streams!$E$15 -> 0 | E8: =E4*Streams!$E$4/Streams!$E$15 -> 0 | F8: =F4*Streams!$E$4/Streams!$E$15 -> 0 | G8: =G4*Streams!$E$4/Streams!$E$15 -> 0 | H8: =H4*Streams!$E$4/Streams!$E$15 -> 0 | I8: =I4*Streams!$E$4/Streams!$E$15 -> 0 | ... DR8: =DR4*Streams!$E$4/Streams!$E$15 -> 0.6
A9: Retail scales revenue | B9: =B4*Streams!$E$5/Streams!$E$15 -> 0 | C9: =C4*Streams!$E$5/Streams!$E$15 -> 0 | D9: =D4*Streams!$E$5/Streams!$E$15 -> 0 | E9: =E4*Streams!$E$5/Streams!$E$15 -> 0 | F9: =F4*Streams!$E$5/Streams!$E$15 -> 0 | G9: =G4*Streams!$E$5/Streams!$E$15 -> 0 | H9: =H4*Streams!$E$5/Streams!$E$15 -> 0 | I9: =I4*Streams!$E$5/Streams!$E$15 -> 0 | ... DR9: =DR4*Streams!$E$5/Streams!$E$15 -> 2.7
A10: Scanners revenue | B10: =B4*Streams!$E$6/Streams!$E$15 -> 0 | C10: =C4*Streams!$E$6/Streams!$E$15 -> 0 | D10: =D4*Streams!$E$6/Streams!$E$15 -> 0 | E10: =E4*Streams!$E$6/Streams!$E$15 -> 0 | F10: =F4*Streams!$E$6/Streams!$E$15 -> 0 | G10: =G4*Streams!$E$6/Streams!$E$15 -> 0 | H10: =H4*Streams!$E$6/Streams!$E$15 -> 0 | I10: =I4*Streams!$E$6/Streams!$E$15 -> 0 | ... DR10: =DR4*Streams!$E$6/Streams!$E$15 -> 0.9
A11: Electricity meters revenue | B11: =B4*Streams!$E$7/Streams!$E$15 -> 0 | C11: =C4*Streams!$E$7/Streams!$E$15 -> 0 | D11: =D4*Streams!$E$7/Streams!$E$15 -> 0 | E11: =E4*Streams!$E$7/Streams!$E$15 -> 0 | F11: =F4*Streams!$E$7/Streams!$E$15 -> 0 | G11: =G4*Streams!$E$7/Streams!$E$15 -> 0 | H11: =H4*Streams!$E$7/Streams!$E$15 -> 0 | I11: =I4*Streams!$E$7/Streams!$E$15 -> 0 | ... DR11: =DR4*Streams!$E$7/Streams!$E$15 -> 3
A12: Telecom billing revenue | B12: =B4*Streams!$E$8/Streams!$E$15 -> 0 | C12: =C4*Streams!$E$8/Streams!$E$15 -> 0 | D12: =D4*Streams!$E$8/Streams!$E$15 -> 0 | E12: =E4*Streams!$E$8/Streams!$E$15 -> 0 | F12: =F4*Streams!$E$8/Streams!$E$15 -> 0 | G12: =G4*Streams!$E$8/Streams!$E$15 -> 0 | H12: =H4*Streams!$E$8/Streams!$E$15 -> 0 | I12: =I4*Streams!$E$8/Streams!$E$15 -> 0 | ... DR12: =DR4*Streams!$E$8/Streams!$E$15 -> 1.5
A13: Banking ICT revenue | B13: =B4*Streams!$E$9/Streams!$E$15 -> 0 | C13: =C4*Streams!$E$9/Streams!$E$15 -> 0 | D13: =D4*Streams!$E$9/Streams!$E$15 -> 0 | E13: =E4*Streams!$E$9/Streams!$E$15 -> 0 | F13: =F4*Streams!$E$9/Streams!$E$15 -> 0 | G13: =G4*Streams!$E$9/Streams!$E$15 -> 0 | H13: =H4*Streams!$E$9/Streams!$E$15 -> 0 | I13: =I4*Streams!$E$9/Streams!$E$15 -> 0 | ... DR13: =DR4*Streams!$E$9/Streams!$E$15 -> 0.9
A14: Manufacturing weighbridges revenue | B14: =B4*Streams!$E$10/Streams!$E$15 -> 0 | C14: =C4*Streams!$E$10/Streams!$E$15 -> 0 | D14: =D4*Streams!$E$10/Streams!$E$15 -> 0 | E14: =E4*Streams!$E$10/Streams!$E$15 -> 0 | F14: =F4*Streams!$E$10/Streams!$E$15 -> 0 | G14: =G4*Streams!$E$10/Streams!$E$15 -> 0 | H14: =H4*Streams!$E$10/Streams!$E$15 -> 0 | I14: =I4*Streams!$E$10/Streams!$E$15 -> 0 | ... DR14: =DR4*Streams!$E$10/Streams!$E$15 -> 1.8
A15: Aviation revenue | B15: =B4*Streams!$E$11/Streams!$E$15 -> 0 | C15: =C4*Streams!$E$11/Streams!$E$15 -> 0 | D15: =D4*Streams!$E$11/Streams!$E$15 -> 0 | E15: =E4*Streams!$E$11/Streams!$E$15 -> 0 | F15: =F4*Streams!$E$11/Streams!$E$15 -> 0 | G15: =G4*Streams!$E$11/Streams!$E$15 -> 0 | H15: =H4*Streams!$E$11/Streams!$E$15 -> 0 | I15: =I4*Streams!$E$11/Streams!$E$15 -> 0 | ... DR15: =DR4*Streams!$E$11/Streams!$E$15 -> 0.6
A16: Marine revenue | B16: =B4*Streams!$E$12/Streams!$E$15 -> 0 | C16: =C4*Streams!$E$12/Streams!$E$15 -> 0 | D16: =D4*Streams!$E$12/Streams!$E$15 -> 0 | E16: =E4*Streams!$E$12/Streams!$E$15 -> 0 | F16: =F4*Streams!$E$12/Streams!$E$15 -> 0 | G16: =G4*Streams!$E$12/Streams!$E$15 -> 0 | H16: =H4*Streams!$E$12/Streams!$E$15 -> 0 | I16: =I4*Streams!$E$12/Streams!$E$15 -> 0 | ... DR16: =DR4*Streams!$E$12/Streams!$E$15 -> 0.6
A17: Licensing revenue | B17: =B4*Streams!$E$13/Streams!$E$15 -> 0 | C17: =C4*Streams!$E$13/Streams!$E$15 -> 0 | D17: =D4*Streams!$E$13/Streams!$E$15 -> 0 | E17: =E4*Streams!$E$13/Streams!$E$15 -> 0 | F17: =F4*Streams!$E$13/Streams!$E$15 -> 0 | G17: =G4*Streams!$E$13/Streams!$E$15 -> 0 | H17: =H4*Streams!$E$13/Streams!$E$15 -> 0 | I17: =I4*Streams!$E$13/Streams!$E$15 -> 0 | ... DR17: =DR4*Streams!$E$13/Streams!$E$15 -> 1.2
A18: Pattern approval revenue | B18: =B4*Streams!$E$14/Streams!$E$15 -> 0 | C18: =C4*Streams!$E$14/Streams!$E$15 -> 0 | D18: =D4*Streams!$E$14/Streams!$E$15 -> 0 | E18: =E4*Streams!$E$14/Streams!$E$15 -> 0 | F18: =F4*Streams!$E$14/Streams!$E$15 -> 0 | G18: =G4*Streams!$E$14/Streams!$E$15 -> 0 | H18: =H4*Streams!$E$14/Streams!$E$15 -> 0 | I18: =I4*Streams!$E$14/Streams!$E$15 -> 0 | ... DR18: =DR4*Streams!$E$14/Streams!$E$15 -> 0.6
A19: Total stream revenue | B19: =SUM(B6:B18) -> 0 | C19: =SUM(C6:C18) -> 0 | D19: =SUM(D6:D18) -> 0 | E19: =SUM(E6:E18) -> 0 | F19: =SUM(F6:F18) -> 0 | G19: =SUM(G6:G18) -> 0 | H19: =SUM(H6:H18) -> 0 | I19: =SUM(I6:I18) -> 0 | ... DR19: =SUM(DR6:DR18) -> 21
A20: AR closing | B20: =B19*Inputs!$B$16/Inputs!$B$18 -> 0 | C20: =C19*Inputs!$B$16/Inputs!$B$18 -> 0 | D20: =D19*Inputs!$B$16/Inputs!$B$18 -> 0 | E20: =E19*Inputs!$B$16/Inputs!$B$18 -> 0 | F20: =F19*Inputs!$B$16/Inputs!$B$18 -> 0 | G20: =G19*Inputs!$B$16/Inputs!$B$18 -> 0 | H20: =H19*Inputs!$B$16/Inputs!$B$18 -> 0 | I20: =I19*Inputs!$B$16/Inputs!$B$18 -> 0 | ... DR20: =DR19*Inputs!$B$16/Inputs!$B$18 -> 0
A21: Change in AR | B21: =B20-Inputs!$B$34 -> 0 | C21: =C20-B20 -> 0 | D21: =D20-C20 -> 0 | E21: =E20-D20 -> 0 | F21: =F20-E20 -> 0 | G21: =G20-F20 -> 0 | H21: =H20-G20 -> 0 | I21: =I20-H20 -> 0 | J21: =J20-I20 -> 0 | ... DR21: =DR20-DQ20 -> 0
A22: Cash receipts | B22: =B19-B21 -> 0 | C22: =C19-C21 -> 0 | D22: =D19-D21 -> 0 | E22: =E19-E21 -> 0 | F22: =F19-F21 -> 0 | G22: =G19-G21 -> 0 | H22: =H19-H21 -> 0 | I22: =I19-I21 -> 0 | ... DR22: =DR19-DR21 -> 21
A23: Government allocation expense / cash paid | B23: =B19*Inputs!$B$4 -> 0 | C23: =C19*Inputs!$B$4 -> 0 | D23: =D19*Inputs!$B$4 -> 0 | E23: =E19*Inputs!$B$4 -> 0 | F23: =F19*Inputs!$B$4 -> 0 | G23: =G19*Inputs!$B$4 -> 0 | H23: =H19*Inputs!$B$4 -> 0 | I23: =I19*Inputs!$B$4 -> 0 | ... DR23: =DR19*Inputs!$B$4 -> 8.4
A24: Investor distribution entitlement | B24: =B22*Inputs!$B$5 -> 0 | C24: =C22*Inputs!$B$5 -> 0 | D24: =D22*Inputs!$B$5 -> 0 | E24: =E22*Inputs!$B$5 -> 0 | F24: =F22*Inputs!$B$5 -> 0 | G24: =G22*Inputs!$B$5 -> 0 | H24: =H22*Inputs!$B$5 -> 0 | I24: =I22*Inputs!$B$5 -> 0 | ... DR24: =DR22*Inputs!$B$5 -> 2.1
A25: CDS legal 50% of receipts (memo) | B25: =B22*Inputs!$B$6 -> 0 | C25: =C22*Inputs!$B$6 -> 0 | D25: =D22*Inputs!$B$6 -> 0 | E25: =E22*Inputs!$B$6 -> 0 | F25: =F22*Inputs!$B$6 -> 0 | G25: =G22*Inputs!$B$6 -> 0 | H25: =H22*Inputs!$B$6 -> 0 | I25: =I22*Inputs!$B$6 -> 0 | ... DR25: =DR22*Inputs!$B$6 -> 10.5
A26: OPEX reserve 20% receipts (memo) | B26: =B22*Inputs!$B$7 -> 0 | C26: =C22*Inputs!$B$7 -> 0 | D26: =D22*Inputs!$B$7 -> 0 | E26: =E22*Inputs!$B$7 -> 0 | F26: =F22*Inputs!$B$7 -> 0 | G26: =G22*Inputs!$B$7 -> 0 | H26: =H22*Inputs!$B$7 -> 0 | I26: =I22*Inputs!$B$7 -> 0 | ... DR26: =DR22*Inputs!$B$7 -> 4.2
A27: CDS distribution 30% receipts | B27: =B22*Inputs!$B$8 -> 0 | C27: =C22*Inputs!$B$8 -> 0 | D27: =D22*Inputs!$B$8 -> 0 | E27: =E22*Inputs!$B$8 -> 0 | F27: =F22*Inputs!$B$8 -> 0 | G27: =G22*Inputs!$B$8 -> 0 | H27: =H22*Inputs!$B$8 -> 0 | I27: =I22*Inputs!$B$8 -> 0 | ... DR27: =DR22*Inputs!$B$8 -> 6.3
A28: Personnel recurring OPEX | B28: =IF(B$1=Inputs!$B$34,Inputs!$B$34,Inputs!$B$12*Inputs!$B$13/Inputs!$B$32) -> 0 | C28: =IF(C$1=Inputs!$B$34,Inputs!$B$34,Inputs!$B$12*Inputs!$B$13/Inputs!$B$32) -> 0.4 | D28: =IF(D$1=Inputs!$B$34,Inputs!$B$34,Inputs!$B$12*Inputs!$B$13/Inputs!$B$32) -> 0.4 | E28: =IF(E$1=Inputs!$B$34,Inputs!$B$34,Inputs!$B$12*Inputs!$B$13/Inputs!$B$32) -> 0.4 | F28: =IF(F$1=Inputs!$B$34,Inputs!$B$34,Inputs!$B$12*Inputs!$B$13/Inputs!$B$32) -> 0.4 | G28: =IF(G$1=Inputs!$B$34,Inputs!$B$34,Inputs!$B$12*Inputs!$B$13/Inputs!$B$32) -> 0.4 | H28: =IF(H$1=Inputs!$B$34,Inputs!$B$34,Inputs!$B$12*Inputs!$B$13/Inputs!$B$32) -> 0.4 | I28: =IF(I$1=Inputs!$B$34,Inputs!$B$34,Inputs!$B$12*Inputs!$B$13/Inputs!$B$32) -> 0.4 | ... DR28: =IF(DR$1=Inputs!$B$34,Inputs!$B$34,Inputs!$B$12*Inputs!$B$13/Inputs!$B$32) -> 0.4
A29: Other fixed recurring OPEX | B29: =IF(B$1=Inputs!$B$34,Inputs!$B$34,Inputs!$B$14) -> 0 | C29: =IF(C$1=Inputs!$B$34,Inputs!$B$34,Inputs!$B$14) -> 0.15 | D29: =IF(D$1=Inputs!$B$34,Inputs!$B$34,Inputs!$B$14) -> 0.15 | E29: =IF(E$1=Inputs!$B$34,Inputs!$B$34,Inputs!$B$14) -> 0.15 | F29: =IF(F$1=Inputs!$B$34,Inputs!$B$34,Inputs!$B$14) -> 0.15 | G29: =IF(G$1=Inputs!$B$34,Inputs!$B$34,Inputs!$B$14) -> 0.15 | H29: =IF(H$1=Inputs!$B$34,Inputs!$B$34,Inputs!$B$14) -> 0.15 | I29: =IF(I$1=Inputs!$B$34,Inputs!$B$34,Inputs!$B$14) -> 0.15 | ... DR29: =IF(DR$1=Inputs!$B$34,Inputs!$B$34,Inputs!$B$14) -> 0.15
A30: Variable recurring OPEX | B30: =B19*Inputs!$B$15 -> 0 | C30: =C19*Inputs!$B$15 -> 0 | D30: =D19*Inputs!$B$15 -> 0 | E30: =E19*Inputs!$B$15 -> 0 | F30: =F19*Inputs!$B$15 -> 0 | G30: =G19*Inputs!$B$15 -> 0 | H30: =H19*Inputs!$B$15 -> 0 | I30: =I19*Inputs!$B$15 -> 0 | ... DR30: =DR19*Inputs!$B$15 -> 1.68
A31: Recurring OPEX total | B31: =SUM(B28:B30) -> 0 | C31: =SUM(C28:C30) -> 0.55 | D31: =SUM(D28:D30) -> 0.55 | E31: =SUM(E28:E30) -> 0.55 | F31: =SUM(F28:F30) -> 0.55 | G31: =SUM(G28:G30) -> 0.55 | H31: =SUM(H28:H30) -> 0.55 | I31: =SUM(I28:I30) -> 0.55 | ... DR31: =SUM(DR28:DR30) -> 2.23
A32: Launch expenses | B32: =IF(AND(B$1>Inputs!$B$34,B$1<=Inputs!$B$19),Funding!$B$8/Inputs!$B$19,Inputs!$B$34) -> 0 | C32: =IF(AND(C$1>Inputs!$B$34,C$1<=Inputs!$B$19),Funding!$B$8/Inputs!$B$19,Inputs!$B$34) -> 0.58333333 | D32: =IF(AND(D$1>Inputs!$B$34,D$1<=Inputs!$B$19),Funding!$B$8/Inputs!$B$19,Inputs!$B$34) -> 0.58333333 | E32: =IF(AND(E$1>Inputs!$B$34,E$1<=Inputs!$B$19),Funding!$B$8/Inputs!$B$19,Inputs!$B$34) -> 0.58333333 | F32: =IF(AND(F$1>Inputs!$B$34,F$1<=Inputs!$B$19),Funding!$B$8/Inputs!$B$19,Inputs!$B$34) -> 0.58333333 | G32: =IF(AND(G$1>Inputs!$B$34,G$1<=Inputs!$B$19),Funding!$B$8/Inputs!$B$19,Inputs!$B$34) -> 0.58333333 | H32: =IF(AND(H$1>Inputs!$B$34,H$1<=Inputs!$B$19),Funding!$B$8/Inputs!$B$19,Inputs!$B$34) -> 0.58333333 | I32: =IF(AND(I$1>Inputs!$B$34,I$1<=Inputs!$B$19),Funding!$B$8/Inputs!$B$19,Inputs!$B$34) -> 0.58333333 | ... DR32: =IF(AND(DR$1>Inputs!$B$34,DR$1<=Inputs!$B$19),Funding!$B$8/Inputs!$B$19,Inputs!$B$34) -> 0
A33: Total actual modeled OPEX | B33: =B31+B32 -> 0 | C33: =C31+C32 -> 1.1333333 | D33: =D31+D32 -> 1.1333333 | E33: =E31+E32 -> 1.1333333 | F33: =F31+F32 -> 1.1333333 | G33: =G31+G32 -> 1.1333333 | H33: =H31+H32 -> 1.1333333 | I33: =I31+I32 -> 1.1333333 | ... DR33: =DR31+DR32 -> 2.23
A34: Reserve less actual OPEX (memo) | B34: =B26-B33 -> 0 | C34: =C26-C33 -> -1.1333333 | D34: =D26-D33 -> -1.1333333 | E34: =E26-E33 -> -1.1333333 | F34: =F26-F33 -> -1.1333333 | G34: =G26-G33 -> -1.1333333 | H34: =H26-H33 -> -1.1333333 | I34: =I26-I33 -> -1.1333333 | ... DR34: =DR26-DR33 -> 1.97
A35: EBITDA after government allocation | B35: =B19-B23-B33 -> 0 | C35: =C19-C23-C33 -> -1.1333333 | D35: =D19-D23-D33 -> -1.1333333 | E35: =E19-E23-E33 -> -1.1333333 | F35: =F19-F23-F33 -> -1.1333333 | G35: =G19-G23-G33 -> -1.1333333 | H35: =H19-H23-H33 -> -1.1333333 | I35: =I19-I23-I33 -> -1.1333333 | ... DR35: =DR19-DR23-DR33 -> 10.37
A36: Initial capex | B36: =IF(AND(B$1>Inputs!$B$34,B$1<=Inputs!$B$19),Funding!$C$7/Inputs!$B$19,Inputs!$B$34) -> 0 | C36: =IF(AND(C$1>Inputs!$B$34,C$1<=Inputs!$B$19),Funding!$C$7/Inputs!$B$19,Inputs!$B$34) -> 3.5833333 | D36: =IF(AND(D$1>Inputs!$B$34,D$1<=Inputs!$B$19),Funding!$C$7/Inputs!$B$19,Inputs!$B$34) -> 3.5833333 | E36: =IF(AND(E$1>Inputs!$B$34,E$1<=Inputs!$B$19),Funding!$C$7/Inputs!$B$19,Inputs!$B$34) -> 3.5833333 | F36: =IF(AND(F$1>Inputs!$B$34,F$1<=Inputs!$B$19),Funding!$C$7/Inputs!$B$19,Inputs!$B$34) -> 3.5833333 | G36: =IF(AND(G$1>Inputs!$B$34,G$1<=Inputs!$B$19),Funding!$C$7/Inputs!$B$19,Inputs!$B$34) -> 3.5833333 | H36: =IF(AND(H$1>Inputs!$B$34,H$1<=Inputs!$B$19),Funding!$C$7/Inputs!$B$19,Inputs!$B$34) -> 3.5833333 | I36: =IF(AND(I$1>Inputs!$B$34,I$1<=Inputs!$B$19),Funding!$C$7/Inputs!$B$19,Inputs!$B$34) -> 3.5833333 | ... DR36: =IF(AND(DR$1>Inputs!$B$34,DR$1<=Inputs!$B$19),Funding!$C$7/Inputs!$B$19,Inputs!$B$34) -> 0
A37: Maintenance capex | B37: =IF(B$1>Inputs!$B$19,B19*Inputs!$B$21,Inputs!$B$34) -> 0 | C37: =IF(C$1>Inputs!$B$19,C19*Inputs!$B$21,Inputs!$B$34) -> 0 | D37: =IF(D$1>Inputs!$B$19,D19*Inputs!$B$21,Inputs!$B$34) -> 0 | E37: =IF(E$1>Inputs!$B$19,E19*Inputs!$B$21,Inputs!$B$34) -> 0 | F37: =IF(F$1>Inputs!$B$19,F19*Inputs!$B$21,Inputs!$B$34) -> 0 | G37: =IF(G$1>Inputs!$B$19,G19*Inputs!$B$21,Inputs!$B$34) -> 0 | H37: =IF(H$1>Inputs!$B$19,H19*Inputs!$B$21,Inputs!$B$34) -> 0 | I37: =IF(I$1>Inputs!$B$19,I19*Inputs!$B$21,Inputs!$B$34) -> 0 | ... DR37: =IF(DR$1>Inputs!$B$19,DR19*Inputs!$B$21,Inputs!$B$34) -> 0.21
A38: Total capex | B38: =B36+B37 -> 0 | C38: =C36+C37 -> 3.5833333 | D38: =D36+D37 -> 3.5833333 | E38: =E36+E37 -> 3.5833333 | F38: =F36+F37 -> 3.5833333 | G38: =G36+G37 -> 3.5833333 | H38: =H36+H37 -> 3.5833333 | I38: =I36+I37 -> 3.5833333 | ... DR38: =DR36+DR37 -> 0.21
A39: Depreciation | B39: =SUM(INDEX($B$38:B38,Inputs!$B$35,MAX(Inputs!$B$35,COLUMN()-Inputs!$B$20)): B38)/Inputs!$B$20 -> 0 | C39: =SUM(INDEX($B$38:C38,Inputs!$B$35,MAX(Inputs!$B$35,COLUMN()-Inputs!$B$20)): C38)/Inputs!$B$20 -> 0.059722222 | D39: =SUM(INDEX($B$38:D38,Inputs!$B$35,MAX(Inputs!$B$35,COLUMN()-Inputs!$B$20)): D38)/Inputs!$B$20 -> 0.11944444 | E39: =SUM(INDEX($B$38:E38,Inputs!$B$35,MAX(Inputs!$B$35,COLUMN()-Inputs!$B$20)): E38)/Inputs!$B$20 -> 0.17916667 | F39: =SUM(INDEX($B$38:F38,Inputs!$B$35,MAX(Inputs!$B$35,COLUMN()-Inputs!$B$20)): F38)/Inputs!$B$20 -> 0.23888889 | G39: =SUM(INDEX($B$38:G38,Inputs!$B$35,MAX(Inputs!$B$35,COLUMN()-Inputs!$B$20)): G38)/Inputs!$B$20 -> 0.29861111 | H39: =SUM(INDEX($B$38:H38,Inputs!$B$35,MAX(Inputs!$B$35,COLUMN()-Inputs!$B$20)): H38)/Inputs!$B$20 -> 0.35833333 | I39: =SUM(INDEX($B$38:I38,Inputs!$B$35,MAX(Inputs!$B$35,COLUMN()-Inputs!$B$20)): I38)/Inputs!$B$20 -> 0.41805556 | ... DR39: =SUM(INDEX($B$38:DR38,Inputs!$B$35,MAX(Inputs!$B$35,COLUMN()-Inputs!$B$20)): DR38)/Inputs!$B$20 -> 0.21
A40: EBIT | B40: =B35-B39 -> 0 | C40: =C35-C39 -> -1.1930556 | D40: =D35-D39 -> -1.2527778 | E40: =E35-E39 -> -1.3125 | F40: =F35-F39 -> -1.3722222 | G40: =G35-G39 -> -1.4319444 | H40: =H35-H39 -> -1.4916667 | I40: =I35-I39 -> -1.5513889 | ... DR40: =DR35-DR39 -> 10.16
A41: Cash tax / tax expense | B41: =MAX(Inputs!$B$34,B40)*Inputs!$B$11 -> 0 | C41: =MAX(Inputs!$B$34,C40)*Inputs!$B$11 -> 0 | D41: =MAX(Inputs!$B$34,D40)*Inputs!$B$11 -> 0 | E41: =MAX(Inputs!$B$34,E40)*Inputs!$B$11 -> 0 | F41: =MAX(Inputs!$B$34,F40)*Inputs!$B$11 -> 0 | G41: =MAX(Inputs!$B$34,G40)*Inputs!$B$11 -> 0 | H41: =MAX(Inputs!$B$34,H40)*Inputs!$B$11 -> 0 | I41: =MAX(Inputs!$B$34,I40)*Inputs!$B$11 -> 0 | ... DR41: =MAX(Inputs!$B$34,DR40)*Inputs!$B$11 -> 3.048
A42: Net income before owner distributions | B42: =B40-B41 -> 0 | C42: =C40-C41 -> -1.1930556 | D42: =D40-D41 -> -1.2527778 | E42: =E40-E41 -> -1.3125 | F42: =F40-F41 -> -1.3722222 | G42: =G40-G41 -> -1.4319444 | H42: =H40-H41 -> -1.4916667 | I42: =I40-I41 -> -1.5513889 | ... DR42: =DR40-DR41 -> 7.112
A43: AP closing | B43: =B31*Inputs!$B$17/Inputs!$B$18 -> 0 | C43: =C31*Inputs!$B$17/Inputs!$B$18 -> 0 | D43: =D31*Inputs!$B$17/Inputs!$B$18 -> 0 | E43: =E31*Inputs!$B$17/Inputs!$B$18 -> 0 | F43: =F31*Inputs!$B$17/Inputs!$B$18 -> 0 | G43: =G31*Inputs!$B$17/Inputs!$B$18 -> 0 | H43: =H31*Inputs!$B$17/Inputs!$B$18 -> 0 | I43: =I31*Inputs!$B$17/Inputs!$B$18 -> 0 | ... DR43: =DR31*Inputs!$B$17/Inputs!$B$18 -> 0
A44: Change in AP | B44: =B43-Inputs!$B$34 -> 0 | C44: =C43-B43 -> 0 | D44: =D43-C43 -> 0 | E44: =E43-D43 -> 0 | F44: =F43-E43 -> 0 | G44: =G43-F43 -> 0 | H44: =H43-G43 -> 0 | I44: =I43-H43 -> 0 | J44: =J43-I43 -> 0 | ... DR44: =DR43-DQ43 -> 0
A45: CFO = NI + DA - change AR + change AP | B45: =B42+B39-B21+B44 -> 0 | C45: =C42+C39-C21+C44 -> -1.1333333 | D45: =D42+D39-D21+D44 -> -1.1333333 | E45: =E42+E39-E21+E44 -> -1.1333333 | F45: =F42+F39-F21+F44 -> -1.1333333 | G45: =G42+G39-G21+G44 -> -1.1333333 | H45: =H42+H39-H21+H44 -> -1.1333333 | I45: =I42+I39-I21+I44 -> -1.1333333 | ... DR45: =DR42+DR39-DR21+DR44 -> 7.322
A46: CFI = capex outflow | B46: =-B38 -> 0 | C46: =-C38 -> -3.5833333 | D46: =-D38 -> -3.5833333 | E46: =-E38 -> -3.5833333 | F46: =-F38 -> -3.5833333 | G46: =-G38 -> -3.5833333 | H46: =-H38 -> -3.5833333 | I46: =-I38 -> -3.5833333 | ... DR46: =-DR38 -> -0.21
A47: Investor capital contributed | B47: =IF(B$1=Inputs!$B$34,Inputs!$B$22,IF(B$1=Inputs!$B$24,Inputs!$B$23,Inputs!$B$34)) -> 25 | C47: =IF(C$1=Inputs!$B$34,Inputs!$B$22,IF(C$1=Inputs!$B$24,Inputs!$B$23,Inputs!$B$34)) -> 0 | D47: =IF(D$1=Inputs!$B$34,Inputs!$B$22,IF(D$1=Inputs!$B$24,Inputs!$B$23,Inputs!$B$34)) -> 0 | E47: =IF(E$1=Inputs!$B$34,Inputs!$B$22,IF(E$1=Inputs!$B$24,Inputs!$B$23,Inputs!$B$34)) -> 0 | F47: =IF(F$1=Inputs!$B$34,Inputs!$B$22,IF(F$1=Inputs!$B$24,Inputs!$B$23,Inputs!$B$34)) -> 0 | G47: =IF(G$1=Inputs!$B$34,Inputs!$B$22,IF(G$1=Inputs!$B$24,Inputs!$B$23,Inputs!$B$34)) -> 0 | H47: =IF(H$1=Inputs!$B$34,Inputs!$B$22,IF(H$1=Inputs!$B$24,Inputs!$B$23,Inputs!$B$34)) -> 0 | I47: =IF(I$1=Inputs!$B$34,Inputs!$B$22,IF(I$1=Inputs!$B$24,Inputs!$B$23,Inputs!$B$34)) -> 0 | ... DR47: =IF(DR$1=Inputs!$B$34,Inputs!$B$22,IF(DR$1=Inputs!$B$24,Inputs!$B$23,Inputs!$B$34)) -> 0
A48: Owner distributions (investor + CDS) | B48: =B24+B27 -> 0 | C48: =C24+C27 -> 0 | D48: =D24+D27 -> 0 | E48: =E24+E27 -> 0 | F48: =F24+F27 -> 0 | G48: =G24+G27 -> 0 | H48: =H24+H27 -> 0 | I48: =I24+I27 -> 0 | ... DR48: =DR24+DR27 -> 8.4
A49: CFF = contributions - owner distributions | B49: =B47-B48 -> 25 | C49: =C47-C48 -> 0 | D49: =D47-D48 -> 0 | E49: =E47-E48 -> 0 | F49: =F47-F48 -> 0 | G49: =G47-G48 -> 0 | H49: =H47-H48 -> 0 | I49: =I47-I48 -> 0 | ... DR49: =DR47-DR48 -> -8.4
A50: Net cash flow | B50: =SUM(B45:B46)+B49 -> 25 | C50: =SUM(C45:C46)+C49 -> -4.7166667 | D50: =SUM(D45:D46)+D49 -> -4.7166667 | E50: =SUM(E45:E46)+E49 -> -4.7166667 | F50: =SUM(F45:F46)+F49 -> -4.7166667 | G50: =SUM(G45:G46)+G49 -> -4.7166667 | H50: =SUM(H45:H46)+H49 -> -4.7166667 | I50: =SUM(I45:I46)+I49 -> -4.7166667 | ... DR50: =SUM(DR45:DR46)+DR49 -> -1.288
A51: Opening unfinanced cash | B51: =Inputs!$B$34 -> 0 | C51: =B52 -> 25 | D51: =C52 -> 20.283333 | E51: =D52 -> 15.566667 | F51: =E52 -> 10.85 | G51: =F52 -> 6.1333333 | H51: =G52 -> 1.4166667 | I51: =H52 -> -3.3 | J51: =I52 -> -8.0166667 | ... DR51: =DQ52 -> -133.6555
A52: Closing unfinanced cash | B52: =B51+B50 -> 25 | C52: =C51+C50 -> 20.283333 | D52: =D51+D50 -> 15.566667 | E52: =E51+E50 -> 10.85 | F52: =F51+F50 -> 6.1333333 | G52: =G51+G50 -> 1.4166667 | H52: =H51+H50 -> -3.3 | I52: =I51+I50 -> -8.0166667 | ... DR52: =DR51+DR50 -> -134.9435
A53: Funding gap at period end | B53: =MAX(Inputs!$B$34,-B52) -> 0 | C53: =MAX(Inputs!$B$34,-C52) -> 0 | D53: =MAX(Inputs!$B$34,-D52) -> 0 | E53: =MAX(Inputs!$B$34,-E52) -> 0 | F53: =MAX(Inputs!$B$34,-F52) -> 0 | G53: =MAX(Inputs!$B$34,-G52) -> 0 | H53: =MAX(Inputs!$B$34,-H52) -> 3.3 | I53: =MAX(Inputs!$B$34,-I52) -> 8.0166667 | ... DR53: =MAX(Inputs!$B$34,-DR52) -> 134.9435
A54: PP&E closing net | B54: =B38-B39 -> 0 | C54: =B54+C38-C39 -> 3.5236111 | D54: =C54+D38-D39 -> 6.9875 | E54: =D54+E38-E39 -> 10.391667 | F54: =E54+F38-F39 -> 13.736111 | G54: =F54+G38-G39 -> 17.020833 | H54: =G54+H38-H39 -> 20.245833 | I54: =H54+I38-I39 -> 23.411111 | J54: =I54+J38-J39 -> 26.516667 | ... DR54: =DQ54+DR38-DR39 -> 6.195
A55: Cumulative contributed capital | B55: =SUM($B47:B47) -> 25 | C55: =SUM($B47:C47) -> 25 | D55: =SUM($B47:D47) -> 25 | E55: =SUM($B47:E47) -> 25 | F55: =SUM($B47:F47) -> 25 | G55: =SUM($B47:G47) -> 25 | H55: =SUM($B47:H47) -> 25 | I55: =SUM($B47:I47) -> 25 | ... DR55: =SUM($B47:DR47) -> 50
A56: Retained earnings after distributions | B56: =B42-B48 -> 0 | C56: =B56+C42-C48 -> -1.1930556 | D56: =C56+D42-D48 -> -2.4458333 | E56: =D56+E42-E48 -> -3.7583333 | F56: =E56+F42-F48 -> -5.1305556 | G56: =F56+G42-G48 -> -6.5625 | H56: =G56+H42-H48 -> -8.0541667 | I56: =H56+I42-I48 -> -9.6055556 | J56: =I56+J42-J48 -> -11.216667 | ... DR56: =DQ56+DR42-DR48 -> -178.7485
A57: Total assets (cash may be unfunded) | B57: =B52+B20+B54 -> 25 | C57: =C52+C20+C54 -> 23.806944 | D57: =D52+D20+D54 -> 22.554167 | E57: =E52+E20+E54 -> 21.241667 | F57: =F52+F20+F54 -> 19.869444 | G57: =G52+G20+G54 -> 18.4375 | H57: =H52+H20+H54 -> 16.945833 | I57: =I52+I20+I54 -> 15.394444 | ... DR57: =DR52+DR20+DR54 -> -128.7485
A58: Total liabilities + equity | B58: =B43+B55+B56 -> 25 | C58: =C43+C55+C56 -> 23.806944 | D58: =D43+D55+D56 -> 22.554167 | E58: =E43+E55+E56 -> 21.241667 | F58: =F43+F55+F56 -> 19.869444 | G58: =G43+G55+G56 -> 18.4375 | H58: =H43+H55+H56 -> 16.945833 | I58: =I43+I55+I56 -> 15.394444 | ... DR58: =DR43+DR55+DR56 -> -128.7485
A59: Balance sheet check | B59: =B57-B58 -> 0 | C59: =C57-C58 -> 0 | D59: =D57-D58 -> 0 | E59: =E57-E58 -> 0 | F59: =F57-F58 -> 0 | G59: =G57-G58 -> 0 | H59: =H57-H58 -> 0 | I59: =I57-I58 -> 0 | ... DR59: =DR57-DR58 -> 7.6738615e-13
A60: Cash roll-forward check | B60: =B52-B51-B50 -> 0 | C60: =C52-C51-C50 -> 0 | D60: =D52-D51-D50 -> 0 | E60: =E52-E51-E50 -> 0 | F60: =F52-F51-F50 -> 0 | G60: =G52-G51-G50 -> 0 | H60: =H52-H51-H50 -> 0 | I60: =I52-I51-I50 -> 0 | ... DR60: =DR52-DR51-DR50 -> -8.8817842e-15
A61: Allocation split check | B61: =B25-B26-B27 -> 0 | C61: =C25-C26-C27 -> 0 | D61: =D25-D26-D27 -> 0 | E61: =E25-E26-E27 -> 0 | F61: =F25-F26-F27 -> 0 | G61: =G25-G26-G27 -> 0 | H61: =H25-H26-H27 -> 0 | I61: =I25-I26-I27 -> 0 | ... DR61: =DR25-DR26-DR27 -> 0
A62: Investor net cash flow | B62: =B24-B47 -> -25 | C62: =C24-C47 -> 0 | D62: =D24-D47 -> 0 | E62: =E24-E47 -> 0 | F62: =F24-F47 -> 0 | G62: =G24-G47 -> 0 | H62: =H24-H47 -> 0 | I62: =I24-I47 -> 0 | ... DR62: =DR24-DR47 -> 2.1
A63: Investor cumulative net cash flow | B63: =SUM($B62:B62) -> -25 | C63: =SUM($B62:C62) -> -25 | D63: =SUM($B62:D62) -> -25 | E63: =SUM($B62:E62) -> -25 | F63: =SUM($B62:F62) -> -25 | G63: =SUM($B62:G62) -> -25 | H63: =SUM($B62:H62) -> -25 | I63: =SUM($B62:I62) -> -25 | ... DR63: =SUM($B62:DR62) -> 179.8
A64: Investor cumulative distributions | B64: =SUM($B24:B24) -> 0 | C64: =SUM($B24:C24) -> 0 | D64: =SUM($B24:D24) -> 0 | E64: =SUM($B24:E24) -> 0 | F64: =SUM($B24:F24) -> 0 | G64: =SUM($B24:G24) -> 0 | H64: =SUM($B24:H24) -> 0 | I64: =SUM($B24:I24) -> 0 | ... DR64: =SUM($B24:DR24) -> 229.8
A65: Gross share source entitlement | B65: =B19*Inputs!$B$5 -> 0 | C65: =C19*Inputs!$B$5 -> 0 | D65: =D19*Inputs!$B$5 -> 0 | E65: =E19*Inputs!$B$5 -> 0 | F65: =F19*Inputs!$B$5 -> 0 | G65: =G19*Inputs!$B$5 -> 0 | H65: =H19*Inputs!$B$5 -> 0 | I65: =I19*Inputs!$B$5 -> 0 | ... DR65: =DR19*Inputs!$B$5 -> 2.1
A66: Revenue stream tie check | B66: =B19-B4 -> 0 | C66: =C19-C4 -> 0 | D66: =D19-D4 -> 0 | E66: =E19-E4 -> 0 | F66: =F19-F4 -> 0 | G66: =G19-G4 -> 0 | H66: =H19-H4 -> 0 | I66: =I19-I4 -> 0 | ... DR66: =DR19-DR4 -> 0
A67: Investor CF after all committed funding reserved | B67: =B64-SUM($B$47:$DR$47) -> -50 | C67: =C64-SUM($B$47:$DR$47) -> -50 | D67: =D64-SUM($B$47:$DR$47) -> -50 | E67: =E64-SUM($B$47:$DR$47) -> -50 | F67: =F64-SUM($B$47:$DR$47) -> -50 | G67: =G64-SUM($B$47:$DR$47) -> -50 | H67: =H64-SUM($B$47:$DR$47) -> -50 | I67: =I64-SUM($B$47:$DR$47) -> -50 | ... DR67: =DR64-SUM($B$47:$DR$47) -> 179.8
A68: Cash receipt negative flag | B68: =IF(B22<-Inputs!$B$33,Inputs!$B$35,Inputs!$B$34) -> 0 | C68: =IF(C22<-Inputs!$B$33,Inputs!$B$35,Inputs!$B$34) -> 0 | D68: =IF(D22<-Inputs!$B$33,Inputs!$B$35,Inputs!$B$34) -> 0 | E68: =IF(E22<-Inputs!$B$33,Inputs!$B$35,Inputs!$B$34) -> 0 | F68: =IF(F22<-Inputs!$B$33,Inputs!$B$35,Inputs!$B$34) -> 0 | G68: =IF(G22<-Inputs!$B$33,Inputs!$B$35,Inputs!$B$34) -> 0 | H68: =IF(H22<-Inputs!$B$33,Inputs!$B$35,Inputs!$B$34) -> 0 | I68: =IF(I22<-Inputs!$B$33,Inputs!$B$35,Inputs!$B$34) -> 0 | ... DR68: =IF(DR22<-Inputs!$B$33,Inputs!$B$35,Inputs!$B$34) -> 0

Sheet Downside annual
A1: Month index | B1: =Inputs!$B$34 -> 0 | C1: =B1+Inputs!$B$35 -> 1 | D1: =C1+Inputs!$B$35 -> 2 | E1: =D1+Inputs!$B$35 -> 3 | F1: =E1+Inputs!$B$35 -> 4 | G1: =F1+Inputs!$B$35 -> 5 | H1: =G1+Inputs!$B$35 -> 6 | I1: =H1+Inputs!$B$35 -> 7 | J1: =I1+Inputs!$B$35 -> 8 | ... L1: =K1+Inputs!$B$35 -> 10
A2: Model year | B2: =B1 -> 0 | C2: =C1 -> 1 | D2: =D1 -> 2 | E2: =E1 -> 3 | F2: =F1 -> 4 | G2: =G1 -> 5 | H2: =H1 -> 6 | I2: =I1 -> 7 | ... L2: =L1 -> 10
A3: Case target before VAT B | B3: =Downside!B3 -> 0 | C3: =SUM(Downside!C3:N3) -> 42 | D3: =SUM(Downside!O3:Z3) -> 240 | E3: =SUM(Downside!AA3:AL3) -> 252 | F3: =SUM(Downside!AM3:AX3) -> 252 | G3: =SUM(Downside!AY3:BJ3) -> 252 | H3: =SUM(Downside!BK3:BV3) -> 252 | I3: =SUM(Downside!BW3:CH3) -> 252 | J3: =SUM(Downside!CI3:CT3) -> 252 | K3: =SUM(Downside!CU3:DF3) -> 252 | L3: =SUM(Downside!DG3:DR3) -> 252
A4: Revenue base excluding VAT | B4: =Downside!B4 -> 0 | C4: =SUM(Downside!C4:N4) -> 42 | D4: =SUM(Downside!O4:Z4) -> 240 | E4: =SUM(Downside!AA4:AL4) -> 252 | F4: =SUM(Downside!AM4:AX4) -> 252 | G4: =SUM(Downside!AY4:BJ4) -> 252 | H4: =SUM(Downside!BK4:BV4) -> 252 | I4: =SUM(Downside!BW4:CH4) -> 252 | J4: =SUM(Downside!CI4:CT4) -> 252 | K4: =SUM(Downside!CU4:DF4) -> 252 | L4: =SUM(Downside!DG4:DR4) -> 252
A5: VAT excluded from base (informational) | B5: =Downside!B5 -> 0 | C5: =SUM(Downside!C5:N5) -> 0 | D5: =SUM(Downside!O5:Z5) -> 0 | E5: =SUM(Downside!AA5:AL5) -> 0 | F5: =SUM(Downside!AM5:AX5) -> 0 | G5: =SUM(Downside!AY5:BJ5) -> 0 | H5: =SUM(Downside!BK5:BV5) -> 0 | I5: =SUM(Downside!BW5:CH5) -> 0 | J5: =SUM(Downside!CI5:CT5) -> 0 | K5: =SUM(Downside!CU5:DF5) -> 0 | L5: =SUM(Downside!DG5:DR5) -> 0
A6: Pumps revenue | B6: =Downside!B6 -> 0 | C6: =SUM(Downside!C6:N6) -> 9.6 | D6: =SUM(Downside!O6:Z6) -> 54.857143 | E6: =SUM(Downside!AA6:AL6) -> 57.6 | F6: =SUM(Downside!AM6:AX6) -> 57.6 | G6: =SUM(Downside!AY6:BJ6) -> 57.6 | H6: =SUM(Downside!BK6:BV6) -> 57.6 | I6: =SUM(Downside!BW6:CH6) -> 57.6 | J6: =SUM(Downside!CI6:CT6) -> 57.6 | K6: =SUM(Downside!CU6:DF6) -> 57.6 | L6: =SUM(Downside!DG6:DR6) -> 57.6
A7: Tankers revenue | B7: =Downside!B7 -> 0 | C7: =SUM(Downside!C7:N7) -> 3.6 | D7: =SUM(Downside!O7:Z7) -> 20.571429 | E7: =SUM(Downside!AA7:AL7) -> 21.6 | F7: =SUM(Downside!AM7:AX7) -> 21.6 | G7: =SUM(Downside!AY7:BJ7) -> 21.6 | H7: =SUM(Downside!BK7:BV7) -> 21.6 | I7: =SUM(Downside!BW7:CH7) -> 21.6 | J7: =SUM(Downside!CI7:CT7) -> 21.6 | K7: =SUM(Downside!CU7:DF7) -> 21.6 | L7: =SUM(Downside!DG7:DR7) -> 21.6
A8: Depots revenue | B8: =Downside!B8 -> 0 | C8: =SUM(Downside!C8:N8) -> 1.2 | D8: =SUM(Downside!O8:Z8) -> 6.8571429 | E8: =SUM(Downside!AA8:AL8) -> 7.2 | F8: =SUM(Downside!AM8:AX8) -> 7.2 | G8: =SUM(Downside!AY8:BJ8) -> 7.2 | H8: =SUM(Downside!BK8:BV8) -> 7.2 | I8: =SUM(Downside!BW8:CH8) -> 7.2 | J8: =SUM(Downside!CI8:CT8) -> 7.2 | K8: =SUM(Downside!CU8:DF8) -> 7.2 | L8: =SUM(Downside!DG8:DR8) -> 7.2
A9: Retail scales revenue | B9: =Downside!B9 -> 0 | C9: =SUM(Downside!C9:N9) -> 5.4 | D9: =SUM(Downside!O9:Z9) -> 30.857143 | E9: =SUM(Downside!AA9:AL9) -> 32.4 | F9: =SUM(Downside!AM9:AX9) -> 32.4 | G9: =SUM(Downside!AY9:BJ9) -> 32.4 | H9: =SUM(Downside!BK9:BV9) -> 32.4 | I9: =SUM(Downside!BW9:CH9) -> 32.4 | J9: =SUM(Downside!CI9:CT9) -> 32.4 | K9: =SUM(Downside!CU9:DF9) -> 32.4 | L9: =SUM(Downside!DG9:DR9) -> 32.4
A10: Scanners revenue | B10: =Downside!B10 -> 0 | C10: =SUM(Downside!C10:N10) -> 1.8 | D10: =SUM(Downside!O10:Z10) -> 10.285714 | E10: =SUM(Downside!AA10:AL10) -> 10.8 | F10: =SUM(Downside!AM10:AX10) -> 10.8 | G10: =SUM(Downside!AY10:BJ10) -> 10.8 | H10: =SUM(Downside!BK10:BV10) -> 10.8 | I10: =SUM(Downside!BW10:CH10) -> 10.8 | J10: =SUM(Downside!CI10:CT10) -> 10.8 | K10: =SUM(Downside!CU10:DF10) -> 10.8 | L10: =SUM(Downside!DG10:DR10) -> 10.8
A11: Electricity meters revenue | B11: =Downside!B11 -> 0 | C11: =SUM(Downside!C11:N11) -> 6 | D11: =SUM(Downside!O11:Z11) -> 34.285714 | E11: =SUM(Downside!AA11:AL11) -> 36 | F11: =SUM(Downside!AM11:AX11) -> 36 | G11: =SUM(Downside!AY11:BJ11) -> 36 | H11: =SUM(Downside!BK11:BV11) -> 36 | I11: =SUM(Downside!BW11:CH11) -> 36 | J11: =SUM(Downside!CI11:CT11) -> 36 | K11: =SUM(Downside!CU11:DF11) -> 36 | L11: =SUM(Downside!DG11:DR11) -> 36
A12: Telecom billing revenue | B12: =Downside!B12 -> 0 | C12: =SUM(Downside!C12:N12) -> 3 | D12: =SUM(Downside!O12:Z12) -> 17.142857 | E12: =SUM(Downside!AA12:AL12) -> 18 | F12: =SUM(Downside!AM12:AX12) -> 18 | G12: =SUM(Downside!AY12:BJ12) -> 18 | H12: =SUM(Downside!BK12:BV12) -> 18 | I12: =SUM(Downside!BW12:CH12) -> 18 | J12: =SUM(Downside!CI12:CT12) -> 18 | K12: =SUM(Downside!CU12:DF12) -> 18 | L12: =SUM(Downside!DG12:DR12) -> 18
A13: Banking ICT revenue | B13: =Downside!B13 -> 0 | C13: =SUM(Downside!C13:N13) -> 1.8 | D13: =SUM(Downside!O13:Z13) -> 10.285714 | E13: =SUM(Downside!AA13:AL13) -> 10.8 | F13: =SUM(Downside!AM13:AX13) -> 10.8 | G13: =SUM(Downside!AY13:BJ13) -> 10.8 | H13: =SUM(Downside!BK13:BV13) -> 10.8 | I13: =SUM(Downside!BW13:CH13) -> 10.8 | J13: =SUM(Downside!CI13:CT13) -> 10.8 | K13: =SUM(Downside!CU13:DF13) -> 10.8 | L13: =SUM(Downside!DG13:DR13) -> 10.8
A14: Manufacturing weighbridges revenue | B14: =Downside!B14 -> 0 | C14: =SUM(Downside!C14:N14) -> 3.6 | D14: =SUM(Downside!O14:Z14) -> 20.571429 | E14: =SUM(Downside!AA14:AL14) -> 21.6 | F14: =SUM(Downside!AM14:AX14) -> 21.6 | G14: =SUM(Downside!AY14:BJ14) -> 21.6 | H14: =SUM(Downside!BK14:BV14) -> 21.6 | I14: =SUM(Downside!BW14:CH14) -> 21.6 | J14: =SUM(Downside!CI14:CT14) -> 21.6 | K14: =SUM(Downside!CU14:DF14) -> 21.6 | L14: =SUM(Downside!DG14:DR14) -> 21.6
... A19: Total stream revenue | B19: =Downside!B19 -> 0 | C19: =SUM(Downside!C19:N19) -> 42 | D19: =SUM(Downside!O19:Z19) -> 240 | E19: =SUM(Downside!AA19:AL19) -> 252 | F19: =SUM(Downside!AM19:AX19) -> 252 | G19: =SUM(Downside!AY19:BJ19) -> 252 | H19: =SUM(Downside!BK19:BV19) -> 252 | I19: =SUM(Downside!BW19:CH19) -> 252 | J19: =SUM(Downside!CI19:CT19) -> 252 | K19: =SUM(Downside!CU19:DF19) -> 252 | L19: =SUM(Downside!DG19:DR19) -> 252
A20: AR closing | B20: =Downside!B20 -> 0 | C20: =Downside!N20 -> 0 | D20: =Downside!Z20 -> 0 | E20: =Downside!AL20 -> 0 | F20: =Downside!AX20 -> 0 | G20: =Downside!BJ20 -> 0 | H20: =Downside!BV20 -> 0 | I20: =Downside!CH20 -> 0 | J20: =Downside!CT20 -> 0 | K20: =Downside!DF20 -> 0 | L20: =Downside!DR20 -> 0
A21: Change in AR | B21: =Downside!B21 -> 0 | C21: =SUM(Downside!C21:N21) -> 0 | D21: =SUM(Downside!O21:Z21) -> 0 | E21: =SUM(Downside!AA21:AL21) -> 0 | F21: =SUM(Downside!AM21:AX21) -> 0 | G21: =SUM(Downside!AY21:BJ21) -> 0 | H21: =SUM(Downside!BK21:BV21) -> 0 | I21: =SUM(Downside!BW21:CH21) -> 0 | J21: =SUM(Downside!CI21:CT21) -> 0 | K21: =SUM(Downside!CU21:DF21) -> 0 | L21: =SUM(Downside!DG21:DR21) -> 0
A22: Cash receipts | B22: =Downside!B22 -> 0 | C22: =SUM(Downside!C22:N22) -> 42 | D22: =SUM(Downside!O22:Z22) -> 240 | E22: =SUM(Downside!AA22:AL22) -> 252 | F22: =SUM(Downside!AM22:AX22) -> 252 | G22: =SUM(Downside!AY22:BJ22) -> 252 | H22: =SUM(Downside!BK22:BV22) -> 252 | I22: =SUM(Downside!BW22:CH22) -> 252 | J22: =SUM(Downside!CI22:CT22) -> 252 | K22: =SUM(Downside!CU22:DF22) -> 252 | L22: =SUM(Downside!DG22:DR22) -> 252
A23: Government allocation expense / cash paid | B23: =Downside!B23 -> 0 | C23: =SUM(Downside!C23:N23) -> 16.8 | D23: =SUM(Downside!O23:Z23) -> 96 | E23: =SUM(Downside!AA23:AL23) -> 100.8 | F23: =SUM(Downside!AM23:AX23) -> 100.8 | G23: =SUM(Downside!AY23:BJ23) -> 100.8 | H23: =SUM(Downside!BK23:BV23) -> 100.8 | I23: =SUM(Downside!BW23:CH23) -> 100.8 | J23: =SUM(Downside!CI23:CT23) -> 100.8 | K23: =SUM(Downside!CU23:DF23) -> 100.8 | L23: =SUM(Downside!DG23:DR23) -> 100.8
A24: Investor distribution entitlement | B24: =Downside!B24 -> 0 | C24: =SUM(Downside!C24:N24) -> 4.2 | D24: =SUM(Downside!O24:Z24) -> 24 | E24: =SUM(Downside!AA24:AL24) -> 25.2 | F24: =SUM(Downside!AM24:AX24) -> 25.2 | G24: =SUM(Downside!AY24:BJ24) -> 25.2 | H24: =SUM(Downside!BK24:BV24) -> 25.2 | I24: =SUM(Downside!BW24:CH24) -> 25.2 | J24: =SUM(Downside!CI24:CT24) -> 25.2 | K24: =SUM(Downside!CU24:DF24) -> 25.2 | L24: =SUM(Downside!DG24:DR24) -> 25.2
A25: CDS legal 50% of receipts (memo) | B25: =Downside!B25 -> 0 | C25: =SUM(Downside!C25:N25) -> 21 | D25: =SUM(Downside!O25:Z25) -> 120 | E25: =SUM(Downside!AA25:AL25) -> 126 | F25: =SUM(Downside!AM25:AX25) -> 126 | G25: =SUM(Downside!AY25:BJ25) -> 126 | H25: =SUM(Downside!BK25:BV25) -> 126 | I25: =SUM(Downside!BW25:CH25) -> 126 | J25: =SUM(Downside!CI25:CT25) -> 126 | K25: =SUM(Downside!CU25:DF25) -> 126 | L25: =SUM(Downside!DG25:DR25) -> 126
A26: OPEX reserve 20% receipts (memo) | B26: =Downside!B26 -> 0 | C26: =SUM(Downside!C26:N26) -> 8.4 | D26: =SUM(Downside!O26:Z26) -> 48 | E26: =SUM(Downside!AA26:AL26) -> 50.4 | F26: =SUM(Downside!AM26:AX26) -> 50.4 | G26: =SUM(Downside!AY26:BJ26) -> 50.4 | H26: =SUM(Downside!BK26:BV26) -> 50.4 | I26: =SUM(Downside!BW26:CH26) -> 50.4 | J26: =SUM(Downside!CI26:CT26) -> 50.4 | K26: =SUM(Downside!CU26:DF26) -> 50.4 | L26: =SUM(Downside!DG26:DR26) -> 50.4
A27: CDS distribution 30% receipts | B27: =Downside!B27 -> 0 | C27: =SUM(Downside!C27:N27) -> 12.6 | D27: =SUM(Downside!O27:Z27) -> 72 | E27: =SUM(Downside!AA27:AL27) -> 75.6 | F27: =SUM(Downside!AM27:AX27) -> 75.6 | G27: =SUM(Downside!AY27:BJ27) -> 75.6 | H27: =SUM(Downside!BK27:BV27) -> 75.6 | I27: =SUM(Downside!BW27:CH27) -> 75.6 | J27: =SUM(Downside!CI27:CT27) -> 75.6 | K27: =SUM(Downside!CU27:DF27) -> 75.6 | L27: =SUM(Downside!DG27:DR27) -> 75.6
A28: Personnel recurring OPEX | B28: =Downside!B28 -> 0 | C28: =SUM(Downside!C28:N28) -> 4.8 | D28: =SUM(Downside!O28:Z28) -> 4.8 | E28: =SUM(Downside!AA28:AL28) -> 4.8 | F28: =SUM(Downside!AM28:AX28) -> 4.8 | G28: =SUM(Downside!AY28:BJ28) -> 4.8 | H28: =SUM(Downside!BK28:BV28) -> 4.8 | I28: =SUM(Downside!BW28:CH28) -> 4.8 | J28: =SUM(Downside!CI28:CT28) -> 4.8 | K28: =SUM(Downside!CU28:DF28) -> 4.8 | L28: =SUM(Downside!DG28:DR28) -> 4.8
A29: Other fixed recurring OPEX | B29: =Downside!B29 -> 0 | C29: =SUM(Downside!C29:N29) -> 1.8 | D29: =SUM(Downside!O29:Z29) -> 1.8 | E29: =SUM(Downside!AA29:AL29) -> 1.8 | F29: =SUM(Downside!AM29:AX29) -> 1.8 | G29: =SUM(Downside!AY29:BJ29) -> 1.8 | H29: =SUM(Downside!BK29:BV29) -> 1.8 | I29: =SUM(Downside!BW29:CH29) -> 1.8 | J29: =SUM(Downside!CI29:CT29) -> 1.8 | K29: =SUM(Downside!CU29:DF29) -> 1.8 | L29: =SUM(Downside!DG29:DR29) -> 1.8
A30: Variable recurring OPEX | B30: =Downside!B30 -> 0 | C30: =SUM(Downside!C30:N30) -> 3.36 | D30: =SUM(Downside!O30:Z30) -> 19.2 | E30: =SUM(Downside!AA30:AL30) -> 20.16 | F30: =SUM(Downside!AM30:AX30) -> 20.16 | G30: =SUM(Downside!AY30:BJ30) -> 20.16 | H30: =SUM(Downside!BK30:BV30) -> 20.16 | I30: =SUM(Downside!BW30:CH30) -> 20.16 | J30: =SUM(Downside!CI30:CT30) -> 20.16 | K30: =SUM(Downside!CU30:DF30) -> 20.16 | L30: =SUM(Downside!DG30:DR30) -> 20.16
A31: Recurring OPEX total | B31: =Downside!B31 -> 0 | C31: =SUM(Downside!C31:N31) -> 9.96 | D31: =SUM(Downside!O31:Z31) -> 25.8 | E31: =SUM(Downside!AA31:AL31) -> 26.76 | F31: =SUM(Downside!AM31:AX31) -> 26.76 | G31: =SUM(Downside!AY31:BJ31) -> 26.76 | H31: =SUM(Downside!BK31:BV31) -> 26.76 | I31: =SUM(Downside!BW31:CH31) -> 26.76 | J31: =SUM(Downside!CI31:CT31) -> 26.76 | K31: =SUM(Downside!CU31:DF31) -> 26.76 | L31: =SUM(Downside!DG31:DR31) -> 26.76
A32: Launch expenses | B32: =Downside!B32 -> 0 | C32: =SUM(Downside!C32:N32) -> 7 | D32: =SUM(Downside!O32:Z32) -> 0 | E32: =SUM(Downside!AA32:AL32) -> 0 | F32: =SUM(Downside!AM32:AX32) -> 0 | G32: =SUM(Downside!AY32:BJ32) -> 0 | H32: =SUM(Downside!BK32:BV32) -> 0 | I32: =SUM(Downside!BW32:CH32) -> 0 | J32: =SUM(Downside!CI32:CT32) -> 0 | K32: =SUM(Downside!CU32:DF32) -> 0 | L32: =SUM(Downside!DG32:DR32) -> 0
... A42: Net income before owner distributions | B42: =Downside!B42 -> 0 | C42: =SUM(Downside!C42:N42) -> -0.85783333 | D42: =SUM(Downside!O42:Z42) -> 76.545 | E42: =SUM(Downside!AA42:AL42) -> 80.5609 | F42: =SUM(Downside!AM42:AX42) -> 80.2081 | G42: =SUM(Downside!AY42:BJ42) -> 79.8553 | H42: =SUM(Downside!BK42:BV42) -> 82.763333 | I42: =SUM(Downside!BW42:CH42) -> 85.3447 | J42: =SUM(Downside!CI42:CT42) -> 85.344 | K42: =SUM(Downside!CU42:DF42) -> 85.344 | L42: =SUM(Downside!DG42:DR42) -> 85.344
A43: AP closing | B43: =Downside!B43 -> 0 | C43: =Downside!N43 -> 0 | D43: =Downside!Z43 -> 0 | E43: =Downside!AL43 -> 0 | F43: =Downside!AX43 -> 0 | G43: =Downside!BJ43 -> 0 | H43: =Downside!BV43 -> 0 | I43: =Downside!CH43 -> 0 | J43: =Downside!CT43 -> 0 | K43: =Downside!DF43 -> 0 | L43: =Downside!DR43 -> 0
A44: Change in AP | B44: =Downside!B44 -> 0 | C44: =SUM(Downside!C44:N44) -> 0 | D44: =SUM(Downside!O44:Z44) -> 0 | E44: =SUM(Downside!AA44:AL44) -> 0 | F44: =SUM(Downside!AM44:AX44) -> 0 | G44: =SUM(Downside!AY44:BJ44) -> 0 | H44: =SUM(Downside!BK44:BV44) -> 0 | I44: =SUM(Downside!BW44:CH44) -> 0 | J44: =SUM(Downside!CI44:CT44) -> 0 | K44: =SUM(Downside!CU44:DF44) -> 0 | L44: =SUM(Downside!DG44:DR44) -> 0
A45: CFO = NI + DA - change AR + change AP | B45: =Downside!B45 -> 0 | C45: =SUM(Downside!C45:N45) -> 3.8005 | D45: =SUM(Downside!O45:Z45) -> 85.395 | E45: =SUM(Downside!AA45:AL45) -> 89.9139 | F45: =SUM(Downside!AM45:AX45) -> 90.0651 | G45: =SUM(Downside!AY45:BJ45) -> 90.2163 | H45: =SUM(Downside!BK45:BV45) -> 88.97 | I45: =SUM(Downside!BW45:CH45) -> 87.8637 | J45: =SUM(Downside!CI45:CT45) -> 87.864 | K45: =SUM(Downside!CU45:DF45) -> 87.864 | L45: =SUM(Downside!DG45:DR45) -> 87.864
A46: CFI = capex outflow | B46: =Downside!B46 -> 0 | C46: =SUM(Downside!C46:N46) -> -43 | D46: =SUM(Downside!O46:Z46) -> -2.4 | E46: =SUM(Downside!AA46:AL46) -> -2.52 | F46: =SUM(Downside!AM46:AX46) -> -2.52 | G46: =SUM(Downside!AY46:BJ46) -> -2.52 | H46: =SUM(Downside!BK46:BV46) -> -2.52 | I46: =SUM(Downside!BW46:CH46) -> -2.52 | J46: =SUM(Downside!CI46:CT46) -> -2.52 | K46: =SUM(Downside!CU46:DF46) -> -2.52 | L46: =SUM(Downside!DG46:DR46) -> -2.52
A47: Investor capital contributed | B47: =Downside!B47 -> 25 | C47: =SUM(Downside!C47:N47) -> 25 | D47: =SUM(Downside!O47:Z47) -> 0 | E47: =SUM(Downside!AA47:AL47) -> 0 | F47: =SUM(Downside!AM47:AX47) -> 0 | G47: =SUM(Downside!AY47:BJ47) -> 0 | H47: =SUM(Downside!BK47:BV47) -> 0 | I47: =SUM(Downside!BW47:CH47) -> 0 | J47: =SUM(Downside!CI47:CT47) -> 0 | K47: =SUM(Downside!CU47:DF47) -> 0 | L47: =SUM(Downside!DG47:DR47) -> 0
A48: Owner distributions (investor + CDS) | B48: =Downside!B48 -> 0 | C48: =SUM(Downside!C48:N48) -> 16.8 | D48: =SUM(Downside!O48:Z48) -> 96 | E48: =SUM(Downside!AA48:AL48) -> 100.8 | F48: =SUM(Downside!AM48:AX48) -> 100.8 | G48: =SUM(Downside!AY48:BJ48) -> 100.8 | H48: =SUM(Downside!BK48:BV48) -> 100.8 | I48: =SUM(Downside!BW48:CH48) -> 100.8 | J48: =SUM(Downside!CI48:CT48) -> 100.8 | K48: =SUM(Downside!CU48:DF48) -> 100.8 | L48: =SUM(Downside!DG48:DR48) -> 100.8
A49: CFF = contributions - owner distributions | B49: =Downside!B49 -> 25 | C49: =SUM(Downside!C49:N49) -> 8.2 | D49: =SUM(Downside!O49:Z49) -> -96 | E49: =SUM(Downside!AA49:AL49) -> -100.8 | F49: =SUM(Downside!AM49:AX49) -> -100.8 | G49: =SUM(Downside!AY49:BJ49) -> -100.8 | H49: =SUM(Downside!BK49:BV49) -> -100.8 | I49: =SUM(Downside!BW49:CH49) -> -100.8 | J49: =SUM(Downside!CI49:CT49) -> -100.8 | K49: =SUM(Downside!CU49:DF49) -> -100.8 | L49: =SUM(Downside!DG49:DR49) -> -100.8
A50: Net cash flow | B50: =Downside!B50 -> 25 | C50: =SUM(Downside!C50:N50) -> -30.9995 | D50: =SUM(Downside!O50:Z50) -> -13.005 | E50: =SUM(Downside!AA50:AL50) -> -13.4061 | F50: =SUM(Downside!AM50:AX50) -> -13.2549 | G50: =SUM(Downside!AY50:BJ50) -> -13.1037 | H50: =SUM(Downside!BK50:BV50) -> -14.35 | I50: =SUM(Downside!BW50:CH50) -> -15.4563 | J50: =SUM(Downside!CI50:CT50) -> -15.456 | K50: =SUM(Downside!CU50:DF50) -> -15.456 | L50: =SUM(Downside!DG50:DR50) -> -15.456
A51: Opening unfinanced cash | B51: =Downside!B51 -> 0 | C51: =Downside!C51 -> 25 | D51: =Downside!O51 -> -5.9995 | E51: =Downside!AA51 -> -19.0045 | F51: =Downside!AM51 -> -32.4106 | G51: =Downside!AY51 -> -45.6655 | H51: =Downside!BK51 -> -58.7692 | I51: =Downside!BW51 -> -73.1192 | J51: =Downside!CI51 -> -88.5755 | K51: =Downside!CU51 -> -104.0315 | L51: =Downside!DG51 -> -119.4875
A52: Closing unfinanced cash | B52: =Downside!B52 -> 25 | C52: =Downside!N52 -> -5.9995 | D52: =Downside!Z52 -> -19.0045 | E52: =Downside!AL52 -> -32.4106 | F52: =Downside!AX52 -> -45.6655 | G52: =Downside!BJ52 -> -58.7692 | H52: =Downside!BV52 -> -73.1192 | I52: =Downside!CH52 -> -88.5755 | J52: =Downside!CT52 -> -104.0315 | K52: =Downside!DF52 -> -119.4875 | L52: =Downside!DR52 -> -134.9435
A53: Funding gap at period end | B53: =Downside!B53 -> 0 | C53: =Downside!N53 -> 5.9995 | D53: =Downside!Z53 -> 19.0045 | E53: =Downside!AL53 -> 32.4106 | F53: =Downside!AX53 -> 45.6655 | G53: =Downside!BJ53 -> 58.7692 | H53: =Downside!BV53 -> 73.1192 | I53: =Downside!CH53 -> 88.5755 | J53: =Downside!CT53 -> 104.0315 | K53: =Downside!DF53 -> 119.4875 | L53: =Downside!DR53 -> 134.9435
A54: PP&E closing net | B54: =Downside!B54 -> 0 | C54: =Downside!N54 -> 38.341667 | D54: =Downside!Z54 -> 31.891667 | E54: =Downside!AL54 -> 25.058667 | F54: =Downside!AX54 -> 17.721667 | G54: =Downside!BJ54 -> 9.8806667 | H54: =Downside!BV54 -> 6.194 | I54: =Downside!CH54 -> 6.195 | J54: =Downside!CT54 -> 6.195 | K54: =Downside!DF54 -> 6.195 | L54: =Downside!DR54 -> 6.195
A55: Cumulative contributed capital | B55: =Downside!B55 -> 25 | C55: =Downside!N55 -> 50 | D55: =Downside!Z55 -> 50 | E55: =Downside!AL55 -> 50 | F55: =Downside!AX55 -> 50 | G55: =Downside!BJ55 -> 50 | H55: =Downside!BV55 -> 50 | I55: =Downside!CH55 -> 50 | J55: =Downside!CT55 -> 50 | K55: =Downside!DF55 -> 50 | L55: =Downside!DR55 -> 50
A56: Retained earnings after distributions | B56: =Downside!B56 -> 0 | C56: =Downside!N56 -> -17.657833 | D56: =Downside!Z56 -> -37.112833 | E56: =Downside!AL56 -> -57.351933 | F56: =Downside!AX56 -> -77.943833 | G56: =Downside!BJ56 -> -98.888533 | H56: =Downside!BV56 -> -116.9252 | I56: =Downside!CH56 -> -132.3805 | J56: =Downside!CT56 -> -147.8365 | K56: =Downside!DF56 -> -163.2925 | L56: =Downside!DR56 -> -178.7485
A57: Total assets (cash may be unfunded) | B57: =Downside!B57 -> 25 | C57: =Downside!N57 -> 32.342167 | D57: =Downside!Z57 -> 12.887167 | E57: =Downside!AL57 -> -7.3519333 | F57: =Downside!AX57 -> -27.943833 | G57: =Downside!BJ57 -> -48.888533 | H57: =Downside!BV57 -> -66.9252 | I57: =Downside!CH57 -> -82.3805 | J57: =Downside!CT57 -> -97.8365 | K57: =Downside!DF57 -> -113.2925 | L57: =Downside!DR57 -> -128.7485
A58: Total liabilities + equity | B58: =Downside!B58 -> 25 | C58: =Downside!N58 -> 32.342167 | D58: =Downside!Z58 -> 12.887167 | E58: =Downside!AL58 -> -7.3519333 | F58: =Downside!AX58 -> -27.943833 | G58: =Downside!BJ58 -> -48.888533 | H58: =Downside!BV58 -> -66.9252 | I58: =Downside!CH58 -> -82.3805 | J58: =Downside!CT58 -> -97.8365 | K58: =Downside!DF58 -> -113.2925 | L58: =Downside!DR58 -> -128.7485
A59: Balance sheet check | B59: =Downside!B59 -> 0 | C59: =SUM(Downside!C59:N59) -> 0 | D59: =SUM(Downside!O59:Z59) -> 0 | E59: =SUM(Downside!AA59:AL59) -> -3.5527137e-15 | F59: =SUM(Downside!AM59:AX59) -> 0 | G59: =SUM(Downside!AY59:BJ59) -> 0 | H59: =SUM(Downside!BK59:BV59) -> 0 | I59: =SUM(Downside!BW59:CH59) -> 8.9528385e-13 | J59: =SUM(Downside!CI59:CT59) -> 4.8601123e-12 | K59: =SUM(Downside!CU59:DF59) -> 6.9064754e-12 | L59: =SUM(Downside!DG59:DR59) -> 8.7538865e-12
A60: Cash roll-forward check | B60: =Downside!B60 -> 0 | C60: =SUM(Downside!C60:N60) -> 0 | D60: =SUM(Downside!O60:Z60) -> 0 | E60: =SUM(Downside!AA60:AL60) -> 0 | F60: =SUM(Downside!AM60:AX60) -> 0 | G60: =SUM(Downside!AY60:BJ60) -> 0 | H60: =SUM(Downside!BK60:BV60) -> 1.1546319e-14 | I60: =SUM(Downside!BW60:CH60) -> 5.2402527e-14 | J60: =SUM(Downside!CI60:CT60) -> 6.3948846e-14 | K60: =SUM(Downside!CU60:DF60) -> 6.3948846e-14 | L60: =SUM(Downside!DG60:DR60) -> -7.1054274e-15
A61: Allocation split check | B61: =Downside!B61 -> 0 | C61: =SUM(Downside!C61:N61) -> 0 | D61: =SUM(Downside!O61:Z61) -> 0 | E61: =SUM(Downside!AA61:AL61) -> 0 | F61: =SUM(Downside!AM61:AX61) -> 0 | G61: =SUM(Downside!AY61:BJ61) -> 0 | H61: =SUM(Downside!BK61:BV61) -> 0 | I61: =SUM(Downside!BW61:CH61) -> 0 | J61: =SUM(Downside!CI61:CT61) -> 0 | K61: =SUM(Downside!CU61:DF61) -> 0 | L61: =SUM(Downside!DG61:DR61) -> 0
A62: Investor net cash flow | B62: =Downside!B62 -> -25 | C62: =SUM(Downside!C62:N62) -> -20.8 | D62: =SUM(Downside!O62:Z62) -> 24 | E62: =SUM(Downside!AA62:AL62) -> 25.2 | F62: =SUM(Downside!AM62:AX62) -> 25.2 | G62: =SUM(Downside!AY62:BJ62) -> 25.2 | H62: =SUM(Downside!BK62:BV62) -> 25.2 | I62: =SUM(Downside!BW62:CH62) -> 25.2 | J62: =SUM(Downside!CI62:CT62) -> 25.2 | K62: =SUM(Downside!CU62:DF62) -> 25.2 | L62: =SUM(Downside!DG62:DR62) -> 25.2
A63: Investor cumulative net cash flow | B63: =Downside!B63 -> -25 | C63: =Downside!N63 -> -45.8 | D63: =Downside!Z63 -> -21.8 | E63: =Downside!AL63 -> 3.4 | F63: =Downside!AX63 -> 28.6 | G63: =Downside!BJ63 -> 53.8 | H63: =Downside!BV63 -> 79 | I63: =Downside!CH63 -> 104.2 | J63: =Downside!CT63 -> 129.4 | K63: =Downside!DF63 -> 154.6 | L63: =Downside!DR63 -> 179.8
A64: Investor cumulative distributions | B64: =Downside!B64 -> 0 | C64: =Downside!N64 -> 4.2 | D64: =Downside!Z64 -> 28.2 | E64: =Downside!AL64 -> 53.4 | F64: =Downside!AX64 -> 78.6 | G64: =Downside!BJ64 -> 103.8 | H64: =Downside!BV64 -> 129 | I64: =Downside!CH64 -> 154.2 | J64: =Downside!CT64 -> 179.4 | K64: =Downside!DF64 -> 204.6 | L64: =Downside!DR64 -> 229.8
A65: Gross share source entitlement | B65: =Downside!B65 -> 0 | C65: =SUM(Downside!C65:N65) -> 4.2 | D65: =SUM(Downside!O65:Z65) -> 24 | E65: =SUM(Downside!AA65:AL65) -> 25.2 | F65: =SUM(Downside!AM65:AX65) -> 25.2 | G65: =SUM(Downside!AY65:BJ65) -> 25.2 | H65: =SUM(Downside!BK65:BV65) -> 25.2 | I65: =SUM(Downside!BW65:CH65) -> 25.2 | J65: =SUM(Downside!CI65:CT65) -> 25.2 | K65: =SUM(Downside!CU65:DF65) -> 25.2 | L65: =SUM(Downside!DG65:DR65) -> 25.2
A66: Revenue stream tie check | B66: =Downside!B66 -> 0 | C66: =SUM(Downside!C66:N66) -> 0 | D66: =SUM(Downside!O66:Z66) -> 0 | E66: =SUM(Downside!AA66:AL66) -> 0 | F66: =SUM(Downside!AM66:AX66) -> 0 | G66: =SUM(Downside!AY66:BJ66) -> 0 | H66: =SUM(Downside!BK66:BV66) -> 0 | I66: =SUM(Downside!BW66:CH66) -> 0 | J66: =SUM(Downside!CI66:CT66) -> 0 | K66: =SUM(Downside!CU66:DF66) -> 0 | L66: =SUM(Downside!DG66:DR66) -> 0
A67: Investor CF after all committed funding reserved | B67: =Downside!B67 -> -50 | C67: =Downside!N67 -> -45.8 | D67: =Downside!Z67 -> -21.8 | E67: =Downside!AL67 -> 3.4 | F67: =Downside!AX67 -> 28.6 | G67: =Downside!BJ67 -> 53.8 | H67: =Downside!BV67 -> 79 | I67: =Downside!CH67 -> 104.2 | J67: =Downside!CT67 -> 129.4 | K67: =Downside!DF67 -> 154.6 | L67: =Downside!DR67 -> 179.8
A68: Cash receipt negative flag | B68: =Downside!B68 -> 0 | C68: =SUM(Downside!C68:N68) -> 0 | D68: =SUM(Downside!O68:Z68) -> 0 | E68: =SUM(Downside!AA68:AL68) -> 0 | F68: =SUM(Downside!AM68:AX68) -> 0 | G68: =SUM(Downside!AY68:BJ68) -> 0 | H68: =SUM(Downside!BK68:BV68) -> 0 | I68: =SUM(Downside!BW68:CH68) -> 0 | J68: =SUM(Downside!CI68:CT68) -> 0 | K68: =SUM(Downside!CU68:DF68) -> 0 | L68: =SUM(Downside!DG68:DR68) -> 0

Sheet Returns
A1: Metric | B1: Headline | C1: Ramp | D1: Downside | E1: Interpretation
A2: Total revenue B | B2: =SUM(Headline!B19:DR19) -> 4200 | C2: =SUM(Ramp!B19:DR19) -> 3935 | D2: =SUM(Downside!B19:DR19) -> 2298
A3: Investor contributions B | B3: =SUM(Headline!B47:DR47) -> 50 | C3: =SUM(Ramp!B47:DR47) -> 50 | D3: =SUM(Downside!B47:DR47) -> 50
A4: Investor distributions B | B4: =SUM(Headline!B24:DR24) -> 420 | C4: =SUM(Ramp!B24:DR24) -> 393.5 | D4: =SUM(Downside!B24:DR24) -> 229.8
A5: Net investor gain B | B5: =B4-B3 -> 370 | C5: =C4-C3 -> 343.5 | D5: =D4-D3 -> 179.8
A6: MOIC x | B6: =B4/B3 -> 8.4 | C6: =C4/C3 -> 7.87 | D6: =D4/D3 -> 4.596
A7: Net ROI | B7: =B6-Inputs!$B$35 -> 7.4 | C7: =C6-Inputs!$B$35 -> 6.87 | D7: =D6-Inputs!$B$35 -> 3.596
A8: Monthly IRR | B8: =IFERROR(IRR(Headline!B62:DR62),"N/A") -> 0.069979104 | C8: =IFERROR(IRR(Ramp!B62:DR62),"N/A") -> 0.057569232 | D8: =IFERROR(IRR(Downside!B62:DR62),"N/A") -> N/A
A9: Effective annual IRR from monthly | B9: =IFERROR((Inputs!$B$35+B8)^Inputs!$B$2-Inputs!$B$35,"N/A") -> 1.2516639 | C9: =IFERROR((Inputs!$B$35+C8)^Inputs!$B$2-Inputs!$B$35,"N/A") -> 0.95751765 | D9: =IFERROR((Inputs!$B$35+D8)^Inputs!$B$2-Inputs!$B$35,"N/A") -> N/A | E9: Monthly receipt timing; effective compounded annual rate, not monthly rate ×12
A10: Annual year-end IRR | B10: =IFERROR(IRR('Headline annual'!B62:L62),"N/A") -> 0.83809187 | C10: =IFERROR(IRR('Ramp annual'!B62:L62),"N/A") -> 0.7750935 | D10: =IFERROR(IRR('Downside annual'!B62:L62),"N/A") -> 0.42206886 | E10: Year-end aggregation changes timing; source ~68% is not reproduced
A11: First whole payback month | B11: =IF(COUNTIF(Headline!B63:DR63,">=0")=Inputs!$B$34,"Not reached",COUNTIF(Headline!B63:DR63,"<0")) -> 15 | C11: =IF(COUNTIF(Ramp!B63:DR63,">=0")=Inputs!$B$34,"Not reached",COUNTIF(Ramp!B63:DR63,"<0")) -> 22 | D11: =IF(COUNTIF(Downside!B63:DR63,">=0")=Inputs!$B$34,"Not reached",COUNTIF(Downside!B63:DR63,"<0")) -> 35
A12: Interpolated payback months | B12: =IF(ISNUMBER(B11),B11-Inputs!$B$35-INDEX(Headline!B63:DR63,Inputs!$B$35,B11)/INDEX(Headline!B62:DR62,Inputs!$B$35,B11+Inputs!$B$35),"Not reached") -> 14.285714 | C12: =IF(ISNUMBER(C11),C11-Inputs!$B$35-INDEX(Ramp!B63:DR63,Inputs!$B$35,C11)/INDEX(Ramp!B62:DR62,Inputs!$B$35,C11+Inputs!$B$35),"Not reached") -> 21.857143 | D12: =IF(ISNUMBER(D11),D11-Inputs!$B$35-INDEX(Downside!B63:DR63,Inputs!$B$35,D11)/INDEX(Downside!B62:DR62,Inputs!$B$35,D11+Inputs!$B$35),"Not reached") -> 34.380952 | E12: Linear interpolation within month; entitlement basis, not cash guarantee
A13: Committed-capital payback month | B13: =IF(COUNTIF(Headline!B67:DR67,">=0")=Inputs!$B$34,"Not reached",COUNTIF(Headline!B67:DR67,"<0")) -> 15 | C13: =IF(COUNTIF(Ramp!B67:DR67,">=0")=Inputs!$B$34,"Not reached",COUNTIF(Ramp!B67:DR67,"<0")) -> 22 | D13: =IF(COUNTIF(Downside!B67:DR67,">=0")=Inputs!$B$34,"Not reached",COUNTIF(Downside!B67:DR67,"<0")) -> 35
A14: Peak funding gap B | B14: =MAX(Headline!B53:DR53) -> 211.9575 | C14: =MAX(Ramp!B53:DR53) -> 204.38625 | D14: =MAX(Downside!B53:DR53) -> 134.9435
A15: Minimum project cash B | B15: =MIN(Headline!B52:DR52) -> -211.9575 | C15: =MIN(Ramp!B52:DR52) -> -204.38625 | D15: =MIN(Downside!B52:DR52) -> -134.9435
A16: Year 1 revenue B | B16: ='Headline annual'!C19 -> 420 | C16: ='Ramp annual'!C19 -> 155 | D16: ='Downside annual'!C19 -> 42
A17: Year 1 investor payout B | B17: ='Headline annual'!C24 -> 42 | C17: ='Ramp annual'!C24 -> 15.5 | D17: ='Downside annual'!C24 -> 4.2
A18: 10Y government B | B18: =SUM(Headline!B23:DR23) -> 1680 | C18: =SUM(Ramp!B23:DR23) -> 1574 | D18: =SUM(Downside!B23:DR23) -> 919.2
A19: 10Y CDS distributions B | B19: =SUM(Headline!B27:DR27) -> 1260 | C19: =SUM(Ramp!B27:DR27) -> 1180.5 | D19: =SUM(Downside!B27:DR27) -> 689.4
A20: 10Y actual modeled OPEX B | B20: =SUM(Headline!B33:DR33) -> 409 | C20: =SUM(Ramp!B33:DR33) -> 387.8 | D20: =SUM(Downside!B33:DR33) -> 256.84
A21: 10Y OPEX reserve B | B21: =SUM(Headline!B26:DR26) -> 840 | C21: =SUM(Ramp!B26:DR26) -> 787 | D21: =SUM(Downside!B26:DR26) -> 459.6
A22: 10Y tax B | B22: =SUM(Headline!B41:DR41) -> 612.1575 | C22: =SUM(Ramp!B41:DR41) -> 572.78625 | D22: =SUM(Downside!B41:DR41) -> 322.1435
A23: Max absolute BS check B | B23: =MAX(MAX(Headline!B59:DR59),-MIN(Headline!B59:DR59)) -> 3.5527137e-14 | C23: =MAX(MAX(Ramp!B59:DR59),-MIN(Ramp!B59:DR59)) -> 5.6843419e-14 | D23: =MAX(MAX(Downside!B59:DR59),-MIN(Downside!B59:DR59)) -> 7.6738615e-13
A24: Max cash rollforward check B | B24: =MAX(MAX(Headline!B60:DR60),-MIN(Headline!B60:DR60)) -> 1.4210855e-14 | C24: =MAX(MAX(Ramp!B60:DR60),-MIN(Ramp!B60:DR60)) -> 1.4210855e-14 | D24: =MAX(MAX(Downside!B60:DR60),-MIN(Downside!B60:DR60)) -> 8.8817842e-15
A25: DSCR | B25: N/A — no debt service schedule | C25: N/A — no debt service schedule | D25: N/A — no debt service schedule
A26: Funding feasibility | B26: =IF(B14>Inputs!$B$33,"UNFUNDED GAP — distributions not assured","No modeled cash gap") -> UNFUNDED GAP — distributions not assured | C26: =IF(C14>Inputs!$B$33,"UNFUNDED GAP — distributions not assured","No modeled cash gap") -> UNFUNDED GAP — distributions not assured | D26: =IF(D14>Inputs!$B$33,"UNFUNDED GAP — distributions not assured","No modeled cash gap") -> UNFUNDED GAP — distributions not assured

Sheet Checks
A1: Audit check | B1: Value / status | C1: Expected / meaning
A2: Legal shares | B2: =Inputs!$B$4+Inputs!$B$5+Inputs!$B$6-Inputs!$B$35 -> 0 | C2: 0
A3: CDS reserve + sweep | B3: =Inputs!$B$6-Inputs!$B$7-Inputs!$B$8 -> 0 | C3: 0
A4: Use vs funding | B4: =Funding!B7-Inputs!$B$22-Inputs!$B$23 -> 0 | C4: 0
A5: Bottom-up monthly | B5: =Streams!J15 -> 2.5 | C5: Quantity×fee×frequency; assumptions flagged
A6: Target monthly | B6: =Streams!E15 -> 35 | C6: Source target, NOT validated
A7: Unbridged monthly | B7: =Streams!E18 -> 32.5 | C7: Target less bottom-up; not a forecast bridge
A8: Bottom-up coverage | B8: =Streams!E17 -> 0.071428571 | C8: Not a claim of addressable demand validation
A9: Working capital days supported | B9: =IF(AND(Inputs!$B$16>=Inputs!$B$34,Inputs!$B$16<=Inputs!$B$18,Inputs!$B$17>=Inputs!$B$34,Inputs!$B$17<=Inputs!$B$18),"PASS","FAIL") -> PASS | C9: 0–30 days
A10: Annual revenue tie | B10: =SUM('Ramp annual'!C19:L19)-SUM(Ramp!C19:DR19) -> 0 | C10: 0
A11: Annual cash tie | B11: ='Ramp annual'!L52-Ramp!DR52 -> 0 | C11: 0
A12: Bucket split max absolute | B12: =MAX(MAX(Streams!E21:E27),-MIN(Streams!E21:E27)) -> 0 | C12: 0
A13: Scenario revenue hierarchy | B13: =IF(AND(Returns!B2>Returns!C2,Returns!C2>Returns!D2),"PASS","FAIL") -> PASS | C13: Headline > ramp > downside
A14: Source claimed ROI | B14: =Returns!B6 -> 8.4 | C14: 8.4x gross proceeds; correct net ROI on Returns row7
A15: Guarantee status | B15: NOT VERIFIED | C15: No guarantee cashflows credited
